Workbook
Name age: Inputs!$B$2
Name healthStatus: Inputs!$B$5
Name Kainput_curve: Inputs!$B$10:$AO$10
Name Kinput_inputs: API!$A$3:$D$8
Name sex: Inputs!$B$3
Name smoker: Inputs!$B$4
Name Xinput_curve: Inputs!$B$9:$AO$10
Name Xjinput_inputs: Inputs!$A$2:$B$7
Name Xoutput_monthlyPremium: Output!$B$3
Name Xoutput_outputs: Output!$A$5:$AO$7

Sheet API
B1: Value | C1: Schema | D1: Description
A2: Inputs
A3: age | C3: {"type": "number", "maximum": 85, "minimum": 18, "required": true }
A4: sex | B4: M | C4: {"enum": ["M","F"]}
A5: smoker | B5: FALSE | C5: { "type": "boolean" }
A6: healthStatus | B6: 1 | C6: {"type": "number", "maximum": 3, "minimum": 1}
A7: lastYearOfPolicyAge | C7: {"type": "number", "maximum": 90, "minimum": 25, "required": true}
A8: permanentCoverage | C8: {"type": "number", "minimum": 0}

Sheet Inputs
A2: age | B2: =API!B3 -> 0
A3: sex | B3: =API!B4 -> M
A4: smoker | B4: =IF(API!B5, "Yes", "No") -> No
A5: healthStatus | B5: =API!B6 -> 1
A6: lastYearOfPolicyAge | B6: =API!B7 -> 0
A7: permanentCoverage | B7: =API!B8 -> 0
A9: year | B9: 1 | C9: =B9+1 -> 2 | D9: =C9+1 -> 3 | E9: =D9+1 -> 4 | F9: =E9+1 -> 5 | G9: =F9+1 -> 6 | H9: =G9+1 -> 7 | I9: =H9+1 -> 8 | J9: =I9+1 -> 9 | ... AO9: =AN9+1 -> 40
A10: curve | B10: 842000 | C10: 837000 | D10: 830000 | E10: 821000 | F10: 811000 | G10: 798000 | H10: 784000 | I10: 767000 | J10: 747000 | K10: 725000 | L10: 699000 | M10: 671000 | N10: 639000 | O10: 604000 | P10: 565000 | Q10: 522000 | R10: 475000 | S10: 423000 | T10: 367000 | U10: 305000 | V10: 238000 | W10: 165000 | X10: 86000 | Y10: 0 | Z10: 0 | AA10: 0 | AB10: 0 | AC10: 0 | AD10: 0 | AE10: 0 | AF10: 0 | AG10: 0 | AH10: 0 | AI10: 0 | AJ10: 0 | AK10: 0 | AL10: 0 | AM10: 0 | AN10: 0 | AO10: 0

Sheet Output
A3: Monthly Premium | B3: =Pricing!M23 -> #N/A
A5: key | B5: Year1 | C5: Year2 | D5: Year3 | E5: Year4 | F5: Year5 | G5: Year6 | H5: Year7 | I5: Year8 | J5: Year9 | K5: Year10 | L5: Year11 | M5: Year12 | N5: Year13 | O5: Year14 | P5: Year15 | Q5: Year16 | R5: Year17 | S5: Year18 | T5: Year19 | U5: Year20 | V5: Year21 | W5: Year22 | X5: Year23 | Y5: Year24 | Z5: Year25 | AA5: Year26 | AB5: Year27 | AC5: Year28 | AD5: Year29 | AE5: Year30 | AF5: Year31 | AG5: Year32 | AH5: Year33 | AI5: Year34 | AJ5: Year35 | AK5: Year36 | AL5: Year37 | AM5: Year38 | AN5: Year39 | AO5: Year40
A6: age | B6: =Pricing!B36 -> 0 | C6: =Pricing!C36 -> 1 | D6: =Pricing!D36 -> 2 | E6: =Pricing!E36 -> 3 | F6: =Pricing!F36 -> 4 | G6: =Pricing!G36 -> 5 | H6: =Pricing!H36 -> 6 | I6: =Pricing!I36 -> 7 | ... AO6: =Pricing!AO36 -> 39
A7: curve | B7: =Pricing!B39 -> 842000 | C7: =Pricing!C39 -> 837000 | D7: =Pricing!D39 -> 830000 | E7: =Pricing!E39 -> 821000 | F7: =Pricing!F39 -> 811000 | G7: =Pricing!G39 -> 798000 | H7: =Pricing!H39 -> 784000 | I7: =Pricing!I39 -> 767000 | ... AO7: =Pricing!AO39 -> 0

Sheet Assms
A1: Level prem years requested | B1: =SUM(B4:AO4) -> 23
B2: 1 | C2: =B2+1 -> 2 | D2: =C2+1 -> 3 | E2: =D2+1 -> 4 | F2: =E2+1 -> 5 | G2: =F2+1 -> 6 | H2: =G2+1 -> 7 | I2: =H2+1 -> 8 | J2: =I2+1 -> 9 | ... AO2: =AN2+1 -> 40
A3: Raw benefit amount | B3: =MAX(Inputs!B10-Inputs!$B$7,0) -> 842000 | C3: =MAX(Inputs!C10-Inputs!$B$7,0) -> 837000 | D3: =MAX(Inputs!D10-Inputs!$B$7,0) -> 830000 | E3: =MAX(Inputs!E10-Inputs!$B$7,0) -> 821000 | F3: =MAX(Inputs!F10-Inputs!$B$7,0) -> 811000 | G3: =MAX(Inputs!G10-Inputs!$B$7,0) -> 798000 | H3: =MAX(Inputs!H10-Inputs!$B$7,0) -> 784000 | I3: =MAX(Inputs!I10-Inputs!$B$7,0) -> 767000 | ... AO3: =MAX(Inputs!AO10-Inputs!$B$7,0) -> 0
A4: Years requested | B4: =IF(B3>0,1,0) -> 1 | C4: =IF(C3>0,1,0) -> 1 | D4: =IF(D3>0,1,0) -> 1 | E4: =IF(E3>0,1,0) -> 1 | F4: =IF(F3>0,1,0) -> 1 | G4: =IF(G3>0,1,0) -> 1 | H4: =IF(H3>0,1,0) -> 1 | I4: =IF(I3>0,1,0) -> 1 | ... AO4: =IF(AO3>0,1,0) -> 0
A5: Adjust once zero | B5: =B3 -> 842000 | C5: =IF(B5=0,0,C3) -> 837000 | D5: =IF(C5=0,0,D3) -> 830000 | E5: =IF(D5=0,0,E3) -> 821000 | F5: =IF(E5=0,0,F3) -> 811000 | G5: =IF(F5=0,0,G3) -> 798000 | H5: =IF(G5=0,0,H3) -> 784000 | I5: =IF(H5=0,0,I3) -> 767000 | J5: =IF(I5=0,0,J3) -> 747000 | ... AO5: =IF(AN5=0,0,AO3) -> 0
A6: Final benefit amount | B6: =IF(B2<=$B$1,B5,0) -> 842000 | C6: =IF(C2<=$B$1,C5,0) -> 837000 | D6: =IF(D2<=$B$1,D5,0) -> 830000 | E6: =IF(E2<=$B$1,E5,0) -> 821000 | F6: =IF(F2<=$B$1,F5,0) -> 811000 | G6: =IF(G2<=$B$1,G5,0) -> 798000 | H6: =IF(H2<=$B$1,H5,0) -> 784000 | I6: =IF(I2<=$B$1,I5,0) -> 767000 | ... AO6: =IF(AO2<=$B$1,AO5,0) -> 0
A7: Indicator of year active | B7: =IF(B5>0,1,"") -> 1 | C7: =IF(C5>0,1,"") -> 1 | D7: =IF(D5>0,1,"") -> 1 | E7: =IF(E5>0,1,"") -> 1 | F7: =IF(F5>0,1,"") -> 1 | G7: =IF(G5>0,1,"") -> 1 | H7: =IF(H5>0,1,"") -> 1 | I7: =IF(I5>0,1,"") -> 1 | ... AO7: =IF(AO5>0,1,"")
A8: Total number years | B8: =SUM(B7:AO7) -> 23
A9: Change since issue: | B9: 0 | C9: =IF(C6="","",IF(C6=0,0,C6/$B$6-1)) -> -0.0059382423 | D9: =IF(D6="","",IF(D6=0,0,D6/$B$6-1)) -> -0.014251781 | E9: =IF(E6="","",IF(E6=0,0,E6/$B$6-1)) -> -0.024940618 | F9: =IF(F6="","",IF(F6=0,0,F6/$B$6-1)) -> -0.036817102 | G9: =IF(G6="","",IF(G6=0,0,G6/$B$6-1)) -> -0.052256532 | H9: =IF(H6="","",IF(H6=0,0,H6/$B$6-1)) -> -0.06888361 | I9: =IF(I6="","",IF(I6=0,0,I6/$B$6-1)) -> -0.089073634 | J9: =IF(J6="","",IF(J6=0,0,J6/$B$6-1)) -> -0.1128266 | ... AO9: =IF(AO6="","",IF(AO6=0,0,AO6/$B$6-1)) -> 0
A11: Expenses and commissions | M11: Unitized Premium Increase | N11: Total Lapse Rate | R11: Issue Age | S11: Margin level | T11: Margin custom
A12: First year marketing & sales costs | C12: 1.7 | E12: Automated UW slippage | I12: Investment yield | K12: 0.06 | M12: 0 | N12: 0 | R12: 0 | S12: 0.3 | T12: 0.2
A13: kmodo license fee | C13: =C26-C27 -> 0.08 | E13: Max age | F13: FA limit | G13: Mort load | I13: Corporate tax rate | K13: 0.28 | M13: =M14-0.025 -> 1 | N13: 0 | R13: 25 | S13: 0.3 | T13: 0.2
A14: Total FY | C14: =C12+C13 -> 1.78 | E14: 50 | F14: 2000000 | G14: 0.06 | I14: Discount rate for prem est: | K14: =K12 -> 0.06 | M14: 1.025 | N14: 0.020634286 | R14: 30 | S14: 0.15 | T14: 0.22
E15: 60 | F15: 1000000 | G15: 0.06 | M15: 1.05 | N15: 0.041268571 | P15: Example: | R15: 35 | S15: 0.1 | T15: 0.13
A16: Premium tax | C16: 0.02 | E16: Applicable mortality load | G16: =IF(age<=E14,IF(Assms!C37<=F14,Assms!G14,0),IF(age<=E15,IF(Assms!C37<=F15,G15,0))) -> 0.06 | I16: Targeted profit margin | K16: 0.06 | M16: 1.075 | N16: 0.061902857 | R16: 40 | S16: 0.11 | T16: 0.13
A17: Commissions | C17: 0.02 | M17: 1.1 | N17: 0.082537143 | P17: Face (t-1) | Q17: 1000000 | R17: 45 | S17: 0.12 | T17: 0.13
A18: kmodo license fee | C18: =C27 -> 0.02 | I18: Margin gross up factor | K18: =IF(G19="Yes",VLOOKUP(C33,R12:T22,2),VLOOKUP(C33,R12:T22,3)) -> 0.2 | M18: 1.125 | N18: 0.10317143 | P18: Face (t) | Q18: 900000 | R18: 50 | S18: 0.15 | T18: 0.13
A19: Expenses as % premium (all years) | C19: =SUM(C16:C18) -> 0.06 | I19: (initial guess before iteration) | M19: 1.15 | N19: 0.12380571 | R19: 55 | S19: 0.16 | T19: 0.16
M20: 1.175 | N20: 0.14444 | P20: Unitied P Incr | Q20: =IF(Q3=0,0,ROUND(Q17 / Q18 * 40,0)/40) -> 1.1 | R20: 60 | S20: 0.16 | T20: 0.16
A21: Per policy issue expenses | C21: =VLOOKUP(C33,A41:B50,2) -> 75 | I21: DMD Effectiveness factor: | K21: 0.5 | M21: 1.2 | N21: 0.14444 | P21: Tot Lapse rate | Q21: =VLOOKUP(Q20,Assms!$M$13:$N$173,2) -> 0.082537143 | R21: 65 | S21: 0.16 | T21: 0.16
A22: Per policy administrative expenses | C22: 75 | F22: Mortality | G22: Lapse | M22: 1.225 | N22: 0.14444 | R22: 100 | S22: 0.16 | T22: 0.16
A23: Annual inflation rate | C23: 0.02 | E23: Super preferred NT | F23: 1 | G23: 1 | I23: Statutory reserving Lx margin | K23: 0.5 | M23: 1.25 | N23: 0.162495
E24: Preferred NT | F24: 2 | G24: 2 | M24: 1.275 | N24: 0.162495
A25: kmodo license fee | C25: Applicable? | E25: Standard Plus NT | F25: 3 | G25: 3 | I25: How RBC factor is applied: | K25: RBC factors: | M25: 1.3 | N25: 0.162495
A26: Year 1 | B26: 0.1 | C26: =IF($B$28=0,0,B26) -> 0.1 | E26: Standard NT | F26: 4 | G26: 3 | I26: Statutory reserve | K26: 0.02 | M26: 1.325 | N26: 0.162495
A27: Year 2-20 | B27: 0.02 | C27: =IF($B$28=0,0,B27) -> 0.02 | E27: Preferred Tobacco | F27: 5 | G27: 4 | I27: Death benefit | K27: 0.002 | M27: 1.35 | N27: 0.18055
A28: Std Dev FA | B28: =_xlfn.STDEV.P(B9:AO9) -> 0.25082705 | E28: Standard Tobacco | F28: 6 | G28: 4 | I28: Gross premium | K28: 0.08 | M28: 1.375 | N28: 0.18055
A29: (if std dev = 0, level FA therefore no license fee) | I29: Only for IRR calc; does not affect prem quote | M29: 1.4 | N29: 0.18055
E30: Face amt | F30: Lx Code | G30: Qx code | M30: 1.425 | N30: 0.18055
A31: Non-commissionable policy fee | C31: 75 | E31: 0 | F31: 1 | G31: 1 | I31: Mortality improvement/year | K31: 0.01 | M31: 1.45 | N31: 0.198605
E32: 250000 | F32: 2 | G32: 2 | M32: 1.475 | N32: 0.198605
A33: Issue age: | C33: =age -> 0 | E33: 500000 | F33: 3 | G33: 2 | M33: 1.5 | N33: 0.198605
A34: Term length | C34: =B8 -> 23 | E34: 1000000 | F34: 4 | G34: 3 | M34: 1.525 | N34: 0.198605
A35: Underwriting code | C35: =IF(smoker="No",healthStatus,IF(healthStatus=3,6,5)) -> 1 | E35: 2000000 | F35: 5 | G35: 3 | M35: 1.55 | N35: 0.198605
A36: Lapse table code | C36: =VLOOKUP(C35,F23:G28,2) -> 1 | E36: 5000000 | F36: 6 | G36: 4 | M36: 1.575 | N36: 0.21666
A37: Face amount | C37: =B6 -> 842000 | E37: Selected | F37: =VLOOKUP($C$37,E31:G36,2) -> 3 | G37: =VLOOKUP($C$37,E31:G36,3) -> 2 | M37: 1.6 | N37: 0.21666
A38: Gender | C38: =sex -> M | M38: 1.625 | N38: 0.21666
E39: NOTE: minimum face amount in any policy duration is set in the benefit model. | M39: 1.65 | N39: 0.21666
A40: Issue Age | B40: Per Policy Exp | E40: This minimum is important to ensure no cash values. | M40: 1.675 | N40: 0.234715
A41: 0 | B41: 75 | E41: Use this model to test for the necessary limits. | M41: 1.7 | N41: 0.234715
A42: 25 | B42: 75 | M42: 1.725 | N42: 0.234715
A43: 30 | B43: 100 | M43: 1.75 | N43: 0.234715
A44: 35 | B44: 125 | M44: 1.775 | N44: 0.234715
A45: 40 | B45: 150 | M45: 1.8 | N45: 0.25277
A46: 45 | B46: 175 | M46: 1.825 | N46: 0.25277
A47: 50 | B47: 225 | M47: 1.85 | N47: 0.25277
A48: 55 | B48: 250 | M48: 1.875 | N48: 0.25277
A49: 60 | B49: 300 | M49: 1.9 | N49: 0.25277
A50: 100 | B50: 300 | M50: 1.925 | N50: 0.270825
M51: 1.95 | N51: 0.270825
M52: 1.975 | N52: 0.270825
M53: 2 | N53: 0.270825 | O53: equivalent to face amount dropping 50%
M54: 2.025 | N54: 0.270825
M55: 2.05 | N55: 0.28888
M56: 2.075 | N56: 0.28888
M57: 2.1 | N57: 0.28888
M58: 2.125 | N58: 0.28888
M59: 2.15 | N59: 0.28888
M60: 2.175 | N60: 0.306935
M61: 2.2 | N61: 0.306935
M62: 2.225 | N62: 0.306935
M63: 2.25 | N63: 0.306935
M64: 2.275 | N64: 0.306935
M65: 2.3 | N65: 0.306935
... M173: 5 | N173: 0.54165

Sheet Pricing
C1: Custom Benefits level premium determination | J1: Last year of coverage requested (BOY age): | M1: =Inputs!B6 -> 0
C2: Base lapses | E2: With Excess | G2: + Mort det | J2: Last year of custom benefit (BOY age) | M2: =age+Pricing!M4-1 -> 22 | N2: EG could be shorter period than requested
A3: PV death claims | C3: =NPV(Assms!K14,$B51:$AO51) -> #N/A | E3: =NPV(Assms!$K$14,$B64:$AO64) -> #N/A | G3: =NPV(Assms!$K$14,$B77:$AO77) -> #N/A | J3: Last year of coverage priced/shown | M3: =MIN(M1,M2) -> 0 | N3: Lessor of above
A4: Annualizing factor | C4: =NPV(Assms!$K$14,$C$48:$AO$48)+$B$48 -> #N/A | E4: =NPV(Assms!$K$14,$C$61:$AO$61)+$B$61 -> #N/A | G4: =NPV(Assms!$K$14,$C$74:$AO$74)+$B$74 -> #N/A | J4: Total covered years | M4: =Assms!B8 -> 23
A5: Annual premium for death claims | C5: =(C3/C4) -> #N/A | E5: =(E3/E4) -> #N/A | G5: =(G3/G4) -> #N/A | J5: Issue age: | M5: =age -> 0
A6: Grossed up for ongoing expenses | C6: =C5/(1-Assms!$C$19) -> #N/A | E6: =E5/(1-Assms!$C$19) -> #N/A | G6: =G5/(1-Assms!$C$19) -> #N/A | O6: Annual rate | P6: 0.06
A7: Total FY expenses & PV DAC tax | C7: =Assms!$C$14+C33 -> #N/A | E7: =Assms!$C$14+E33 -> #N/A | G7: =Assms!$C$14+G33 -> #N/A | O7: Int rate: | P7: =(1+Assms!K12)^(1/12)-1 -> 0.0048675506
A8: Premium for FY expenses & DAC tax I | C8: =C6*C7/C4 -> #N/A | E8: =E6*E7/E4 -> #N/A | G8: =G6*G7/G4 -> #N/A
A9: Premium for FY expenses & DAC tax II | C9: =C8*C7/C4 -> #N/A | E9: =E8*E7/E4 -> #N/A | G9: =G8*G7/G4 -> #N/A | K9: Pre-final | L9: Alt 1 | M9: Alt 2 | N9: Alt 3 | O9: Month | P9: =NPV(P7,P11:P21)+P10 -> 1752.9859
A10: Premium for FY expenses & DAC tax III | C10: =C9*C7/C4 -> #N/A | E10: =E9*E7/E4 -> #N/A | G10: =G9*G7/G4 -> #N/A | J10: Premium | K10: =I30 -> #N/A | L10: =K10*(1+K16) -> #N/A | M10: =L10*(1+L16) -> #N/A | N10: =M10*(1+M16) -> #N/A | O10: 0 | P10: 150.015
A11: Premium for FY expenses & DAC tax IV | C11: =C10*C7/C4 -> #N/A | E11: =E10*E7/E4 -> #N/A | G11: =G10*G7/G4 -> #N/A | J11: PV premium | K11: =NPV(Assms!K14,C95:AO95)+B95 -> #N/A | L11: ='Alt1'!E1 -> #N/A | M11: ='Alt2'!E1 -> #N/A | N11: ='Alt3'!E1 -> #N/A | O11: 1 | P11: =$P$10 -> 150.015
A12: Premium for FY expenses & DAC tax V | C12: =C11*C7/C4 -> #N/A | E12: =E11*E7/E4 -> #N/A | G12: =G11*G7/G4 -> #N/A | J12: PV book pft | K12: =NPV(Assms!K14,B106:AO106) -> #N/A | L12: ='Alt1'!E2 -> #N/A | M12: ='Alt2'!E2 -> #N/A | N12: ='Alt3'!E2 -> #N/A | O12: 2 | P12: =$P$10 -> 150.015
A13: Annual premium (Prelim 2) | C13: =C6+SUM(C8:C12) -> #N/A | E13: =E6+SUM(E8:E12) -> #N/A | G13: =G6+SUM(G8:G12) -> #N/A | J13: Margin | K13: =K12/K11 -> #N/A | L13: ='Alt1'!E3 -> #N/A | M13: ='Alt2'!E3 -> #N/A | N13: ='Alt3'!E3 -> #N/A | O13: 3 | P13: =$P$10 -> 150.015
A14: Premium grossed up for margin | C14: =C13/(1-Assms!$K$18) -> #N/A | E14: =E13/(1-Assms!$K$18) -> #N/A | G14: =G13/(1-Assms!$K$18) -> #N/A | J14: Target | K14: =Assms!K16 -> 0.06 | L14: =Assms!K16 -> 0.06 | M14: =Assms!K16 -> 0.06 | O14: 4 | P14: =$P$10 -> 150.015
A15: Savings for FY comp on pol fee I | C15: =Assms!$C$31*Assms!$C$12 -> 127.5 | E15: =Assms!$C$31*Assms!$C$12 -> 127.5 | G15: =Assms!$C$31*Assms!$C$12 -> 127.5 | J15: Variance | K15: =K13-K14 -> #N/A | L15: =L13-L14 -> #N/A | M15: =M13-M14 -> #N/A | O15: 5 | P15: =$P$10 -> 150.015
A16: Premium for FY expenses & DAC tax II | C16: =C15/C4 -> #N/A | E16: =E15/E4 -> #N/A | G16: =G15/G4 -> #N/A | J16: Adjustment | K16: =-K15*(1+Assms!$K$18)/(1-Assms!$K$13) -> #N/A | L16: =-L15*(1+Assms!$K$18)/(1-Assms!$K$13) -> #N/A | M16: =-M15*(1+Assms!$K$18)/(1-Assms!$K$13) -> #N/A | O16: 6 | P16: =$P$10 -> 150.015
A17: Premium for FY expenses & DAC tax III | C17: =C16/C4 -> #N/A | E17: =E16/E4 -> #N/A | G17: =G16/G4 -> #N/A | O17: 7 | P17: =$P$10 -> 150.015
A18: Premium for FY expenses & DAC tax IV | C18: =C17/C4 -> #N/A | E18: =E17/E4 -> #N/A | G18: =G17/G4 -> #N/A | J18: Other metrics only for viewing; not used | O18: 8 | P18: =$P$10 -> 150.015
A19: Premium reduction grossed up | C19: =-SUM(C16:C18)/(1-Assms!$K$18) -> #N/A | E19: =-SUM(E16:E18)/(1-Assms!$K$18) -> #N/A | G19: =-SUM(G16:G18)/(1-Assms!$K$18) -> #N/A | L19: Stat strain | M19: ='Alt3'!E5 -> #N/A | O19: 9 | P19: =$P$10 -> 150.015
A20: Premium for costs related to gross up I | C20: =(C14-C13)*(Assms!$C$14+C$33)/C4 -> #N/A | E20: =(E14-E13)*(Assms!$C$14+C$33)/E4 -> #N/A | G20: =(G14-G13)*(Assms!$C$14+E$33)/G4 -> #N/A | L20: IRR with RBC | M20: ='Alt3'!E4 -> #VALUE! | O20: 10 | P20: =$P$10 -> 150.015
A21: Premium for costs related to gross up II | C21: =C20*(Assms!$C$14+$B$33)/C4 -> #N/A | E21: =E20*(Assms!$C$14+$B$33)/E4 -> #N/A | G21: =G20*(Assms!$C$14+$B$33)/G4 -> #N/A | O21: 11 | P21: =$P$10 -> 150.015
A22: Premium for costs related to gross up III | C22: =C21*(Assms!$C$14+$B$33)/C4 -> #N/A | E22: =E21*(Assms!$C$14+$B$33)/E4 -> #N/A | G22: =G21*(Assms!$C$14+$B$33)/G4 -> #N/A
A23: Premium for costs related to gross up IV | C23: =C22*(Assms!$C$14+$B$33)/C4 -> #N/A | E23: =E22*(Assms!$C$14+$B$33)/E4 -> #N/A | G23: =G22*(Assms!$C$14+$B$33)/G4 -> #N/A | J23: Final monthly premium quote: | M23: =N10*P24/12 -> #N/A | O23: Annual/12 | P23: 146.08
A24: Pre fixed cost Annual Premium | C24: =C14+C19+SUM(C20:C23) -> #N/A | E24: =E14+E19+SUM(E20:E23) -> #N/A | G24: =G14+G19+SUM(G20:G23) -> #N/A | O24: Conversion | P24: =P21/P23 -> 1.0269373
A25: Premium for per policy expenses | C25: =(NPV(Assms!$K$14,$C$53:$AO$53)+$B$53)/C4 -> #N/A | E25: =(NPV(Assms!$K$14,$C$66:$AO$66)+$B$66)/E4 -> #N/A | G25: =(NPV(Assms!$K$14,$C$79:$AO$79)+$B$79)/G4 -> #N/A
A26: Premium for extra comp & DAC tax | C26: =(C25*Assms!$C$14)*(1+C$33+Assms!$C$19)/C$4 -> #N/A | E26: =(E25*Assms!$C$14)*(1+C$33+Assms!$C$19)/E$4 -> #N/A | G26: =(G25*Assms!$C$14)*(1+E$33+Assms!$C$19)/G$4 -> #N/A
A27: Premium for extra comp & DAC tax II | C27: =(C26*Assms!$C$14)*(1+C$33+Assms!$C$19)/C$4 -> #N/A | E27: =(E26*Assms!$C$14)*(1+C$33+Assms!$C$19)/E$4 -> #N/A | G27: =(G26*Assms!$C$14)*(1+E$33+Assms!$C$19)/G$4 -> #N/A
A28: Premium for extra comp & DAC tax III | C28: =(C27*Assms!$C$14)*(1+C$33+Assms!$C$19)/C$4 -> #N/A | E28: =(E27*Assms!$C$14)*(1+C$33+Assms!$C$19)/E$4 -> #N/A | G28: =(G27*Assms!$C$14)*(1+E$33+Assms!$C$19)/G$4 -> #N/A | H28: Final "Base" | I28: Initial test | J28: check: is the benefit zero in all years so as to produce a bogus premium (e.g., pol expenses)?
A29: Premium for extra comp & DAC tax IV | C29: =(C28*Assms!$C$14)*(1+C$33+Assms!$C$19)/C$4 -> #N/A | E29: =(E28*Assms!$C$14)*(1+C$33+Assms!$C$19)/E$4 -> #N/A | G29: =(G28*Assms!$C$14)*(1+E$33+Assms!$C$19)/G$4 -> #N/A | H29: Premium | I29: Premium
A30: Total annual premium | C30: =SUM(C24:C29) -> #N/A | E30: =SUM(E24:E29) -> #N/A | G30: =SUM(G24:G29) -> #N/A | H30: =G30 -> #N/A | I30: =IF(J30="Yes",0,G30) -> #N/A | J30: =IF(SUM(Assms!B6:AO6)=0,"Yes","No") -> No
E31: =E30/C30-1 -> #N/A | G31: =G30/E30-1 -> #N/A
A33: Cost of DAC tax (PV CFs as % initial premium) | C33: =DACtax!K3 -> #N/A | E33: =C33 -> #N/A | G33: =C33 -> #N/A
A35: Policy Year | B35: 1 | C35: =B35+1 -> 2 | D35: =C35+1 -> 3 | E35: =D35+1 -> 4 | F35: =E35+1 -> 5 | G35: =F35+1 -> 6 | H35: =G35+1 -> 7 | I35: =H35+1 -> 8 | J35: =I35+1 -> 9 | ... AO35: =AN35+1 -> 40
A36: Age of insured | B36: =age -> 0 | C36: =B36+1 -> 1 | D36: =C36+1 -> 2 | E36: =D36+1 -> 3 | F36: =E36+1 -> 4 | G36: =F36+1 -> 5 | H36: =G36+1 -> 6 | I36: =H36+1 -> 7 | J36: =I36+1 -> 8 | ... AO36: =AN36+1 -> 39
A37: Coverage active? | B37: 1 | C37: =IF(C39>0,1,0) -> 1 | D37: =IF(D39>0,1,0) -> 1 | E37: =IF(E39>0,1,0) -> 1 | F37: =IF(F39>0,1,0) -> 1 | G37: =IF(G39>0,1,0) -> 1 | H37: =IF(H39>0,1,0) -> 1 | I37: =IF(I39>0,1,0) -> 1 | J37: =IF(J39>0,1,0) -> 1 | ... AO37: =IF(AO39>0,1,0) -> 0
A38: Inflation factor (cumulative since issue) | B38: 1 | C38: =B38*(1+Assms!C23) -> 1.02 | D38: =C38*(1+Assms!C23) -> 1.0404 | E38: =D38*(1+Assms!C23) -> 1.061208 | F38: =E38*(1+Assms!C23) -> 1.0824322 | G38: =F38*(1+Assms!C23) -> 1.1040808 | H38: =G38*(1+Assms!C23) -> 1.1261624 | I38: =H38*(1+Assms!C23) -> 1.1486857 | J38: =I38*(1+Assms!C23) -> 1.1716594 | K38: =J38*(1+Assms!C23) -> 1.1950926 | L38: =K38*(1+Assms!C23) -> 1.2189944 | M38: =L38*(1+Assms!C23) -> 1.2433743 | N38: =M38*(1+Assms!C23) -> 1.2682418 | O38: =N38*(1+Assms!C23) -> 1.2936066 | P38: =O38*(1+Assms!C23) -> 1.3194788 | Q38: =P38*(1+Assms!C23) -> 1.3458683 | R38: =Q38*(1+Assms!C23) -> 1.3727857 | S38: =R38*(1+Assms!C23) -> 1.4002414 | T38: =S38*(1+Assms!C23) -> 1.4282462 | U38: =T38*(1+Assms!C23) -> 1.4568112 | V38: =U38*(1+Assms!C23) -> 1.4859474 | W38: =V38*(1+Assms!C23) -> 1.5156663 | X38: =W38*(1+Assms!C23) -> 1.5459797 | Y38: =X38*(1+Assms!C23) -> 1.5768993 | Z38: =Y38*(1+Assms!C23) -> 1.6084372 | AA38: =Z38*(1+Assms!C23) -> 1.640606 | AB38: =AA38*(1+Assms!C23) -> 1.6734181 | AC38: =AB38*(1+Assms!C23) -> 1.7068865 | AD38: =AC38*(1+Assms!C23) -> 1.7410242 | AE38: =AD38*(1+Assms!C23) -> 1.7758447 | AF38: =AE38*(1+Assms!C23) -> 1.8113616 | AG38: =AF38*(1+Assms!C23) -> 1.8475888 | AH38: =AG38*(1+Assms!C23) -> 1.8845406 | AI38: =AH38*(1+Assms!C23) -> 1.9222314 | AJ38: =AI38*(1+Assms!C23) -> 1.960676 | AK38: =AJ38*(1+Assms!C23) -> 1.9998896 | AL38: =AK38*(1+Assms!C23) -> 2.0398873 | AM38: =AL38*(1+Assms!C23) -> 2.0806851 | AN38: =AM38*(1+Assms!C23) -> 2.1222988 | AO38: =AN38*(1+Assms!C23) -> 2.1647448
A39: Death benefit | B39: =Assms!B6 -> 842000 | C39: =Assms!C6 -> 837000 | D39: =Assms!D6 -> 830000 | E39: =Assms!E6 -> 821000 | F39: =Assms!F6 -> 811000 | G39: =Assms!G6 -> 798000 | H39: =Assms!H6 -> 784000 | I39: =Assms!I6 -> 767000 | ... AO39: =Assms!AO6 -> 0
A40: Mortality rate before auto slippage | B40: =PriceQx!$B3/1000 -> #N/A | C40: =PriceQx!$B4/1000 -> #N/A | D40: =PriceQx!$B5/1000 -> #N/A | E40: =PriceQx!$B6/1000 -> #N/A | F40: =PriceQx!$B7/1000 -> #N/A | G40: =PriceQx!$B8/1000 -> #N/A | H40: =PriceQx!$B9/1000 -> #N/A | I40: =PriceQx!$B10/1000 -> #N/A | J40: =PriceQx!$B11/1000 -> #N/A | K40: =PriceQx!$B12/1000 -> #N/A | L40: =PriceQx!$B13/1000 -> #N/A | M40: =PriceQx!$B14/1000 -> #N/A | N40: =PriceQx!$B15/1000 -> #N/A | O40: =PriceQx!$B16/1000 -> #N/A | P40: =PriceQx!$B17/1000 -> #N/A | Q40: =PriceQx!$B18/1000 -> #N/A | R40: =PriceQx!$B19/1000 -> #N/A | S40: =PriceQx!$B20/1000 -> #N/A | T40: =PriceQx!$B21/1000 -> #N/A | U40: =PriceQx!$B22/1000 -> #N/A | V40: =PriceQx!$B23/1000 -> #N/A | W40: =PriceQx!$B24/1000 -> #N/A | X40: =PriceQx!$B25/1000 -> #N/A | Y40: =PriceQx!$B24/1000 -> #N/A | Z40: =PriceQx!$B27/1000 -> #N/A | AA40: =PriceQx!$B28/1000 -> #N/A | AB40: =PriceQx!$B29/1000 -> #N/A | AC40: =PriceQx!$B30/1000 -> #N/A | AD40: =PriceQx!$B31/1000 -> #N/A | AE40: =PriceQx!$B32/1000 -> #N/A | AF40: =PriceQx!$B33/1000 -> #N/A | AG40: =PriceQx!$B34/1000 -> #N/A | AH40: =PriceQx!$B35/1000 -> #N/A | AI40: =PriceQx!$B36/1000 -> #N/A | AJ40: =PriceQx!$B37/1000 -> #N/A | AK40: =PriceQx!$B38/1000 -> #N/A | AL40: =PriceQx!$B39/1000 -> #N/A | AM40: =PriceQx!$B40/1000 -> #N/A | AN40: =PriceQx!$B41/1000 -> #N/A | AO40: =PriceQx!$B42/1000 -> #N/A
A41: Mortality improvement since issue | B41: 1 | C41: =B41*(1-Assms!$K$31) -> 0.99 | D41: =C41*(1-Assms!$K$31) -> 0.9801 | E41: =D41*(1-Assms!$K$31) -> 0.970299 | F41: =E41*(1-Assms!$K$31) -> 0.96059601 | G41: =F41*(1-Assms!$K$31) -> 0.95099005 | H41: =G41*(1-Assms!$K$31) -> 0.94148015 | I41: =H41*(1-Assms!$K$31) -> 0.93206535 | J41: =I41*(1-Assms!$K$31) -> 0.92274469 | ... AO41: =AN41*(1-Assms!$K$31) -> 0.67572905
A42: Final mortality rate with auto UW slippage | B42: =B40*(1+Assms!$G$16)*B41 -> #N/A | C42: =C40*(1+Assms!$G$16)*C41 -> #N/A | D42: =D40*(1+Assms!$G$16)*D41 -> #N/A | E42: =E40*(1+Assms!$G$16)*E41 -> #N/A | F42: =F40*(1+Assms!$G$16)*F41 -> #N/A | G42: =G40*(1+Assms!$G$16)*G41 -> #N/A | H42: =H40*(1+Assms!$G$16)*H41 -> #N/A | I42: =I40*(1+Assms!$G$16)*I41 -> #N/A | ... AO42: =AO40*(1+Assms!$G$16)*AO41 -> #N/A
A43: Base lapse rates per RGA | B43: =SelectLX!$G$4 -> 0.04 | C43: =SelectLX!$G$5 -> 0.05 | D43: =SelectLX!$G$6 -> 0.05 | E43: =SelectLX!$G$7 -> 0.04 | F43: =SelectLX!$G$8 -> 0.04 | G43: =SelectLX!$G$9 -> 0.04 | H43: =SelectLX!$G$10 -> 0.03 | I43: =SelectLX!$G$11 -> 0.03 | J43: =SelectLX!$G$12 -> 0.03 | K43: =SelectLX!$G$13 -> 0.02 | L43: =SelectLX!$G$14 -> 0.02 | M43: =SelectLX!$G$15 -> 0.02 | N43: =SelectLX!$G$16 -> 0.02 | O43: =SelectLX!$G$17 -> 0.02 | P43: =SelectLX!$G$18 -> 0.02 | Q43: =SelectLX!$G$19 -> 0.02 | R43: =SelectLX!$G$20 -> 0.02 | S43: =SelectLX!$G$21 -> 0.02 | T43: =SelectLX!$G$22 -> 0.03 | U43: =SelectLX!$G$23 -> 0.03 | V43: =SelectLX!$G$24 -> 0.03 | W43: =SelectLX!$G$25 -> 0.03 | X43: =SelectLX!$G$26 -> 0.03 | Y43: =SelectLX!$G$27 -> 0.03 | Z43: =SelectLX!$G$28 -> 0.03 | AA43: =SelectLX!$G$29 -> 0.03 | AB43: =SelectLX!$G$30 -> 0.03 | AC43: =SelectLX!$G$31 -> 0.02 | AD43: =SelectLX!$G$32 -> 0.02 | AE43: =SelectLX!$G$33 -> 0.02 | AF43: =SelectLX!$G$34 -> 0.02 | AG43: =SelectLX!$G$35 -> 0.02 | AH43: =SelectLX!$G$36 -> 0.02 | AI43: =SelectLX!$G$37 -> 0.02 | AJ43: =SelectLX!$G$38 -> 0.02 | AK43: =SelectLX!$G$39 -> 0.02 | AL43: =SelectLX!$G$40 -> 0.02 | AM43: =SelectLX!$G$41 -> 0.02 | AN43: =SelectLX!$G$42 -> 0.02 | AO43: =SelectLX!$G$43 -> 0.02
A45: Custom design benefits-base lapses
A46: Base Pricing Lapse rate - customized DB | B46: =B43 -> 0.04 | C46: =C43 -> 0.05 | D46: =D43 -> 0.05 | E46: =E43 -> 0.04 | F46: =F43 -> 0.04 | G46: =G43 -> 0.04 | H46: =H43 -> 0.03 | I46: =I43 -> 0.03 | ... AO46: =AO43 -> 0.02
A47: EOY survival rate before that yr's Qx and Lx | B47: 1 | C47: =B47*(1-B46-B42) -> #N/A | D47: =C47*(1-C46-C42) -> #N/A | E47: =D47*(1-D46-D42) -> #N/A | F47: =E47*(1-E46-E42) -> #N/A | G47: =F47*(1-F46-F42) -> #N/A | H47: =G47*(1-G46-G42) -> #N/A | I47: =H47*(1-H46-H42) -> #N/A | J47: =I47*(1-I46-I42) -> #N/A | ... AO47: =AN47*(1-AN46-AN42) -> #N/A
A48: Survival rate for coverage period | B48: =IF(B37=1,B47,0) -> 1 | C48: =IF(C37=1,C47,0) -> #N/A | D48: =IF(D37=1,D47,0) -> #N/A | E48: =IF(E37=1,E47,0) -> #N/A | F48: =IF(F37=1,F47,0) -> #N/A | G48: =IF(G37=1,G47,0) -> #N/A | H48: =IF(H37=1,H47,0) -> #N/A | I48: =IF(I37=1,I47,0) -> #N/A | ... AO48: =IF(AO37=1,AO47,0) -> 0
A50: Inforce death benefit (beg of year) | B50: =B39*B48 -> 842000 | C50: =C39*C48 -> #N/A | D50: =D39*D48 -> #N/A | E50: =E39*E48 -> #N/A | F50: =F39*F48 -> #N/A | G50: =G39*G48 -> #N/A | H50: =H39*H48 -> #N/A | I50: =I39*I48 -> #N/A | ... AO50: =AO39*AO48 -> 0
A51: Expected death claims (EOY before lapses) | B51: =B50*B42 -> #N/A | C51: =C50*C42 -> #N/A | D51: =D50*D42 -> #N/A | E51: =E50*E42 -> #N/A | F51: =F50*F42 -> #N/A | G51: =G50*G42 -> #N/A | H51: =H50*H42 -> #N/A | I51: =I50*I42 -> #N/A | ... AO51: =AO50*AO42 -> #N/A
A52: Inforce premium collected (beg of year) | B52: =$C$30*B48 -> #N/A | C52: =$C$30*C48 -> #N/A | D52: =$C$30*D48 -> #N/A | E52: =$C$30*E48 -> #N/A | F52: =$C$30*F48 -> #N/A | G52: =$C$30*G48 -> #N/A | H52: =$C$30*H48 -> #N/A | I52: =$C$30*I48 -> #N/A | ... AO52: =$C$30*AO48 -> #N/A
A53: Per Policy expenses | B53: =Assms!C21+Assms!C22 -> 150 | C53: =Assms!C22*C38*C48 -> #N/A | D53: =Assms!C22*D38*D48 -> #N/A | E53: =Assms!C22*E38*E48 -> #N/A | F53: =Assms!C22*F38*F48 -> #N/A | G53: =Assms!C22*G38*G48 -> #N/A | H53: =Assms!C22*H38*H48 -> #N/A | I53: =Assms!C22*I38*I48 -> #N/A | J53: =Assms!C22*J38*J48 -> #N/A | K53: =Assms!C22*K38*K48 -> #N/A | L53: =Assms!C22*L38*L48 -> #N/A | M53: =Assms!C22*M38*M48 -> #N/A | N53: =Assms!C22*N38*N48 -> #N/A | O53: =Assms!C22*O38*O48 -> #N/A | P53: =Assms!C22*P38*P48 -> #N/A | Q53: =Assms!C22*Q38*Q48 -> #N/A | R53: =Assms!C22*R38*R48 -> #N/A | S53: =Assms!C22*S38*S48 -> #N/A | T53: =Assms!C22*T38*T48 -> #N/A | U53: =Assms!C22*U38*U48 -> #N/A | V53: =Assms!C22*V38*V48 -> #N/A | W53: =Assms!C22*W38*W48 -> #N/A | X53: =Assms!C22*X38*X48 -> #N/A | Y53: =Assms!C22*Y38*Y48 -> 0 | Z53: =Assms!C22*Z38*Z48 -> 0 | AA53: =Assms!C22*AA38*AA48 -> 0 | AB53: =Assms!C22*AB38*AB48 -> 0 | AC53: =Assms!C22*AC38*AC48 -> 0 | AD53: =Assms!C22*AD38*AD48 -> 0 | AE53: =Assms!C22*AE38*AE48 -> 0 | AF53: =Assms!C22*AF38*AF48 -> 0 | AG53: =Assms!C22*AG38*AG48 -> 0 | AH53: =Assms!C22*AH38*AH48 -> 0 | AI53: =Assms!C22*AI38*AI48 -> 0 | AJ53: =Assms!C22*AJ38*AJ48 -> 0 | AK53: =Assms!C22*AK38*AK48 -> 0 | AL53: =Assms!C22*AL38*AL48 -> 0 | AM53: =Assms!C22*AM38*AM48 -> 0 | AN53: =Assms!C22*AN38*AN48 -> 0 | AO53: =Assms!C22*AO38*AO48 -> 0
A55: Custom design benefits-add excess lapses
A56: Change in face lookup factor | C56: =IF(C39=0,0,ROUND(B39 / C39 * 40,0)/40) -> 1 | D56: =IF(D39=0,0,ROUND(C39 / D39 * 40,0)/40) -> 1 | E56: =IF(E39=0,0,ROUND(D39 / E39 * 40,0)/40) -> 1 | F56: =IF(F39=0,0,ROUND(E39 / F39 * 40,0)/40) -> 1 | G56: =IF(G39=0,0,ROUND(F39 / G39 * 40,0)/40) -> 1.025 | H56: =IF(H39=0,0,ROUND(G39 / H39 * 40,0)/40) -> 1.025 | I56: =IF(I39=0,0,ROUND(H39 / I39 * 40,0)/40) -> 1.025 | J56: =IF(J39=0,0,ROUND(I39 / J39 * 40,0)/40) -> 1.025 | ... AO56: =IF(AO39=0,0,ROUND(AN39 / AO39 * 40,0)/40) -> 0
A57: Final lapse rate | B57: =B59 -> 0.04 | C57: =MAX(IF(C56<=1,C59,VLOOKUP(C56,Assms!$M$13:$N$173,2)),C59) -> 0.05 | D57: =MAX(IF(D56<=1,D59,VLOOKUP(D56,Assms!$M$13:$N$173,2)),D59) -> 0.05 | E57: =MAX(IF(E56<=1,E59,VLOOKUP(E56,Assms!$M$13:$N$173,2)),E59) -> 0.04 | F57: =MAX(IF(F56<=1,F59,VLOOKUP(F56,Assms!$M$13:$N$173,2)),F59) -> 0.04 | G57: =MAX(IF(G56<=1,G59,VLOOKUP(G56,Assms!$M$13:$N$173,2)),G59) -> 0.04 | H57: =MAX(IF(H56<=1,H59,VLOOKUP(H56,Assms!$M$13:$N$173,2)),H59) -> 0.03 | I57: =MAX(IF(I56<=1,I59,VLOOKUP(I56,Assms!$M$13:$N$173,2)),I59) -> 0.03 | J57: =MAX(IF(J56<=1,J59,VLOOKUP(J56,Assms!$M$13:$N$173,2)),J59) -> 0.03 | ... AO57: =MAX(IF(AO56<=1,AO59,VLOOKUP(AO56,Assms!$M$13:$N$173,2)),AO59) -> 0.02
A58: Excess lapse rate per RGA | B58: =B57-B59 -> 0 | C58: =C57-C59 -> 0 | D58: =D57-D59 -> 0 | E58: =E57-E59 -> 0 | F58: =F57-F59 -> 0 | G58: =G57-G59 -> 0 | H58: =H57-H59 -> 0 | I58: =I57-I59 -> 0 | ... AO58: =AO57-AO59 -> 0
A59: Base lapse rate | B59: =B43 -> 0.04 | C59: =C43 -> 0.05 | D59: =D43 -> 0.05 | E59: =E43 -> 0.04 | F59: =F43 -> 0.04 | G59: =G43 -> 0.04 | H59: =H43 -> 0.03 | I59: =I43 -> 0.03 | ... AO59: =AO43 -> 0.02
A60: EOY survival rate before that yr's Qx and Lx | B60: 1 | C60: =B60*(1-B57-B42) -> #N/A | D60: =C60*(1-C57-C42) -> #N/A | E60: =D60*(1-D57-D42) -> #N/A | F60: =E60*(1-E57-E42) -> #N/A | G60: =F60*(1-F57-F42) -> #N/A | H60: =G60*(1-G57-G42) -> #N/A | I60: =H60*(1-H57-H42) -> #N/A | J60: =I60*(1-I57-I42) -> #N/A | ... AO60: =AN60*(1-AN57-AN42) -> #N/A
A61: Survival rate for coverage period | B61: =IF(B37=1,B60,0) -> 1 | C61: =IF(C37=1,C60,0) -> #N/A | D61: =IF(D37=1,D60,0) -> #N/A | E61: =IF(E37=1,E60,0) -> #N/A | F61: =IF(F37=1,F60,0) -> #N/A | G61: =IF(G37=1,G60,0) -> #N/A | H61: =IF(H37=1,H60,0) -> #N/A | I61: =IF(I37=1,I60,0) -> #N/A | ... AO61: =IF(AO37=1,AO60,0) -> 0
A63: Inforce death benefit (beg of year) | B63: =B39*B61 -> 842000 | C63: =C39*C61 -> #N/A | D63: =D39*D61 -> #N/A | E63: =E39*E61 -> #N/A | F63: =F39*F61 -> #N/A | G63: =G39*G61 -> #N/A | H63: =H39*H61 -> #N/A | I63: =I39*I61 -> #N/A | ... AO63: =AO39*AO61 -> 0
A64: Expected death claims (EOY before lapses) | B64: =B63*B42 -> #N/A | C64: =C63*C42 -> #N/A | D64: =D63*D42 -> #N/A | E64: =E63*E42 -> #N/A | F64: =F63*F42 -> #N/A | G64: =G63*G42 -> #N/A | H64: =H63*H42 -> #N/A | I64: =I63*I42 -> #N/A | ... AO64: =AO63*AO42 -> #N/A
A65: Inforce premium collected (beg of year) | B65: =$C$30*B61 -> #N/A | C65: =$C$30*C61 -> #N/A | D65: =$C$30*D61 -> #N/A | E65: =$C$30*E61 -> #N/A | F65: =$C$30*F61 -> #N/A | G65: =$C$30*G61 -> #N/A | H65: =$C$30*H61 -> #N/A | I65: =$C$30*I61 -> #N/A | ... AO65: =$C$30*AO61 -> #N/A
A66: Per Policy expenses | B66: =Assms!C21+Assms!C22 -> 150 | C66: =Assms!$C$22*C38*C61 -> #N/A | D66: =Assms!$C$22*D38*D61 -> #N/A | E66: =Assms!$C$22*E38*E61 -> #N/A | F66: =Assms!$C$22*F38*F61 -> #N/A | G66: =Assms!$C$22*G38*G61 -> #N/A | H66: =Assms!$C$22*H38*H61 -> #N/A | I66: =Assms!$C$22*I38*I61 -> #N/A | J66: =Assms!$C$22*J38*J61 -> #N/A | ... AO66: =Assms!$C$22*AO38*AO61 -> 0
A68: Custom design benefits-add mortality deterioration
A69: Final lapse rate | B69: =B57 -> 0.04 | C69: =C57 -> 0.05 | D69: =D57 -> 0.05 | E69: =E57 -> 0.04 | F69: =F57 -> 0.04 | G69: =G57 -> 0.04 | H69: =H57 -> 0.03 | I69: =I57 -> 0.03 | ... AO69: =AO57 -> 0.02
A70: Base mortality rate | B70: =B42 -> #N/A | C70: =C42 -> #N/A | D70: =D42 -> #N/A | E70: =E42 -> #N/A | F70: =F42 -> #N/A | G70: =G42 -> #N/A | H70: =H42 -> #N/A | I70: =I42 -> #N/A | ... AO70: =AO42 -> #N/A
A71: Excess mortality due to excess lapses | B71: =DMD!B53 -> 0 | C71: =DMD!C53 -> #N/A | D71: =DMD!D53 -> #N/A | E71: =DMD!E53 -> #N/A | F71: =DMD!F53 -> #N/A | G71: =DMD!G53 -> #N/A | H71: =DMD!H53 -> #N/A | I71: =DMD!I53 -> #N/A | ... AO71: =DMD!AO53 -> #N/A
A72: Final mortality rate | B72: =B70*(1+B71) -> #N/A | C72: =C70*(1+C71) -> #N/A | D72: =D70*(1+D71) -> #N/A | E72: =E70*(1+E71) -> #N/A | F72: =F70*(1+F71) -> #N/A | G72: =G70*(1+G71) -> #N/A | H72: =H70*(1+H71) -> #N/A | I72: =I70*(1+I71) -> #N/A | ... AO72: =AO70*(1+AO71) -> #N/A
A73: EOY survival rate before that yr's Qx and Lx | B73: 1 | C73: =B73*(1-B69-B72) -> #N/A | D73: =C73*(1-C69-C72) -> #N/A | E73: =D73*(1-D69-D72) -> #N/A | F73: =E73*(1-E69-E72) -> #N/A | G73: =F73*(1-F69-F72) -> #N/A | H73: =G73*(1-G69-G72) -> #N/A | I73: =H73*(1-H69-H72) -> #N/A | J73: =I73*(1-I69-I72) -> #N/A | ... AO73: =AN73*(1-AN69-AN72) -> #N/A
A74: Survival rate for coverage period | B74: =IF(B37=1,B73,0) -> 1 | C74: =IF(C37=1,C73,0) -> #N/A | D74: =IF(D37=1,D73,0) -> #N/A | E74: =IF(E37=1,E73,0) -> #N/A | F74: =IF(F37=1,F73,0) -> #N/A | G74: =IF(G37=1,G73,0) -> #N/A | H74: =IF(H37=1,H73,0) -> #N/A | I74: =IF(I37=1,I73,0) -> #N/A | ... AO74: =IF(AO37=1,AO73,0) -> 0
A76: Inforce death benefit (beg of year) | B76: =B39*B74 -> 842000 | C76: =C39*C74 -> #N/A | D76: =D39*D74 -> #N/A | E76: =E39*E74 -> #N/A | F76: =F39*F74 -> #N/A | G76: =G39*G74 -> #N/A | H76: =H39*H74 -> #N/A | I76: =I39*I74 -> #N/A | ... AO76: =AO39*AO74 -> 0
A77: Expected death claims (EOY before lapses) | B77: =B76*B72 -> #N/A | C77: =C76*C72 -> #N/A | D77: =D76*D72 -> #N/A | E77: =E76*E72 -> #N/A | F77: =F76*F72 -> #N/A | G77: =G76*G72 -> #N/A | H77: =H76*H72 -> #N/A | I77: =I76*I72 -> #N/A | ... AO77: =AO76*AO72 -> #N/A
A78: Inforce premium collected (beg of year) | B78: =$C$30*B74 -> #N/A | C78: =$C$30*C74 -> #N/A | D78: =$C$30*D74 -> #N/A | E78: =$C$30*E74 -> #N/A | F78: =$C$30*F74 -> #N/A | G78: =$C$30*G74 -> #N/A | H78: =$C$30*H74 -> #N/A | I78: =$C$30*I74 -> #N/A | ... AO78: =$C$30*AO74 -> #N/A
A79: Per Policy expenses | B79: =Assms!C21+Assms!C22 -> 150 | C79: =Assms!$C$22*C38*C74 -> #N/A | D79: =Assms!$C$22*D38*D74 -> #N/A | E79: =Assms!$C$22*E38*E74 -> #N/A | F79: =Assms!$C$22*F38*F74 -> #N/A | G79: =Assms!$C$22*G38*G74 -> #N/A | H79: =Assms!$C$22*H38*H74 -> #N/A | I79: =Assms!$C$22*I38*I74 -> #N/A | J79: =Assms!$C$22*J38*J74 -> #N/A | ... AO79: =Assms!$C$22*AO38*AO74 -> 0
A82: Profitability Calculation
A83: Inforce? | B83: =StatV!B12 -> 1 | C83: =StatV!C12 -> 1 | D83: =StatV!D12 -> 1 | E83: =StatV!E12 -> 1 | F83: =StatV!F12 -> 1 | G83: =StatV!G12 -> 1 | H83: =StatV!H12 -> 1 | I83: =StatV!I12 -> 1 | ... AO83: =StatV!AO12 -> 0
A84: Reserve per DB inforce | B84: =StatV!B203 -> #N/A | C84: =StatV!C203 -> #N/A | D84: =StatV!D203 -> #N/A | E84: =StatV!E203 -> #N/A | F84: =StatV!F203 -> #N/A | G84: =StatV!G203 -> #N/A | H84: =StatV!H203 -> #N/A | I84: =StatV!I203 -> #N/A | ... AO84: =StatV!AO203 -> #N/A
A85: Cash Value per DB inforce | B85: =CashValue!C39 -> #N/A | C85: =CashValue!D39 -> #N/A | D85: =CashValue!E39 -> #N/A | E85: =CashValue!F39 -> #N/A | F85: =CashValue!G39 -> #N/A | G85: =CashValue!H39 -> #N/A | H85: =CashValue!I39 -> #N/A | I85: =CashValue!J39 -> #N/A | ... AO85: =CashValue!AP39 -> #N/A
A86: Mortality rate | B86: =B72 -> #N/A | C86: =C72 -> #N/A | D86: =D72 -> #N/A | E86: =E72 -> #N/A | F86: =F72 -> #N/A | G86: =G72 -> #N/A | H86: =H72 -> #N/A | I86: =I72 -> #N/A | ... AO86: =AO72 -> #N/A
A87: Lapse rate with excess added | B87: =B69 -> 0.04 | C87: =C69 -> 0.05 | D87: =D69 -> 0.05 | E87: =E69 -> 0.04 | F87: =F69 -> 0.04 | G87: =G69 -> 0.04 | H87: =H69 -> 0.03 | I87: =I69 -> 0.03 | ... AO87: =AO69 -> 0.02
A88: tPx (beg yr) | B88: 1 | C88: =IF(C83=1,B88*(1-B86-B87),0) -> #N/A | D88: =IF(D83=1,C88*(1-C86-C87),0) -> #N/A | E88: =IF(E83=1,D88*(1-D86-D87),0) -> #N/A | F88: =IF(F83=1,E88*(1-E86-E87),0) -> #N/A | G88: =IF(G83=1,F88*(1-F86-F87),0) -> #N/A | H88: =IF(H83=1,G88*(1-G86-G87),0) -> #N/A | I88: =IF(I83=1,H88*(1-H86-H87),0) -> #N/A | J88: =IF(J83=1,I88*(1-I86-I87),0) -> #N/A | ... AO88: =IF(AO83=1,AN88*(1-AN86-AN87),0) -> 0
A89: Inforce DB (BOY) | B89: =Pricing!B39*B88 -> 842000 | C89: =Pricing!C39*C88 -> #N/A | D89: =Pricing!D39*D88 -> #N/A | E89: =Pricing!E39*E88 -> #N/A | F89: =Pricing!F39*F88 -> #N/A | G89: =Pricing!G39*G88 -> #N/A | H89: =Pricing!H39*H88 -> #N/A | I89: =Pricing!I39*I88 -> #N/A | ... AO89: =Pricing!AO39*AO88 -> 0
A90: Reserve inforce | B90: =B89*B84 -> #N/A | C90: =C89*C84 -> #N/A | D90: =D89*D84 -> #N/A | E90: =E89*E84 -> #N/A | F90: =F89*F84 -> #N/A | G90: =G89*G84 -> #N/A | H90: =H89*H84 -> #N/A | I90: =I89*I84 -> #N/A | ... AN90: =AN89*AN84 -> #N/A | AO90: 0
A91: CV inforce | B91: =B89*B85 -> #N/A | C91: =C89*C85 -> #N/A | D91: =D89*D85 -> #N/A | E91: =E89*E85 -> #N/A | F91: =F89*F85 -> #N/A | G91: =G89*G85 -> #N/A | H91: =H89*H85 -> #N/A | I91: =I89*I85 -> #N/A | ... AO91: =AO89*AO85 -> #N/A
A93: Stat book profit (customized policy)
A94: Policy Year | B94: 1 | C94: =B94+1 -> 2 | D94: =C94+1 -> 3 | E94: =D94+1 -> 4 | F94: =E94+1 -> 5 | G94: =F94+1 -> 6 | H94: =G94+1 -> 7 | I94: =H94+1 -> 8 | J94: =I94+1 -> 9 | ... AO94: =AN94+1 -> 40
A95: Premiums | B95: =Pricing!$H$30*B88 -> #N/A | C95: =Pricing!$H$30*C88 -> #N/A | D95: =Pricing!$H$30*D88 -> #N/A | E95: =Pricing!$H$30*E88 -> #N/A | F95: =Pricing!$H$30*F88 -> #N/A | G95: =Pricing!$H$30*G88 -> #N/A | H95: =Pricing!$H$30*H88 -> #N/A | I95: =Pricing!$H$30*I88 -> #N/A | ... AO95: =Pricing!$H$30*AO88 -> #N/A
A96: Inv Inc reserves | B96: =Assms!$K$12*B90 -> #N/A | C96: =Assms!$K$12*C90 -> #N/A | D96: =Assms!$K$12*D90 -> #N/A | E96: =Assms!$K$12*E90 -> #N/A | F96: =Assms!$K$12*F90 -> #N/A | G96: =Assms!$K$12*G90 -> #N/A | H96: =Assms!$K$12*H90 -> #N/A | I96: =Assms!$K$12*I90 -> #N/A | ... AO96: =Assms!$K$12*AO90 -> 0
A97: Prem-based exp | B97: =(B95-B88*Assms!$C$31)*Assms!$C$12+(Assms!$C$13*B95) -> #N/A | C97: =(C95-C88*Assms!$C$31)*Assms!$C$17+(C95*(Assms!$C$16+Assms!$C$18)) -> #N/A | D97: =(D95-D88*Assms!$C$31)*Assms!$C$17+(D95*(Assms!$C$16+Assms!$C$18)) -> #N/A | E97: =(E95-E88*Assms!$C$31)*Assms!$C$17+(E95*(Assms!$C$16+Assms!$C$18)) -> #N/A | F97: =(F95-F88*Assms!$C$31)*Assms!$C$17+(F95*(Assms!$C$16+Assms!$C$18)) -> #N/A | G97: =(G95-G88*Assms!$C$31)*Assms!$C$17+(G95*(Assms!$C$16+Assms!$C$18)) -> #N/A | H97: =(H95-H88*Assms!$C$31)*Assms!$C$17+(H95*(Assms!$C$16+Assms!$C$18)) -> #N/A | I97: =(I95-I88*Assms!$C$31)*Assms!$C$17+(I95*(Assms!$C$16+Assms!$C$18)) -> #N/A | J97: =(J95-J88*Assms!$C$31)*Assms!$C$17+(J95*(Assms!$C$16+Assms!$C$18)) -> #N/A | ... AO97: =(AO95-AO88*Assms!$C$31)*Assms!$C$17+(AO95*(Assms!$C$16+Assms!$C$18)) -> #N/A
A98: Per policy Exp | B98: =Assms!C21+Assms!C22 -> 150 | C98: =IF(C89>0,Assms!$C$22*Pricing!C38*C88,0) -> #N/A | D98: =IF(D89>0,Assms!$C$22*Pricing!D38*D88,0) -> #N/A | E98: =IF(E89>0,Assms!$C$22*Pricing!E38*E88,0) -> #N/A | F98: =IF(F89>0,Assms!$C$22*Pricing!F38*F88,0) -> #N/A | G98: =IF(G89>0,Assms!$C$22*Pricing!G38*G88,0) -> #N/A | H98: =IF(H89>0,Assms!$C$22*Pricing!H38*H88,0) -> #N/A | I98: =IF(I89>0,Assms!$C$22*Pricing!I38*I88,0) -> #N/A | J98: =IF(J89>0,Assms!$C$22*Pricing!J38*J88,0) -> #N/A | ... AO98: =IF(AO89>0,Assms!$C$22*Pricing!AO38*AO88,0) -> 0
A99: Death claims | B99: =B89*B86 -> #N/A | C99: =C89*C86 -> #N/A | D99: =D89*D86 -> #N/A | E99: =E89*E86 -> #N/A | F99: =F89*F86 -> #N/A | G99: =G89*G86 -> #N/A | H99: =H89*H86 -> #N/A | I99: =I89*I86 -> #N/A | ... AO99: =AO89*AO86 -> #N/A
A100: Cash value/lapses | B100: =IF(B83=1,B89*B87*B85,"") -> #N/A | C100: =IF(C83=1,C89*C87*C85,"") -> #N/A | D100: =IF(D83=1,D89*D87*D85,"") -> #N/A | E100: =IF(E83=1,E89*E87*E85,"") -> #N/A | F100: =IF(F83=1,F89*F87*F85,"") -> #N/A | G100: =IF(G83=1,G89*G87*G85,"") -> #N/A | H100: =IF(H83=1,H89*H87*H85,"") -> #N/A | I100: =IF(I83=1,I89*I87*I85,"") -> #N/A | ... AO100: =IF(AO83=1,AO89*AO87*AO85,"")
A101: Change in resv | B101: =B90 -> #N/A | C101: =C90-B90 -> #N/A | D101: =D90-C90 -> #N/A | E101: =E90-D90 -> #N/A | F101: =F90-E90 -> #N/A | G101: =G90-F90 -> #N/A | H101: =H90-G90 -> #N/A | I101: =I90-H90 -> #N/A | J101: =J90-I90 -> #N/A | ... AO101: =AO90-AN90 -> #N/A
A103: Pre-tax stat book | B103: =(B95+B96)-SUM(B97:B101) -> #N/A | C103: =(C95+C96)-SUM(C97:C101) -> #N/A | D103: =(D95+D96)-SUM(D97:D101) -> #N/A | E103: =(E95+E96)-SUM(E97:E101) -> #N/A | F103: =(F95+F96)-SUM(F97:F101) -> #N/A | G103: =(G95+G96)-SUM(G97:G101) -> #N/A | H103: =(H95+H96)-SUM(H97:H101) -> #N/A | I103: =(I95+I96)-SUM(I97:I101) -> #N/A | ... AO103: =(AO95+AO96)-SUM(AO97:AO101) -> #N/A
A104: Income tax | B104: =B103*Assms!K13 -> #N/A | C104: =C103*Assms!K13 -> #N/A | D104: =D103*Assms!K13 -> #N/A | E104: =E103*Assms!K13 -> #N/A | F104: =F103*Assms!K13 -> #N/A | G104: =G103*Assms!K13 -> #N/A | H104: =H103*Assms!K13 -> #N/A | I104: =I103*Assms!K13 -> #N/A | J104: =J103*Assms!K13 -> #N/A | K104: =K103*Assms!K13 -> #N/A | L104: =L103*Assms!K13 -> #N/A | M104: =M103*Assms!K13 -> #N/A | N104: =N103*Assms!K13 -> #N/A | O104: =O103*Assms!K13 -> #N/A | P104: =P103*Assms!K13 -> #N/A | Q104: =Q103*Assms!K13 -> #N/A | R104: =R103*Assms!K13 -> #N/A | S104: =S103*Assms!K13 -> #N/A | T104: =T103*Assms!K13 -> #N/A | U104: =U103*Assms!K13 -> #N/A | V104: =V103*Assms!K13 -> #N/A | W104: =W103*Assms!K13 -> #N/A | X104: =X103*Assms!K13 -> #N/A | Y104: =Y103*Assms!K13 -> #N/A | Z104: =Z103*Assms!K13 -> #N/A | AA104: =AA103*Assms!K13 -> #N/A | AB104: =AB103*Assms!K13 -> #N/A | AC104: =AC103*Assms!K13 -> #N/A | AD104: =AD103*Assms!K13 -> #N/A | AE104: =AE103*Assms!K13 -> #N/A | AF104: =AF103*Assms!K13 -> #N/A | AG104: =AG103*Assms!K13 -> #N/A | AH104: =AH103*Assms!K13 -> #N/A | AI104: =AI103*Assms!K13 -> #N/A | AJ104: =AJ103*Assms!K13 -> #N/A | AK104: =AK103*Assms!K13 -> #N/A | AL104: =AL103*Assms!K13 -> #N/A | AM104: =AM103*Assms!K13 -> #N/A | AN104: =AN103*Assms!K13 -> #N/A | AO104: =AO103*Assms!K13 -> #N/A
A105: DAC tax payments | B105: =-StatV!$F$2/DACtax!$F$2*DACtax!B8 -> #N/A | C105: =-StatV!$F$2/DACtax!$F$2*DACtax!C8 -> #N/A | D105: =-StatV!$F$2/DACtax!$F$2*DACtax!D8 -> #N/A | E105: =-StatV!$F$2/DACtax!$F$2*DACtax!E8 -> #N/A | F105: =-StatV!$F$2/DACtax!$F$2*DACtax!F8 -> #N/A | G105: =-StatV!$F$2/DACtax!$F$2*DACtax!G8 -> #N/A | H105: =-StatV!$F$2/DACtax!$F$2*DACtax!H8 -> #N/A | I105: =-StatV!$F$2/DACtax!$F$2*DACtax!I8 -> #N/A | ... AO105: =-StatV!$F$2/DACtax!$F$2*DACtax!AO8 -> #N/A
A106: Net income | B106: =B103-B104+B105 -> #N/A | C106: =C103-C104+C105 -> #N/A | D106: =D103-D104+D105 -> #N/A | E106: =E103-E104+E105 -> #N/A | F106: =F103-F104+F105 -> #N/A | G106: =G103-G104+G105 -> #N/A | H106: =H103-H104+H105 -> #N/A | I106: =I103-I104+I105 -> #N/A | ... AO106: =AO103-AO104+AO105 -> #N/A

Sheet Alt1
A1: Calculate IRR with Alt1 premium | B1: =Pricing!L10 -> #N/A | D1: PV premium | E1: =NPV(Assms!K14,C35:AO35)+B35 -> #N/A
D2: PV book pft | E2: =NPV(Assms!K14,B46:AO46) -> #N/A
A3: Last year of coverage requested (BOY age): | B3: =Pricing!M1 -> 0 | D3: Margin | E3: =E2/E1 -> #N/A
A4: Last year of custom design model (BOY age) | B4: =Pricing!M2 -> 22
A5: Last year of coverage priced/shown | B5: =Pricing!M3 -> 0
A7: Policy Year | B7: 1 | C7: =B7+1 -> 2 | D7: =C7+1 -> 3 | E7: =D7+1 -> 4 | F7: =E7+1 -> 5 | G7: =F7+1 -> 6 | H7: =G7+1 -> 7 | I7: =H7+1 -> 8 | J7: =I7+1 -> 9 | ... AO7: =AN7+1 -> 40
A8: Age of insured | B8: =Pricing!B36 -> 0 | C8: =Pricing!C36 -> 1 | D8: =Pricing!D36 -> 2 | E8: =Pricing!E36 -> 3 | F8: =Pricing!F36 -> 4 | G8: =Pricing!G36 -> 5 | H8: =Pricing!H36 -> 6 | I8: =Pricing!I36 -> 7 | ... AO8: =Pricing!AO36 -> 39
A9: Coverage active? | B9: =Pricing!B37 -> 1 | C9: =Pricing!C37 -> 1 | D9: =Pricing!D37 -> 1 | E9: =Pricing!E37 -> 1 | F9: =Pricing!F37 -> 1 | G9: =Pricing!G37 -> 1 | H9: =Pricing!H37 -> 1 | I9: =Pricing!I37 -> 1 | ... AO9: =Pricing!AO37 -> 0
A10: Inflation factor (cumulative since issue) | B10: 1 | C10: =B10*(1+Assms!C23) -> 1.02 | D10: =C10*(1+Assms!C23) -> 1.0404 | E10: =D10*(1+Assms!C23) -> 1.061208 | F10: =E10*(1+Assms!C23) -> 1.0824322 | G10: =F10*(1+Assms!C23) -> 1.1040808 | H10: =G10*(1+Assms!C23) -> 1.1261624 | I10: =H10*(1+Assms!C23) -> 1.1486857 | J10: =I10*(1+Assms!C23) -> 1.1716594 | K10: =J10*(1+Assms!C23) -> 1.1950926 | L10: =K10*(1+Assms!C23) -> 1.2189944 | M10: =L10*(1+Assms!C23) -> 1.2433743 | N10: =M10*(1+Assms!C23) -> 1.2682418 | O10: =N10*(1+Assms!C23) -> 1.2936066 | P10: =O10*(1+Assms!C23) -> 1.3194788 | Q10: =P10*(1+Assms!C23) -> 1.3458683 | R10: =Q10*(1+Assms!C23) -> 1.3727857 | S10: =R10*(1+Assms!C23) -> 1.4002414 | T10: =S10*(1+Assms!C23) -> 1.4282462 | U10: =T10*(1+Assms!C23) -> 1.4568112 | V10: =U10*(1+Assms!C23) -> 1.4859474 | W10: =V10*(1+Assms!C23) -> 1.5156663 | X10: =W10*(1+Assms!C23) -> 1.5459797 | Y10: =X10*(1+Assms!C23) -> 1.5768993 | Z10: =Y10*(1+Assms!C23) -> 1.6084372 | AA10: =Z10*(1+Assms!C23) -> 1.640606 | AB10: =AA10*(1+Assms!C23) -> 1.6734181 | AC10: =AB10*(1+Assms!C23) -> 1.7068865 | AD10: =AC10*(1+Assms!C23) -> 1.7410242 | AE10: =AD10*(1+Assms!C23) -> 1.7758447 | AF10: =AE10*(1+Assms!C23) -> 1.8113616 | AG10: =AF10*(1+Assms!C23) -> 1.8475888 | AH10: =AG10*(1+Assms!C23) -> 1.8845406 | AI10: =AH10*(1+Assms!C23) -> 1.9222314 | AJ10: =AI10*(1+Assms!C23) -> 1.960676 | AK10: =AJ10*(1+Assms!C23) -> 1.9998896 | AL10: =AK10*(1+Assms!C23) -> 2.0398873 | AM10: =AL10*(1+Assms!C23) -> 2.0806851 | AN10: =AM10*(1+Assms!C23) -> 2.1222988 | AO10: =AN10*(1+Assms!C23) -> 2.1647448
A11: Expected mortality rate | B11: =Pricing!B42 -> #N/A | C11: =Pricing!C42 -> #N/A | D11: =Pricing!D42 -> #N/A | E11: =Pricing!E42 -> #N/A | F11: =Pricing!F42 -> #N/A | G11: =Pricing!G42 -> #N/A | H11: =Pricing!H42 -> #N/A | I11: =Pricing!I42 -> #N/A | ... AO11: =Pricing!AO42 -> #N/A
A12: Lapse rate with excess | B12: =Pricing!B57 -> 0.04 | C12: =Pricing!C57 -> 0.05 | D12: =Pricing!D57 -> 0.05 | E12: =Pricing!E57 -> 0.04 | F12: =Pricing!F57 -> 0.04 | G12: =Pricing!G57 -> 0.04 | H12: =Pricing!H57 -> 0.03 | I12: =Pricing!I57 -> 0.03 | ... AO12: =Pricing!AO57 -> 0.02
A13: EOY survival rate before that yr's Qx and Lx | B13: 1 | C13: =B13*(1-B12-B11) -> #N/A | D13: =C13*(1-C12-C11) -> #N/A | E13: =D13*(1-D12-D11) -> #N/A | F13: =E13*(1-E12-E11) -> #N/A | G13: =F13*(1-F12-F11) -> #N/A | H13: =G13*(1-G12-G11) -> #N/A | I13: =H13*(1-H12-H11) -> #N/A | J13: =I13*(1-I12-I11) -> #N/A | ... AO13: =AN13*(1-AN12-AN11) -> #N/A
A14: Survival rate for coverage period | B14: =IF(B9=1,B13,0) -> 1 | C14: =IF(C9=1,C13,0) -> #N/A | D14: =IF(D9=1,D13,0) -> #N/A | E14: =IF(E9=1,E13,0) -> #N/A | F14: =IF(F9=1,F13,0) -> #N/A | G14: =IF(G9=1,G13,0) -> #N/A | H14: =IF(H9=1,H13,0) -> #N/A | I14: =IF(I9=1,I13,0) -> #N/A | ... AO14: =IF(AO9=1,AO13,0) -> 0
A16: Death benefit | B16: =Pricing!B39 -> 842000 | C16: =Pricing!C39 -> 837000 | D16: =Pricing!D39 -> 830000 | E16: =Pricing!E39 -> 821000 | F16: =Pricing!F39 -> 811000 | G16: =Pricing!G39 -> 798000 | H16: =Pricing!H39 -> 784000 | I16: =Pricing!I39 -> 767000 | ... AO16: =Pricing!AO39 -> 0
A17: Inforce death benefit (beg of year) | B17: =B16*B14 -> 842000 | C17: =C16*C14 -> #N/A | D17: =D16*D14 -> #N/A | E17: =E16*E14 -> #N/A | F17: =F16*F14 -> #N/A | G17: =G16*G14 -> #N/A | H17: =H16*H14 -> #N/A | I17: =I16*I14 -> #N/A | ... AO17: =AO16*AO14 -> 0
A18: Expected death claims (EOY before lapses) | B18: =B17*B11 -> #N/A | C18: =C17*C11 -> #N/A | D18: =D17*D11 -> #N/A | E18: =E17*E11 -> #N/A | F18: =F17*F11 -> #N/A | G18: =G17*G11 -> #N/A | H18: =H17*H11 -> #N/A | I18: =I17*I11 -> #N/A | ... AO18: =AO17*AO11 -> #N/A
A19: Inforce premium collected (beg of year) | B19: =$B$1*B14 -> #N/A | C19: =$B$1*C14 -> #N/A | D19: =$B$1*D14 -> #N/A | E19: =$B$1*E14 -> #N/A | F19: =$B$1*F14 -> #N/A | G19: =$B$1*G14 -> #N/A | H19: =$B$1*H14 -> #N/A | I19: =$B$1*I14 -> #N/A | ... AO19: =$B$1*AO14 -> #N/A
A20: Per Policy expenses | B20: =Assms!C21+Assms!C22 -> 150 | C20: =Assms!C22*C10*C14 -> #N/A | D20: =Assms!C22*D10*D14 -> #N/A | E20: =Assms!C22*E10*E14 -> #N/A | F20: =Assms!C22*F10*F14 -> #N/A | G20: =Assms!C22*G10*G14 -> #N/A | H20: =Assms!C22*H10*H14 -> #N/A | I20: =Assms!C22*I10*I14 -> #N/A | J20: =Assms!C22*J10*J14 -> #N/A | K20: =Assms!C22*K10*K14 -> #N/A | L20: =Assms!C22*L10*L14 -> #N/A | M20: =Assms!C22*M10*M14 -> #N/A | N20: =Assms!C22*N10*N14 -> #N/A | O20: =Assms!C22*O10*O14 -> #N/A | P20: =Assms!C22*P10*P14 -> #N/A | Q20: =Assms!C22*Q10*Q14 -> #N/A | R20: =Assms!C22*R10*R14 -> #N/A | S20: =Assms!C22*S10*S14 -> #N/A | T20: =Assms!C22*T10*T14 -> #N/A | U20: =Assms!C22*U10*U14 -> #N/A | V20: =Assms!C22*V10*V14 -> #N/A | W20: =Assms!C22*W10*W14 -> #N/A | X20: =Assms!C22*X10*X14 -> #N/A | Y20: =Assms!C22*Y10*Y14 -> 0 | Z20: =Assms!C22*Z10*Z14 -> 0 | AA20: =Assms!C22*AA10*AA14 -> 0 | AB20: =Assms!C22*AB10*AB14 -> 0 | AC20: =Assms!C22*AC10*AC14 -> 0 | AD20: =Assms!C22*AD10*AD14 -> 0 | AE20: =Assms!C22*AE10*AE14 -> 0 | AF20: =Assms!C22*AF10*AF14 -> 0 | AG20: =Assms!C22*AG10*AG14 -> 0 | AH20: =Assms!C22*AH10*AH14 -> 0 | AI20: =Assms!C22*AI10*AI14 -> 0 | AJ20: =Assms!C22*AJ10*AJ14 -> 0 | AK20: =Assms!C22*AK10*AK14 -> 0 | AL20: =Assms!C22*AL10*AL14 -> 0 | AM20: =Assms!C22*AM10*AM14 -> 0 | AN20: =Assms!C22*AN10*AN14 -> 0 | AO20: =Assms!C22*AO10*AO14 -> 0
A22: Profitability Calculation
A23: Inforce? | B23: =StatV!B12 -> 1 | C23: =StatV!C12 -> 1 | D23: =StatV!D12 -> 1 | E23: =StatV!E12 -> 1 | F23: =StatV!F12 -> 1 | G23: =StatV!G12 -> 1 | H23: =StatV!H12 -> 1 | I23: =StatV!I12 -> 1 | ... AO23: =StatV!AO12 -> 0
A24: Reserve per DB inforce | B24: =StatV!B203 -> #N/A | C24: =StatV!C203 -> #N/A | D24: =StatV!D203 -> #N/A | E24: =StatV!E203 -> #N/A | F24: =StatV!F203 -> #N/A | G24: =StatV!G203 -> #N/A | H24: =StatV!H203 -> #N/A | I24: =StatV!I203 -> #N/A | ... AO24: =StatV!AO203 -> #N/A
A25: Cash Value per DB inforce | B25: =CashValue!C39 -> #N/A | C25: =CashValue!D39 -> #N/A | D25: =CashValue!E39 -> #N/A | E25: =CashValue!F39 -> #N/A | F25: =CashValue!G39 -> #N/A | G25: =CashValue!H39 -> #N/A | H25: =CashValue!I39 -> #N/A | I25: =CashValue!J39 -> #N/A | ... AO25: =CashValue!AP39 -> #N/A
A26: Mortality rate | B26: =Pricing!B72 -> #N/A | C26: =Pricing!C72 -> #N/A | D26: =Pricing!D72 -> #N/A | E26: =Pricing!E72 -> #N/A | F26: =Pricing!F72 -> #N/A | G26: =Pricing!G72 -> #N/A | H26: =Pricing!H72 -> #N/A | I26: =Pricing!I72 -> #N/A | ... AO26: =Pricing!AO72 -> #N/A
A27: Lapse rate | B27: =Pricing!B69 -> 0.04 | C27: =Pricing!C69 -> 0.05 | D27: =Pricing!D69 -> 0.05 | E27: =Pricing!E69 -> 0.04 | F27: =Pricing!F69 -> 0.04 | G27: =Pricing!G69 -> 0.04 | H27: =Pricing!H69 -> 0.03 | I27: =Pricing!I69 -> 0.03 | ... AO27: =Pricing!AO69 -> 0.02
A28: tPx (beg yr) | B28: 1 | C28: =IF(C23=1,B28*(1-B26-B27),0) -> #N/A | D28: =IF(D23=1,C28*(1-C26-C27),0) -> #N/A | E28: =IF(E23=1,D28*(1-D26-D27),0) -> #N/A | F28: =IF(F23=1,E28*(1-E26-E27),0) -> #N/A | G28: =IF(G23=1,F28*(1-F26-F27),0) -> #N/A | H28: =IF(H23=1,G28*(1-G26-G27),0) -> #N/A | I28: =IF(I23=1,H28*(1-H26-H27),0) -> #N/A | J28: =IF(J23=1,I28*(1-I26-I27),0) -> #N/A | ... AO28: =IF(AO23=1,AN28*(1-AN26-AN27),0) -> 0
A29: Inforce DB (BOY) | B29: =Pricing!B39*B28 -> 842000 | C29: =Pricing!C39*C28 -> #N/A | D29: =Pricing!D39*D28 -> #N/A | E29: =Pricing!E39*E28 -> #N/A | F29: =Pricing!F39*F28 -> #N/A | G29: =Pricing!G39*G28 -> #N/A | H29: =Pricing!H39*H28 -> #N/A | I29: =Pricing!I39*I28 -> #N/A | ... AO29: =Pricing!AO39*AO28 -> 0
A30: Reserve inforce | B30: =B29*B24 -> #N/A | C30: =C29*C24 -> #N/A | D30: =D29*D24 -> #N/A | E30: =E29*E24 -> #N/A | F30: =F29*F24 -> #N/A | G30: =G29*G24 -> #N/A | H30: =H29*H24 -> #N/A | I30: =I29*I24 -> #N/A | ... AN30: =AN29*AN24 -> #N/A | AO30: 0
A31: CV inforce | B31: =B29*B25 -> #N/A | C31: =C29*C25 -> #N/A | D31: =D29*D25 -> #N/A | E31: =E29*E25 -> #N/A | F31: =F29*F25 -> #N/A | G31: =G29*G25 -> #N/A | H31: =H29*H25 -> #N/A | I31: =I29*I25 -> #N/A | ... AO31: =AO29*AO25 -> #N/A
A33: Stat book profit (customized policy)
A34: Policy Year | B34: 1 | C34: =B34+1 -> 2 | D34: =C34+1 -> 3 | E34: =D34+1 -> 4 | F34: =E34+1 -> 5 | G34: =F34+1 -> 6 | H34: =G34+1 -> 7 | I34: =H34+1 -> 8 | J34: =I34+1 -> 9 | ... AO34: =AN34+1 -> 40
A35: Premiums | B35: =$B$1*B28 -> #N/A | C35: =$B$1*C28 -> #N/A | D35: =$B$1*D28 -> #N/A | E35: =$B$1*E28 -> #N/A | F35: =$B$1*F28 -> #N/A | G35: =$B$1*G28 -> #N/A | H35: =$B$1*H28 -> #N/A | I35: =$B$1*I28 -> #N/A | ... AO35: =$B$1*AO28 -> #N/A
A36: Inv Inc reserves | B36: =Assms!$K$12*B30 -> #N/A | C36: =Assms!$K$12*C30 -> #N/A | D36: =Assms!$K$12*D30 -> #N/A | E36: =Assms!$K$12*E30 -> #N/A | F36: =Assms!$K$12*F30 -> #N/A | G36: =Assms!$K$12*G30 -> #N/A | H36: =Assms!$K$12*H30 -> #N/A | I36: =Assms!$K$12*I30 -> #N/A | ... AO36: =Assms!$K$12*AO30 -> 0
A37: Prem-based exp | B37: =(B35-B28*Assms!$C$31)*Assms!$C$12+(Assms!$C$13*B35) -> #N/A | C37: =(C35-C28*Assms!$C$31)*Assms!$C$17+(C35*(Assms!$C$16+Assms!$C$18)) -> #N/A | D37: =(D35-D28*Assms!$C$31)*Assms!$C$17+(D35*(Assms!$C$16+Assms!$C$18)) -> #N/A | E37: =(E35-E28*Assms!$C$31)*Assms!$C$17+(E35*(Assms!$C$16+Assms!$C$18)) -> #N/A | F37: =(F35-F28*Assms!$C$31)*Assms!$C$17+(F35*(Assms!$C$16+Assms!$C$18)) -> #N/A | G37: =(G35-G28*Assms!$C$31)*Assms!$C$17+(G35*(Assms!$C$16+Assms!$C$18)) -> #N/A | H37: =(H35-H28*Assms!$C$31)*Assms!$C$17+(H35*(Assms!$C$16+Assms!$C$18)) -> #N/A | I37: =(I35-I28*Assms!$C$31)*Assms!$C$17+(I35*(Assms!$C$16+Assms!$C$18)) -> #N/A | J37: =(J35-J28*Assms!$C$31)*Assms!$C$17+(J35*(Assms!$C$16+Assms!$C$18)) -> #N/A | ... AO37: =(AO35-AO28*Assms!$C$31)*Assms!$C$17+(AO35*(Assms!$C$16+Assms!$C$18)) -> #N/A
A38: Per policy Exp | B38: =Assms!C21+Assms!C22 -> 150 | C38: =IF(C29>0,Assms!$C$22*Pricing!C38*C28,0) -> #N/A | D38: =IF(D29>0,Assms!$C$22*Pricing!D38*D28,0) -> #N/A | E38: =IF(E29>0,Assms!$C$22*Pricing!E38*E28,0) -> #N/A | F38: =IF(F29>0,Assms!$C$22*Pricing!F38*F28,0) -> #N/A | G38: =IF(G29>0,Assms!$C$22*Pricing!G38*G28,0) -> #N/A | H38: =IF(H29>0,Assms!$C$22*Pricing!H38*H28,0) -> #N/A | I38: =IF(I29>0,Assms!$C$22*Pricing!I38*I28,0) -> #N/A | J38: =IF(J29>0,Assms!$C$22*Pricing!J38*J28,0) -> #N/A | ... AO38: =IF(AO29>0,Assms!$C$22*Pricing!AO38*AO28,0) -> 0
A39: Death claims | B39: =B29*B26 -> #N/A | C39: =C29*C26 -> #N/A | D39: =D29*D26 -> #N/A | E39: =E29*E26 -> #N/A | F39: =F29*F26 -> #N/A | G39: =G29*G26 -> #N/A | H39: =H29*H26 -> #N/A | I39: =I29*I26 -> #N/A | ... AO39: =AO29*AO26 -> #N/A
A40: Cash value/lapses | B40: =IF(B23=1,B29*B27*B25,"") -> #N/A | C40: =IF(C23=1,C29*C27*C25,"") -> #N/A | D40: =IF(D23=1,D29*D27*D25,"") -> #N/A | E40: =IF(E23=1,E29*E27*E25,"") -> #N/A | F40: =IF(F23=1,F29*F27*F25,"") -> #N/A | G40: =IF(G23=1,G29*G27*G25,"") -> #N/A | H40: =IF(H23=1,H29*H27*H25,"") -> #N/A | I40: =IF(I23=1,I29*I27*I25,"") -> #N/A | ... AO40: =IF(AO23=1,AO29*AO27*AO25,"")
A41: Change in resv | B41: =B30 -> #N/A | C41: =C30-B30 -> #N/A | D41: =D30-C30 -> #N/A | E41: =E30-D30 -> #N/A | F41: =F30-E30 -> #N/A | G41: =G30-F30 -> #N/A | H41: =H30-G30 -> #N/A | I41: =I30-H30 -> #N/A | J41: =J30-I30 -> #N/A | ... AO41: =AO30-AN30 -> #N/A
A43: Pre-tax stat book | B43: =(B35+B36)-SUM(B37:B41) -> #N/A | C43: =(C35+C36)-SUM(C37:C41) -> #N/A | D43: =(D35+D36)-SUM(D37:D41) -> #N/A | E43: =(E35+E36)-SUM(E37:E41) -> #N/A | F43: =(F35+F36)-SUM(F37:F41) -> #N/A | G43: =(G35+G36)-SUM(G37:G41) -> #N/A | H43: =(H35+H36)-SUM(H37:H41) -> #N/A | I43: =(I35+I36)-SUM(I37:I41) -> #N/A | ... AO43: =(AO35+AO36)-SUM(AO37:AO41) -> #N/A
A44: Income tax | B44: =B43*Assms!K13 -> #N/A | C44: =C43*Assms!K13 -> #N/A | D44: =D43*Assms!K13 -> #N/A | E44: =E43*Assms!K13 -> #N/A | F44: =F43*Assms!K13 -> #N/A | G44: =G43*Assms!K13 -> #N/A | H44: =H43*Assms!K13 -> #N/A | I44: =I43*Assms!K13 -> #N/A | J44: =J43*Assms!K13 -> #N/A | K44: =K43*Assms!K13 -> #N/A | L44: =L43*Assms!K13 -> #N/A | M44: =M43*Assms!K13 -> #N/A | N44: =N43*Assms!K13 -> #N/A | O44: =O43*Assms!K13 -> #N/A | P44: =P43*Assms!K13 -> #N/A | Q44: =Q43*Assms!K13 -> #N/A | R44: =R43*Assms!K13 -> #N/A | S44: =S43*Assms!K13 -> #N/A | T44: =T43*Assms!K13 -> #N/A | U44: =U43*Assms!K13 -> #N/A | V44: =V43*Assms!K13 -> #N/A | W44: =W43*Assms!K13 -> #N/A | X44: =X43*Assms!K13 -> #N/A | Y44: =Y43*Assms!K13 -> #N/A | Z44: =Z43*Assms!K13 -> #N/A | AA44: =AA43*Assms!K13 -> #N/A | AB44: =AB43*Assms!K13 -> #N/A | AC44: =AC43*Assms!K13 -> #N/A | AD44: =AD43*Assms!K13 -> #N/A | AE44: =AE43*Assms!K13 -> #N/A | AF44: =AF43*Assms!K13 -> #N/A | AG44: =AG43*Assms!K13 -> #N/A | AH44: =AH43*Assms!K13 -> #N/A | AI44: =AI43*Assms!K13 -> #N/A | AJ44: =AJ43*Assms!K13 -> #N/A | AK44: =AK43*Assms!K13 -> #N/A | AL44: =AL43*Assms!K13 -> #N/A | AM44: =AM43*Assms!K13 -> #N/A | AN44: =AN43*Assms!K13 -> #N/A | AO44: =AO43*Assms!K13 -> #N/A
A45: DAC tax payments | B45: =Pricing!B105*'Alt1'!$B$1/Pricing!$K$10 -> #N/A | C45: =Pricing!C105*'Alt1'!$B$1/Pricing!$K$10 -> #N/A | D45: =Pricing!D105*'Alt1'!$B$1/Pricing!$K$10 -> #N/A | E45: =Pricing!E105*'Alt1'!$B$1/Pricing!$K$10 -> #N/A | F45: =Pricing!F105*'Alt1'!$B$1/Pricing!$K$10 -> #N/A | G45: =Pricing!G105*'Alt1'!$B$1/Pricing!$K$10 -> #N/A | H45: =Pricing!H105*'Alt1'!$B$1/Pricing!$K$10 -> #N/A | I45: =Pricing!I105*'Alt1'!$B$1/Pricing!$K$10 -> #N/A | ... AO45: =Pricing!AO105*'Alt1'!$B$1/Pricing!$K$10 -> #N/A
A46: Net income | B46: =B43-B44+B45 -> #N/A | C46: =C43-C44+C45 -> #N/A | D46: =D43-D44+D45 -> #N/A | E46: =E43-E44+E45 -> #N/A | F46: =F43-F44+F45 -> #N/A | G46: =G43-G44+G45 -> #N/A | H46: =H43-H44+H45 -> #N/A | I46: =I43-I44+I45 -> #N/A | ... AO46: =AO43-AO44+AO45 -> #N/A

Sheet Alt2
A1: Calculate IRR with Alt2 premium | B1: =Pricing!M10 -> #N/A | D1: PV premium | E1: =NPV(Assms!K14,C35:AO35)+B35 -> #N/A
D2: PV book pft | E2: =NPV(Assms!K14,B46:AO46) -> #N/A
A3: Last year of coverage requested (BOY age): | B3: =Pricing!M1 -> 0 | D3: Margin | E3: =E2/E1 -> #N/A
A4: Last year of custom design model (BOY age) | B4: =Pricing!M2 -> 22
A5: Last year of coverage priced/shown | B5: =Pricing!M3 -> 0
A7: Policy Year | B7: 1 | C7: =B7+1 -> 2 | D7: =C7+1 -> 3 | E7: =D7+1 -> 4 | F7: =E7+1 -> 5 | G7: =F7+1 -> 6 | H7: =G7+1 -> 7 | I7: =H7+1 -> 8 | J7: =I7+1 -> 9 | ... AO7: =AN7+1 -> 40
A8: Age of insured | B8: =Pricing!B36 -> 0 | C8: =Pricing!C36 -> 1 | D8: =Pricing!D36 -> 2 | E8: =Pricing!E36 -> 3 | F8: =Pricing!F36 -> 4 | G8: =Pricing!G36 -> 5 | H8: =Pricing!H36 -> 6 | I8: =Pricing!I36 -> 7 | ... AO8: =Pricing!AO36 -> 39
A9: Coverage active? | B9: =Pricing!B37 -> 1 | C9: =Pricing!C37 -> 1 | D9: =Pricing!D37 -> 1 | E9: =Pricing!E37 -> 1 | F9: =Pricing!F37 -> 1 | G9: =Pricing!G37 -> 1 | H9: =Pricing!H37 -> 1 | I9: =Pricing!I37 -> 1 | ... AO9: =Pricing!AO37 -> 0
A10: Inflation factor (cumulative since issue) | B10: 1 | C10: =B10*(1+Assms!C23) -> 1.02 | D10: =C10*(1+Assms!C23) -> 1.0404 | E10: =D10*(1+Assms!C23) -> 1.061208 | F10: =E10*(1+Assms!C23) -> 1.0824322 | G10: =F10*(1+Assms!C23) -> 1.1040808 | H10: =G10*(1+Assms!C23) -> 1.1261624 | I10: =H10*(1+Assms!C23) -> 1.1486857 | J10: =I10*(1+Assms!C23) -> 1.1716594 | K10: =J10*(1+Assms!C23) -> 1.1950926 | L10: =K10*(1+Assms!C23) -> 1.2189944 | M10: =L10*(1+Assms!C23) -> 1.2433743 | N10: =M10*(1+Assms!C23) -> 1.2682418 | O10: =N10*(1+Assms!C23) -> 1.2936066 | P10: =O10*(1+Assms!C23) -> 1.3194788 | Q10: =P10*(1+Assms!C23) -> 1.3458683 | R10: =Q10*(1+Assms!C23) -> 1.3727857 | S10: =R10*(1+Assms!C23) -> 1.4002414 | T10: =S10*(1+Assms!C23) -> 1.4282462 | U10: =T10*(1+Assms!C23) -> 1.4568112 | V10: =U10*(1+Assms!C23) -> 1.4859474 | W10: =V10*(1+Assms!C23) -> 1.5156663 | X10: =W10*(1+Assms!C23) -> 1.5459797 | Y10: =X10*(1+Assms!C23) -> 1.5768993 | Z10: =Y10*(1+Assms!C23) -> 1.6084372 | AA10: =Z10*(1+Assms!C23) -> 1.640606 | AB10: =AA10*(1+Assms!C23) -> 1.6734181 | AC10: =AB10*(1+Assms!C23) -> 1.7068865 | AD10: =AC10*(1+Assms!C23) -> 1.7410242 | AE10: =AD10*(1+Assms!C23) -> 1.7758447 | AF10: =AE10*(1+Assms!C23) -> 1.8113616 | AG10: =AF10*(1+Assms!C23) -> 1.8475888 | AH10: =AG10*(1+Assms!C23) -> 1.8845406 | AI10: =AH10*(1+Assms!C23) -> 1.9222314 | AJ10: =AI10*(1+Assms!C23) -> 1.960676 | AK10: =AJ10*(1+Assms!C23) -> 1.9998896 | AL10: =AK10*(1+Assms!C23) -> 2.0398873 | AM10: =AL10*(1+Assms!C23) -> 2.0806851 | AN10: =AM10*(1+Assms!C23) -> 2.1222988 | AO10: =AN10*(1+Assms!C23) -> 2.1647448
A11: Expected mortality rate | B11: =Pricing!B42 -> #N/A | C11: =Pricing!C42 -> #N/A | D11: =Pricing!D42 -> #N/A | E11: =Pricing!E42 -> #N/A | F11: =Pricing!F42 -> #N/A | G11: =Pricing!G42 -> #N/A | H11: =Pricing!H42 -> #N/A | I11: =Pricing!I42 -> #N/A | ... AO11: =Pricing!AO42 -> #N/A
A12: Lapse rate with excess | B12: =Pricing!B59 -> 0.04 | C12: =Pricing!C59 -> 0.05 | D12: =Pricing!D59 -> 0.05 | E12: =Pricing!E59 -> 0.04 | F12: =Pricing!F59 -> 0.04 | G12: =Pricing!G59 -> 0.04 | H12: =Pricing!H59 -> 0.03 | I12: =Pricing!I59 -> 0.03 | ... AO12: =Pricing!AO59 -> 0.02
A13: EOY survival rate before that yr's Qx and Lx | B13: 1 | C13: =B13*(1-B12-B11) -> #N/A | D13: =C13*(1-C12-C11) -> #N/A | E13: =D13*(1-D12-D11) -> #N/A | F13: =E13*(1-E12-E11) -> #N/A | G13: =F13*(1-F12-F11) -> #N/A | H13: =G13*(1-G12-G11) -> #N/A | I13: =H13*(1-H12-H11) -> #N/A | J13: =I13*(1-I12-I11) -> #N/A | ... AO13: =AN13*(1-AN12-AN11) -> #N/A
A14: Survival rate for coverage period | B14: =IF(B9=1,B13,0) -> 1 | C14: =IF(C9=1,C13,0) -> #N/A | D14: =IF(D9=1,D13,0) -> #N/A | E14: =IF(E9=1,E13,0) -> #N/A | F14: =IF(F9=1,F13,0) -> #N/A | G14: =IF(G9=1,G13,0) -> #N/A | H14: =IF(H9=1,H13,0) -> #N/A | I14: =IF(I9=1,I13,0) -> #N/A | ... AO14: =IF(AO9=1,AO13,0) -> 0
A16: Death benefit | B16: =Pricing!B39 -> 842000 | C16: =Pricing!C39 -> 837000 | D16: =Pricing!D39 -> 830000 | E16: =Pricing!E39 -> 821000 | F16: =Pricing!F39 -> 811000 | G16: =Pricing!G39 -> 798000 | H16: =Pricing!H39 -> 784000 | I16: =Pricing!I39 -> 767000 | ... AO16: =Pricing!AO39 -> 0
A17: Inforce death benefit (beg of year) | B17: =B16*B14 -> 842000 | C17: =C16*C14 -> #N/A | D17: =D16*D14 -> #N/A | E17: =E16*E14 -> #N/A | F17: =F16*F14 -> #N/A | G17: =G16*G14 -> #N/A | H17: =H16*H14 -> #N/A | I17: =I16*I14 -> #N/A | ... AO17: =AO16*AO14 -> 0
A18: Expected death claims (EOY before lapses) | B18: =B17*B11 -> #N/A | C18: =C17*C11 -> #N/A | D18: =D17*D11 -> #N/A | E18: =E17*E11 -> #N/A | F18: =F17*F11 -> #N/A | G18: =G17*G11 -> #N/A | H18: =H17*H11 -> #N/A | I18: =I17*I11 -> #N/A | ... AO18: =AO17*AO11 -> #N/A
A19: Inforce premium collected (beg of year) | B19: =$B$1*B14 -> #N/A | C19: =$B$1*C14 -> #N/A | D19: =$B$1*D14 -> #N/A | E19: =$B$1*E14 -> #N/A | F19: =$B$1*F14 -> #N/A | G19: =$B$1*G14 -> #N/A | H19: =$B$1*H14 -> #N/A | I19: =$B$1*I14 -> #N/A | ... AO19: =$B$1*AO14 -> #N/A
A20: Per Policy expenses | B20: =Assms!C21+Assms!C22 -> 150 | C20: =Assms!C22*C10*C14 -> #N/A | D20: =Assms!C22*D10*D14 -> #N/A | E20: =Assms!C22*E10*E14 -> #N/A | F20: =Assms!C22*F10*F14 -> #N/A | G20: =Assms!C22*G10*G14 -> #N/A | H20: =Assms!C22*H10*H14 -> #N/A | I20: =Assms!C22*I10*I14 -> #N/A | J20: =Assms!C22*J10*J14 -> #N/A | K20: =Assms!C22*K10*K14 -> #N/A | L20: =Assms!C22*L10*L14 -> #N/A | M20: =Assms!C22*M10*M14 -> #N/A | N20: =Assms!C22*N10*N14 -> #N/A | O20: =Assms!C22*O10*O14 -> #N/A | P20: =Assms!C22*P10*P14 -> #N/A | Q20: =Assms!C22*Q10*Q14 -> #N/A | R20: =Assms!C22*R10*R14 -> #N/A | S20: =Assms!C22*S10*S14 -> #N/A | T20: =Assms!C22*T10*T14 -> #N/A | U20: =Assms!C22*U10*U14 -> #N/A | V20: =Assms!C22*V10*V14 -> #N/A | W20: =Assms!C22*W10*W14 -> #N/A | X20: =Assms!C22*X10*X14 -> #N/A | Y20: =Assms!C22*Y10*Y14 -> 0 | Z20: =Assms!C22*Z10*Z14 -> 0 | AA20: =Assms!C22*AA10*AA14 -> 0 | AB20: =Assms!C22*AB10*AB14 -> 0 | AC20: =Assms!C22*AC10*AC14 -> 0 | AD20: =Assms!C22*AD10*AD14 -> 0 | AE20: =Assms!C22*AE10*AE14 -> 0 | AF20: =Assms!C22*AF10*AF14 -> 0 | AG20: =Assms!C22*AG10*AG14 -> 0 | AH20: =Assms!C22*AH10*AH14 -> 0 | AI20: =Assms!C22*AI10*AI14 -> 0 | AJ20: =Assms!C22*AJ10*AJ14 -> 0 | AK20: =Assms!C22*AK10*AK14 -> 0 | AL20: =Assms!C22*AL10*AL14 -> 0 | AM20: =Assms!C22*AM10*AM14 -> 0 | AN20: =Assms!C22*AN10*AN14 -> 0 | AO20: =Assms!C22*AO10*AO14 -> 0
A22: Profitability Calculation
A23: Inforce? | B23: =StatV!B12 -> 1 | C23: =StatV!C12 -> 1 | D23: =StatV!D12 -> 1 | E23: =StatV!E12 -> 1 | F23: =StatV!F12 -> 1 | G23: =StatV!G12 -> 1 | H23: =StatV!H12 -> 1 | I23: =StatV!I12 -> 1 | ... AO23: =StatV!AO12 -> 0
A24: Reserve per DB inforce | B24: =StatV!B203 -> #N/A | C24: =StatV!C203 -> #N/A | D24: =StatV!D203 -> #N/A | E24: =StatV!E203 -> #N/A | F24: =StatV!F203 -> #N/A | G24: =StatV!G203 -> #N/A | H24: =StatV!H203 -> #N/A | I24: =StatV!I203 -> #N/A | ... AO24: =StatV!AO203 -> #N/A
A25: Cash Value per DB inforce | B25: =CashValue!C39 -> #N/A | C25: =CashValue!D39 -> #N/A | D25: =CashValue!E39 -> #N/A | E25: =CashValue!F39 -> #N/A | F25: =CashValue!G39 -> #N/A | G25: =CashValue!H39 -> #N/A | H25: =CashValue!I39 -> #N/A | I25: =CashValue!J39 -> #N/A | ... AO25: =CashValue!AP39 -> #N/A
A26: Mortality rate | B26: =Pricing!B72 -> #N/A | C26: =Pricing!C72 -> #N/A | D26: =Pricing!D72 -> #N/A | E26: =Pricing!E72 -> #N/A | F26: =Pricing!F72 -> #N/A | G26: =Pricing!G72 -> #N/A | H26: =Pricing!H72 -> #N/A | I26: =Pricing!I72 -> #N/A | ... AO26: =Pricing!AO72 -> #N/A
A27: Lapse rate | B27: =Pricing!B69 -> 0.04 | C27: =Pricing!C69 -> 0.05 | D27: =Pricing!D69 -> 0.05 | E27: =Pricing!E69 -> 0.04 | F27: =Pricing!F69 -> 0.04 | G27: =Pricing!G69 -> 0.04 | H27: =Pricing!H69 -> 0.03 | I27: =Pricing!I69 -> 0.03 | ... AO27: =Pricing!AO69 -> 0.02
A28: tPx (beg yr) | B28: 1 | C28: =IF(C23=1,B28*(1-B26-B27),0) -> #N/A | D28: =IF(D23=1,C28*(1-C26-C27),0) -> #N/A | E28: =IF(E23=1,D28*(1-D26-D27),0) -> #N/A | F28: =IF(F23=1,E28*(1-E26-E27),0) -> #N/A | G28: =IF(G23=1,F28*(1-F26-F27),0) -> #N/A | H28: =IF(H23=1,G28*(1-G26-G27),0) -> #N/A | I28: =IF(I23=1,H28*(1-H26-H27),0) -> #N/A | J28: =IF(J23=1,I28*(1-I26-I27),0) -> #N/A | ... AO28: =IF(AO23=1,AN28*(1-AN26-AN27),0) -> 0
A29: Inforce DB (BOY) | B29: =Pricing!B39*B28 -> 842000 | C29: =Pricing!C39*C28 -> #N/A | D29: =Pricing!D39*D28 -> #N/A | E29: =Pricing!E39*E28 -> #N/A | F29: =Pricing!F39*F28 -> #N/A | G29: =Pricing!G39*G28 -> #N/A | H29: =Pricing!H39*H28 -> #N/A | I29: =Pricing!I39*I28 -> #N/A | ... AO29: =Pricing!AO39*AO28 -> 0
A30: Reserve inforce | B30: =B29*B24 -> #N/A | C30: =C29*C24 -> #N/A | D30: =D29*D24 -> #N/A | E30: =E29*E24 -> #N/A | F30: =F29*F24 -> #N/A | G30: =G29*G24 -> #N/A | H30: =H29*H24 -> #N/A | I30: =I29*I24 -> #N/A | ... AN30: =AN29*AN24 -> #N/A | AO30: 0
A31: CV inforce | B31: =B29*B25 -> #N/A | C31: =C29*C25 -> #N/A | D31: =D29*D25 -> #N/A | E31: =E29*E25 -> #N/A | F31: =F29*F25 -> #N/A | G31: =G29*G25 -> #N/A | H31: =H29*H25 -> #N/A | I31: =I29*I25 -> #N/A | ... AO31: =AO29*AO25 -> #N/A
A33: Stat book profit (customized policy)
A34: Policy Year | B34: 1 | C34: =B34+1 -> 2 | D34: =C34+1 -> 3 | E34: =D34+1 -> 4 | F34: =E34+1 -> 5 | G34: =F34+1 -> 6 | H34: =G34+1 -> 7 | I34: =H34+1 -> 8 | J34: =I34+1 -> 9 | ... AO34: =AN34+1 -> 40
A35: Premiums | B35: =$B$1*B28 -> #N/A | C35: =$B$1*C28 -> #N/A | D35: =$B$1*D28 -> #N/A | E35: =$B$1*E28 -> #N/A | F35: =$B$1*F28 -> #N/A | G35: =$B$1*G28 -> #N/A | H35: =$B$1*H28 -> #N/A | I35: =$B$1*I28 -> #N/A | ... AO35: =$B$1*AO28 -> #N/A
A36: Inv Inc reserves | B36: =Assms!$K$12*B30 -> #N/A | C36: =Assms!$K$12*C30 -> #N/A | D36: =Assms!$K$12*D30 -> #N/A | E36: =Assms!$K$12*E30 -> #N/A | F36: =Assms!$K$12*F30 -> #N/A | G36: =Assms!$K$12*G30 -> #N/A | H36: =Assms!$K$12*H30 -> #N/A | I36: =Assms!$K$12*I30 -> #N/A | ... AO36: =Assms!$K$12*AO30 -> 0
A37: Prem-based exp | B37: =(B35-B28*Assms!$C$31)*Assms!$C$12+(Assms!$C$13*B35) -> #N/A | C37: =(C35-C28*Assms!$C$31)*Assms!$C$17+(C35*(Assms!$C$16+Assms!$C$18)) -> #N/A | D37: =(D35-D28*Assms!$C$31)*Assms!$C$17+(D35*(Assms!$C$16+Assms!$C$18)) -> #N/A | E37: =(E35-E28*Assms!$C$31)*Assms!$C$17+(E35*(Assms!$C$16+Assms!$C$18)) -> #N/A | F37: =(F35-F28*Assms!$C$31)*Assms!$C$17+(F35*(Assms!$C$16+Assms!$C$18)) -> #N/A | G37: =(G35-G28*Assms!$C$31)*Assms!$C$17+(G35*(Assms!$C$16+Assms!$C$18)) -> #N/A | H37: =(H35-H28*Assms!$C$31)*Assms!$C$17+(H35*(Assms!$C$16+Assms!$C$18)) -> #N/A | I37: =(I35-I28*Assms!$C$31)*Assms!$C$17+(I35*(Assms!$C$16+Assms!$C$18)) -> #N/A | J37: =(J35-J28*Assms!$C$31)*Assms!$C$17+(J35*(Assms!$C$16+Assms!$C$18)) -> #N/A | ... AO37: =(AO35-AO28*Assms!$C$31)*Assms!$C$17+(AO35*(Assms!$C$16+Assms!$C$18)) -> #N/A
A38: Per policy Exp | B38: =Assms!C21+Assms!C22 -> 150 | C38: =IF(C29>0,Assms!$C$22*Pricing!C38*C28,0) -> #N/A | D38: =IF(D29>0,Assms!$C$22*Pricing!D38*D28,0) -> #N/A | E38: =IF(E29>0,Assms!$C$22*Pricing!E38*E28,0) -> #N/A | F38: =IF(F29>0,Assms!$C$22*Pricing!F38*F28,0) -> #N/A | G38: =IF(G29>0,Assms!$C$22*Pricing!G38*G28,0) -> #N/A | H38: =IF(H29>0,Assms!$C$22*Pricing!H38*H28,0) -> #N/A | I38: =IF(I29>0,Assms!$C$22*Pricing!I38*I28,0) -> #N/A | J38: =IF(J29>0,Assms!$C$22*Pricing!J38*J28,0) -> #N/A | ... AO38: =IF(AO29>0,Assms!$C$22*Pricing!AO38*AO28,0) -> 0
A39: Death claims | B39: =B29*B26 -> #N/A | C39: =C29*C26 -> #N/A | D39: =D29*D26 -> #N/A | E39: =E29*E26 -> #N/A | F39: =F29*F26 -> #N/A | G39: =G29*G26 -> #N/A | H39: =H29*H26 -> #N/A | I39: =I29*I26 -> #N/A | ... AO39: =AO29*AO26 -> #N/A
A40: Cash value/lapses | B40: =IF(B23=1,B29*B27*B25,"") -> #N/A | C40: =IF(C23=1,C29*C27*C25,"") -> #N/A | D40: =IF(D23=1,D29*D27*D25,"") -> #N/A | E40: =IF(E23=1,E29*E27*E25,"") -> #N/A | F40: =IF(F23=1,F29*F27*F25,"") -> #N/A | G40: =IF(G23=1,G29*G27*G25,"") -> #N/A | H40: =IF(H23=1,H29*H27*H25,"") -> #N/A | I40: =IF(I23=1,I29*I27*I25,"") -> #N/A | ... AO40: =IF(AO23=1,AO29*AO27*AO25,"")
A41: Change in resv | B41: =B30 -> #N/A | C41: =C30-B30 -> #N/A | D41: =D30-C30 -> #N/A | E41: =E30-D30 -> #N/A | F41: =F30-E30 -> #N/A | G41: =G30-F30 -> #N/A | H41: =H30-G30 -> #N/A | I41: =I30-H30 -> #N/A | J41: =J30-I30 -> #N/A | ... AO41: =AO30-AN30 -> #N/A
A43: Pre-tax stat book | B43: =(B35+B36)-SUM(B37:B41) -> #N/A | C43: =(C35+C36)-SUM(C37:C41) -> #N/A | D43: =(D35+D36)-SUM(D37:D41) -> #N/A | E43: =(E35+E36)-SUM(E37:E41) -> #N/A | F43: =(F35+F36)-SUM(F37:F41) -> #N/A | G43: =(G35+G36)-SUM(G37:G41) -> #N/A | H43: =(H35+H36)-SUM(H37:H41) -> #N/A | I43: =(I35+I36)-SUM(I37:I41) -> #N/A | ... AO43: =(AO35+AO36)-SUM(AO37:AO41) -> #N/A
A44: Income tax | B44: =B43*Assms!K13 -> #N/A | C44: =C43*Assms!K13 -> #N/A | D44: =D43*Assms!K13 -> #N/A | E44: =E43*Assms!K13 -> #N/A | F44: =F43*Assms!K13 -> #N/A | G44: =G43*Assms!K13 -> #N/A | H44: =H43*Assms!K13 -> #N/A | I44: =I43*Assms!K13 -> #N/A | J44: =J43*Assms!K13 -> #N/A | K44: =K43*Assms!K13 -> #N/A | L44: =L43*Assms!K13 -> #N/A | M44: =M43*Assms!K13 -> #N/A | N44: =N43*Assms!K13 -> #N/A | O44: =O43*Assms!K13 -> #N/A | P44: =P43*Assms!K13 -> #N/A | Q44: =Q43*Assms!K13 -> #N/A | R44: =R43*Assms!K13 -> #N/A | S44: =S43*Assms!K13 -> #N/A | T44: =T43*Assms!K13 -> #N/A | U44: =U43*Assms!K13 -> #N/A | V44: =V43*Assms!K13 -> #N/A | W44: =W43*Assms!K13 -> #N/A | X44: =X43*Assms!K13 -> #N/A | Y44: =Y43*Assms!K13 -> #N/A | Z44: =Z43*Assms!K13 -> #N/A | AA44: =AA43*Assms!K13 -> #N/A | AB44: =AB43*Assms!K13 -> #N/A | AC44: =AC43*Assms!K13 -> #N/A | AD44: =AD43*Assms!K13 -> #N/A | AE44: =AE43*Assms!K13 -> #N/A | AF44: =AF43*Assms!K13 -> #N/A | AG44: =AG43*Assms!K13 -> #N/A | AH44: =AH43*Assms!K13 -> #N/A | AI44: =AI43*Assms!K13 -> #N/A | AJ44: =AJ43*Assms!K13 -> #N/A | AK44: =AK43*Assms!K13 -> #N/A | AL44: =AL43*Assms!K13 -> #N/A | AM44: =AM43*Assms!K13 -> #N/A | AN44: =AN43*Assms!K13 -> #N/A | AO44: =AO43*Assms!K13 -> #N/A
A45: DAC tax payments | B45: =Pricing!B105*'Alt1'!$B$1/Pricing!$K$10 -> #N/A | C45: =Pricing!C105*'Alt1'!$B$1/Pricing!$K$10 -> #N/A | D45: =Pricing!D105*'Alt1'!$B$1/Pricing!$K$10 -> #N/A | E45: =Pricing!E105*'Alt1'!$B$1/Pricing!$K$10 -> #N/A | F45: =Pricing!F105*'Alt1'!$B$1/Pricing!$K$10 -> #N/A | G45: =Pricing!G105*'Alt1'!$B$1/Pricing!$K$10 -> #N/A | H45: =Pricing!H105*'Alt1'!$B$1/Pricing!$K$10 -> #N/A | I45: =Pricing!I105*'Alt1'!$B$1/Pricing!$K$10 -> #N/A | ... AO45: =Pricing!AO105*'Alt1'!$B$1/Pricing!$K$10 -> #N/A
A46: Net income | B46: =B43-B44+B45 -> #N/A | C46: =C43-C44+C45 -> #N/A | D46: =D43-D44+D45 -> #N/A | E46: =E43-E44+E45 -> #N/A | F46: =F43-F44+F45 -> #N/A | G46: =G43-G44+G45 -> #N/A | H46: =H43-H44+H45 -> #N/A | I46: =I43-I44+I45 -> #N/A | ... AO46: =AO43-AO44+AO45 -> #N/A

Sheet Alt3
A1: Calculate IRR with Alt3 premium | B1: =Pricing!N10 -> #N/A | D1: PV premium | E1: =NPV(Assms!K14,C35:AO35)+B35 -> #N/A
D2: PV book pft | E2: =NPV(Assms!K14,B46:AO46) -> #N/A
A3: Last year of coverage requested (BOY age): | B3: =Pricing!M1 -> 0 | D3: Margin | E3: =E2/E1 -> #N/A
A4: Last year of custom design model (BOY age) | B4: =Pricing!M2 -> 22 | D4: IRR | E4: =IRR(B55:AO55,8%) -> #VALUE!
A5: Last year of coverage priced/shown | B5: =Pricing!M3 -> 0 | D5: Stat strain | E5: =B46/B35 -> #N/A
A7: Policy Year | B7: 1 | C7: =B7+1 -> 2 | D7: =C7+1 -> 3 | E7: =D7+1 -> 4 | F7: =E7+1 -> 5 | G7: =F7+1 -> 6 | H7: =G7+1 -> 7 | I7: =H7+1 -> 8 | J7: =I7+1 -> 9 | ... AO7: =AN7+1 -> 40
A8: Age of insured | B8: =Pricing!B36 -> 0 | C8: =Pricing!C36 -> 1 | D8: =Pricing!D36 -> 2 | E8: =Pricing!E36 -> 3 | F8: =Pricing!F36 -> 4 | G8: =Pricing!G36 -> 5 | H8: =Pricing!H36 -> 6 | I8: =Pricing!I36 -> 7 | ... AO8: =Pricing!AO36 -> 39
A9: Coverage active? | B9: =Pricing!B37 -> 1 | C9: =Pricing!C37 -> 1 | D9: =Pricing!D37 -> 1 | E9: =Pricing!E37 -> 1 | F9: =Pricing!F37 -> 1 | G9: =Pricing!G37 -> 1 | H9: =Pricing!H37 -> 1 | I9: =Pricing!I37 -> 1 | ... AO9: =Pricing!AO37 -> 0
A10: Inflation factor (cumulative since issue) | B10: 1 | C10: =B10*(1+Assms!C23) -> 1.02 | D10: =C10*(1+Assms!C23) -> 1.0404 | E10: =D10*(1+Assms!C23) -> 1.061208 | F10: =E10*(1+Assms!C23) -> 1.0824322 | G10: =F10*(1+Assms!C23) -> 1.1040808 | H10: =G10*(1+Assms!C23) -> 1.1261624 | I10: =H10*(1+Assms!C23) -> 1.1486857 | J10: =I10*(1+Assms!C23) -> 1.1716594 | K10: =J10*(1+Assms!C23) -> 1.1950926 | L10: =K10*(1+Assms!C23) -> 1.2189944 | M10: =L10*(1+Assms!C23) -> 1.2433743 | N10: =M10*(1+Assms!C23) -> 1.2682418 | O10: =N10*(1+Assms!C23) -> 1.2936066 | P10: =O10*(1+Assms!C23) -> 1.3194788 | Q10: =P10*(1+Assms!C23) -> 1.3458683 | R10: =Q10*(1+Assms!C23) -> 1.3727857 | S10: =R10*(1+Assms!C23) -> 1.4002414 | T10: =S10*(1+Assms!C23) -> 1.4282462 | U10: =T10*(1+Assms!C23) -> 1.4568112 | V10: =U10*(1+Assms!C23) -> 1.4859474 | W10: =V10*(1+Assms!C23) -> 1.5156663 | X10: =W10*(1+Assms!C23) -> 1.5459797 | Y10: =X10*(1+Assms!C23) -> 1.5768993 | Z10: =Y10*(1+Assms!C23) -> 1.6084372 | AA10: =Z10*(1+Assms!C23) -> 1.640606 | AB10: =AA10*(1+Assms!C23) -> 1.6734181 | AC10: =AB10*(1+Assms!C23) -> 1.7068865 | AD10: =AC10*(1+Assms!C23) -> 1.7410242 | AE10: =AD10*(1+Assms!C23) -> 1.7758447 | AF10: =AE10*(1+Assms!C23) -> 1.8113616 | AG10: =AF10*(1+Assms!C23) -> 1.8475888 | AH10: =AG10*(1+Assms!C23) -> 1.8845406 | AI10: =AH10*(1+Assms!C23) -> 1.9222314 | AJ10: =AI10*(1+Assms!C23) -> 1.960676 | AK10: =AJ10*(1+Assms!C23) -> 1.9998896 | AL10: =AK10*(1+Assms!C23) -> 2.0398873 | AM10: =AL10*(1+Assms!C23) -> 2.0806851 | AN10: =AM10*(1+Assms!C23) -> 2.1222988 | AO10: =AN10*(1+Assms!C23) -> 2.1647448
A11: Expected mortality rate | B11: =Pricing!B42 -> #N/A | C11: =Pricing!C42 -> #N/A | D11: =Pricing!D42 -> #N/A | E11: =Pricing!E42 -> #N/A | F11: =Pricing!F42 -> #N/A | G11: =Pricing!G42 -> #N/A | H11: =Pricing!H42 -> #N/A | I11: =Pricing!I42 -> #N/A | ... AO11: =Pricing!AO42 -> #N/A
A12: Lapse rate with excess | B12: =Pricing!B59 -> 0.04 | C12: =Pricing!C59 -> 0.05 | D12: =Pricing!D59 -> 0.05 | E12: =Pricing!E59 -> 0.04 | F12: =Pricing!F59 -> 0.04 | G12: =Pricing!G59 -> 0.04 | H12: =Pricing!H59 -> 0.03 | I12: =Pricing!I59 -> 0.03 | ... AO12: =Pricing!AO59 -> 0.02
A13: EOY survival rate before that yr's Qx and Lx | B13: 1 | C13: =B13*(1-B12-B11) -> #N/A | D13: =C13*(1-C12-C11) -> #N/A | E13: =D13*(1-D12-D11) -> #N/A | F13: =E13*(1-E12-E11) -> #N/A | G13: =F13*(1-F12-F11) -> #N/A | H13: =G13*(1-G12-G11) -> #N/A | I13: =H13*(1-H12-H11) -> #N/A | J13: =I13*(1-I12-I11) -> #N/A | ... AO13: =AN13*(1-AN12-AN11) -> #N/A
A14: Survival rate for coverage period | B14: =IF(B9=1,B13,0) -> 1 | C14: =IF(C9=1,C13,0) -> #N/A | D14: =IF(D9=1,D13,0) -> #N/A | E14: =IF(E9=1,E13,0) -> #N/A | F14: =IF(F9=1,F13,0) -> #N/A | G14: =IF(G9=1,G13,0) -> #N/A | H14: =IF(H9=1,H13,0) -> #N/A | I14: =IF(I9=1,I13,0) -> #N/A | ... AO14: =IF(AO9=1,AO13,0) -> 0
A16: Death benefit | B16: =Pricing!B39 -> 842000 | C16: =Pricing!C39 -> 837000 | D16: =Pricing!D39 -> 830000 | E16: =Pricing!E39 -> 821000 | F16: =Pricing!F39 -> 811000 | G16: =Pricing!G39 -> 798000 | H16: =Pricing!H39 -> 784000 | I16: =Pricing!I39 -> 767000 | ... AO16: =Pricing!AO39 -> 0
A17: Inforce death benefit (beg of year) | B17: =B16*B14 -> 842000 | C17: =C16*C14 -> #N/A | D17: =D16*D14 -> #N/A | E17: =E16*E14 -> #N/A | F17: =F16*F14 -> #N/A | G17: =G16*G14 -> #N/A | H17: =H16*H14 -> #N/A | I17: =I16*I14 -> #N/A | ... AO17: =AO16*AO14 -> 0
A18: Expected death claims (EOY before lapses) | B18: =B17*B11 -> #N/A | C18: =C17*C11 -> #N/A | D18: =D17*D11 -> #N/A | E18: =E17*E11 -> #N/A | F18: =F17*F11 -> #N/A | G18: =G17*G11 -> #N/A | H18: =H17*H11 -> #N/A | I18: =I17*I11 -> #N/A | ... AO18: =AO17*AO11 -> #N/A
A19: Inforce premium collected (beg of year) | B19: =$B$1*B14 -> #N/A | C19: =$B$1*C14 -> #N/A | D19: =$B$1*D14 -> #N/A | E19: =$B$1*E14 -> #N/A | F19: =$B$1*F14 -> #N/A | G19: =$B$1*G14 -> #N/A | H19: =$B$1*H14 -> #N/A | I19: =$B$1*I14 -> #N/A | ... AO19: =$B$1*AO14 -> #N/A
A20: Per Policy expenses | B20: =Assms!C21+Assms!C22 -> 150 | C20: =Assms!C22*C10*C14 -> #N/A | D20: =Assms!C22*D10*D14 -> #N/A | E20: =Assms!C22*E10*E14 -> #N/A | F20: =Assms!C22*F10*F14 -> #N/A | G20: =Assms!C22*G10*G14 -> #N/A | H20: =Assms!C22*H10*H14 -> #N/A | I20: =Assms!C22*I10*I14 -> #N/A | J20: =Assms!C22*J10*J14 -> #N/A | K20: =Assms!C22*K10*K14 -> #N/A | L20: =Assms!C22*L10*L14 -> #N/A | M20: =Assms!C22*M10*M14 -> #N/A | N20: =Assms!C22*N10*N14 -> #N/A | O20: =Assms!C22*O10*O14 -> #N/A | P20: =Assms!C22*P10*P14 -> #N/A | Q20: =Assms!C22*Q10*Q14 -> #N/A | R20: =Assms!C22*R10*R14 -> #N/A | S20: =Assms!C22*S10*S14 -> #N/A | T20: =Assms!C22*T10*T14 -> #N/A | U20: =Assms!C22*U10*U14 -> #N/A | V20: =Assms!C22*V10*V14 -> #N/A | W20: =Assms!C22*W10*W14 -> #N/A | X20: =Assms!C22*X10*X14 -> #N/A | Y20: =Assms!C22*Y10*Y14 -> 0 | Z20: =Assms!C22*Z10*Z14 -> 0 | AA20: =Assms!C22*AA10*AA14 -> 0 | AB20: =Assms!C22*AB10*AB14 -> 0 | AC20: =Assms!C22*AC10*AC14 -> 0 | AD20: =Assms!C22*AD10*AD14 -> 0 | AE20: =Assms!C22*AE10*AE14 -> 0 | AF20: =Assms!C22*AF10*AF14 -> 0 | AG20: =Assms!C22*AG10*AG14 -> 0 | AH20: =Assms!C22*AH10*AH14 -> 0 | AI20: =Assms!C22*AI10*AI14 -> 0 | AJ20: =Assms!C22*AJ10*AJ14 -> 0 | AK20: =Assms!C22*AK10*AK14 -> 0 | AL20: =Assms!C22*AL10*AL14 -> 0 | AM20: =Assms!C22*AM10*AM14 -> 0 | AN20: =Assms!C22*AN10*AN14 -> 0 | AO20: =Assms!C22*AO10*AO14 -> 0
A22: Profitability Calculation
A23: Inforce? | B23: =StatV!B12 -> 1 | C23: =StatV!C12 -> 1 | D23: =StatV!D12 -> 1 | E23: =StatV!E12 -> 1 | F23: =StatV!F12 -> 1 | G23: =StatV!G12 -> 1 | H23: =StatV!H12 -> 1 | I23: =StatV!I12 -> 1 | ... AO23: =StatV!AO12 -> 0
A24: Reserve per DB inforce | B24: =StatV!B203 -> #N/A | C24: =StatV!C203 -> #N/A | D24: =StatV!D203 -> #N/A | E24: =StatV!E203 -> #N/A | F24: =StatV!F203 -> #N/A | G24: =StatV!G203 -> #N/A | H24: =StatV!H203 -> #N/A | I24: =StatV!I203 -> #N/A | ... AO24: =StatV!AO203 -> #N/A
A25: Cash Value per DB inforce | B25: =CashValue!C39 -> #N/A | C25: =CashValue!D39 -> #N/A | D25: =CashValue!E39 -> #N/A | E25: =CashValue!F39 -> #N/A | F25: =CashValue!G39 -> #N/A | G25: =CashValue!H39 -> #N/A | H25: =CashValue!I39 -> #N/A | I25: =CashValue!J39 -> #N/A | ... AO25: =CashValue!AP39 -> #N/A
A26: Mortality rate | B26: =Pricing!B72 -> #N/A | C26: =Pricing!C72 -> #N/A | D26: =Pricing!D72 -> #N/A | E26: =Pricing!E72 -> #N/A | F26: =Pricing!F72 -> #N/A | G26: =Pricing!G72 -> #N/A | H26: =Pricing!H72 -> #N/A | I26: =Pricing!I72 -> #N/A | ... AO26: =Pricing!AO72 -> #N/A
A27: Lapse rate | B27: =Pricing!B69 -> 0.04 | C27: =Pricing!C69 -> 0.05 | D27: =Pricing!D69 -> 0.05 | E27: =Pricing!E69 -> 0.04 | F27: =Pricing!F69 -> 0.04 | G27: =Pricing!G69 -> 0.04 | H27: =Pricing!H69 -> 0.03 | I27: =Pricing!I69 -> 0.03 | ... AO27: =Pricing!AO69 -> 0.02
A28: tPx (beg yr) | B28: 1 | C28: =IF(C23=1,B28*(1-B26-B27),0) -> #N/A | D28: =IF(D23=1,C28*(1-C26-C27),0) -> #N/A | E28: =IF(E23=1,D28*(1-D26-D27),0) -> #N/A | F28: =IF(F23=1,E28*(1-E26-E27),0) -> #N/A | G28: =IF(G23=1,F28*(1-F26-F27),0) -> #N/A | H28: =IF(H23=1,G28*(1-G26-G27),0) -> #N/A | I28: =IF(I23=1,H28*(1-H26-H27),0) -> #N/A | J28: =IF(J23=1,I28*(1-I26-I27),0) -> #N/A | ... AO28: =IF(AO23=1,AN28*(1-AN26-AN27),0) -> 0
A29: Inforce DB (BOY) | B29: =Pricing!B39*B28 -> 842000 | C29: =Pricing!C39*C28 -> #N/A | D29: =Pricing!D39*D28 -> #N/A | E29: =Pricing!E39*E28 -> #N/A | F29: =Pricing!F39*F28 -> #N/A | G29: =Pricing!G39*G28 -> #N/A | H29: =Pricing!H39*H28 -> #N/A | I29: =Pricing!I39*I28 -> #N/A | ... AO29: =Pricing!AO39*AO28 -> 0
A30: Reserve inforce | B30: =B29*B24 -> #N/A | C30: =C29*C24 -> #N/A | D30: =D29*D24 -> #N/A | E30: =E29*E24 -> #N/A | F30: =F29*F24 -> #N/A | G30: =G29*G24 -> #N/A | H30: =H29*H24 -> #N/A | I30: =I29*I24 -> #N/A | ... AN30: =AN29*AN24 -> #N/A | AO30: 0
A31: CV inforce | B31: =B29*B25 -> #N/A | C31: =C29*C25 -> #N/A | D31: =D29*D25 -> #N/A | E31: =E29*E25 -> #N/A | F31: =F29*F25 -> #N/A | G31: =G29*G25 -> #N/A | H31: =H29*H25 -> #N/A | I31: =I29*I25 -> #N/A | ... AO31: =AO29*AO25 -> #N/A
A33: Stat book profit (customized policy)
A34: Policy Year | B34: 1 | C34: =B34+1 -> 2 | D34: =C34+1 -> 3 | E34: =D34+1 -> 4 | F34: =E34+1 -> 5 | G34: =F34+1 -> 6 | H34: =G34+1 -> 7 | I34: =H34+1 -> 8 | J34: =I34+1 -> 9 | ... AO34: =AN34+1 -> 40
A35: Premiums | B35: =$B$1*B28 -> #N/A | C35: =$B$1*C28 -> #N/A | D35: =$B$1*D28 -> #N/A | E35: =$B$1*E28 -> #N/A | F35: =$B$1*F28 -> #N/A | G35: =$B$1*G28 -> #N/A | H35: =$B$1*H28 -> #N/A | I35: =$B$1*I28 -> #N/A | ... AO35: =$B$1*AO28 -> #N/A
A36: Inv Inc reserves | B36: =Assms!$K$12*B30 -> #N/A | C36: =Assms!$K$12*C30 -> #N/A | D36: =Assms!$K$12*D30 -> #N/A | E36: =Assms!$K$12*E30 -> #N/A | F36: =Assms!$K$12*F30 -> #N/A | G36: =Assms!$K$12*G30 -> #N/A | H36: =Assms!$K$12*H30 -> #N/A | I36: =Assms!$K$12*I30 -> #N/A | ... AO36: =Assms!$K$12*AO30 -> 0
A37: Prem-based exp | B37: =(B35-B28*Assms!$C$31)*Assms!$C$12+(Assms!$C$13*B35) -> #N/A | C37: =(C35-C28*Assms!$C$31)*Assms!$C$17+(C35*(Assms!$C$16+Assms!$C$18)) -> #N/A | D37: =(D35-D28*Assms!$C$31)*Assms!$C$17+(D35*(Assms!$C$16+Assms!$C$18)) -> #N/A | E37: =(E35-E28*Assms!$C$31)*Assms!$C$17+(E35*(Assms!$C$16+Assms!$C$18)) -> #N/A | F37: =(F35-F28*Assms!$C$31)*Assms!$C$17+(F35*(Assms!$C$16+Assms!$C$18)) -> #N/A | G37: =(G35-G28*Assms!$C$31)*Assms!$C$17+(G35*(Assms!$C$16+Assms!$C$18)) -> #N/A | H37: =(H35-H28*Assms!$C$31)*Assms!$C$17+(H35*(Assms!$C$16+Assms!$C$18)) -> #N/A | I37: =(I35-I28*Assms!$C$31)*Assms!$C$17+(I35*(Assms!$C$16+Assms!$C$18)) -> #N/A | J37: =(J35-J28*Assms!$C$31)*Assms!$C$17+(J35*(Assms!$C$16+Assms!$C$18)) -> #N/A | ... AO37: =(AO35-AO28*Assms!$C$31)*Assms!$C$17+(AO35*(Assms!$C$16+Assms!$C$18)) -> #N/A
A38: Per policy Exp | B38: =Assms!C21+Assms!C22 -> 150 | C38: =IF(C29>0,Assms!$C$22*Pricing!C38*C28,0) -> #N/A | D38: =IF(D29>0,Assms!$C$22*Pricing!D38*D28,0) -> #N/A | E38: =IF(E29>0,Assms!$C$22*Pricing!E38*E28,0) -> #N/A | F38: =IF(F29>0,Assms!$C$22*Pricing!F38*F28,0) -> #N/A | G38: =IF(G29>0,Assms!$C$22*Pricing!G38*G28,0) -> #N/A | H38: =IF(H29>0,Assms!$C$22*Pricing!H38*H28,0) -> #N/A | I38: =IF(I29>0,Assms!$C$22*Pricing!I38*I28,0) -> #N/A | J38: =IF(J29>0,Assms!$C$22*Pricing!J38*J28,0) -> #N/A | ... AO38: =IF(AO29>0,Assms!$C$22*Pricing!AO38*AO28,0) -> 0
A39: Death claims | B39: =B29*B26 -> #N/A | C39: =C29*C26 -> #N/A | D39: =D29*D26 -> #N/A | E39: =E29*E26 -> #N/A | F39: =F29*F26 -> #N/A | G39: =G29*G26 -> #N/A | H39: =H29*H26 -> #N/A | I39: =I29*I26 -> #N/A | ... AO39: =AO29*AO26 -> #N/A
A40: Cash value/lapses | B40: =IF(B23=1,B29*B27*B25,"") -> #N/A | C40: =IF(C23=1,C29*C27*C25,"") -> #N/A | D40: =IF(D23=1,D29*D27*D25,"") -> #N/A | E40: =IF(E23=1,E29*E27*E25,"") -> #N/A | F40: =IF(F23=1,F29*F27*F25,"") -> #N/A | G40: =IF(G23=1,G29*G27*G25,"") -> #N/A | H40: =IF(H23=1,H29*H27*H25,"") -> #N/A | I40: =IF(I23=1,I29*I27*I25,"") -> #N/A | ... AO40: =IF(AO23=1,AO29*AO27*AO25,"")
A41: Change in resv | B41: =B30 -> #N/A | C41: =C30-B30 -> #N/A | D41: =D30-C30 -> #N/A | E41: =E30-D30 -> #N/A | F41: =F30-E30 -> #N/A | G41: =G30-F30 -> #N/A | H41: =H30-G30 -> #N/A | I41: =I30-H30 -> #N/A | J41: =J30-I30 -> #N/A | ... AO41: =AO30-AN30 -> #N/A
A43: Pre-tax stat book | B43: =(B35+B36)-SUM(B37:B41) -> #N/A | C43: =(C35+C36)-SUM(C37:C41) -> #N/A | D43: =(D35+D36)-SUM(D37:D41) -> #N/A | E43: =(E35+E36)-SUM(E37:E41) -> #N/A | F43: =(F35+F36)-SUM(F37:F41) -> #N/A | G43: =(G35+G36)-SUM(G37:G41) -> #N/A | H43: =(H35+H36)-SUM(H37:H41) -> #N/A | I43: =(I35+I36)-SUM(I37:I41) -> #N/A | ... AO43: =(AO35+AO36)-SUM(AO37:AO41) -> #N/A
A44: Income tax | B44: =B43*Assms!K13 -> #N/A | C44: =C43*Assms!K13 -> #N/A | D44: =D43*Assms!K13 -> #N/A | E44: =E43*Assms!K13 -> #N/A | F44: =F43*Assms!K13 -> #N/A | G44: =G43*Assms!K13 -> #N/A | H44: =H43*Assms!K13 -> #N/A | I44: =I43*Assms!K13 -> #N/A | J44: =J43*Assms!K13 -> #N/A | K44: =K43*Assms!K13 -> #N/A | L44: =L43*Assms!K13 -> #N/A | M44: =M43*Assms!K13 -> #N/A | N44: =N43*Assms!K13 -> #N/A | O44: =O43*Assms!K13 -> #N/A | P44: =P43*Assms!K13 -> #N/A | Q44: =Q43*Assms!K13 -> #N/A | R44: =R43*Assms!K13 -> #N/A | S44: =S43*Assms!K13 -> #N/A | T44: =T43*Assms!K13 -> #N/A | U44: =U43*Assms!K13 -> #N/A | V44: =V43*Assms!K13 -> #N/A | W44: =W43*Assms!K13 -> #N/A | X44: =X43*Assms!K13 -> #N/A | Y44: =Y43*Assms!K13 -> #N/A | Z44: =Z43*Assms!K13 -> #N/A | AA44: =AA43*Assms!K13 -> #N/A | AB44: =AB43*Assms!K13 -> #N/A | AC44: =AC43*Assms!K13 -> #N/A | AD44: =AD43*Assms!K13 -> #N/A | AE44: =AE43*Assms!K13 -> #N/A | AF44: =AF43*Assms!K13 -> #N/A | AG44: =AG43*Assms!K13 -> #N/A | AH44: =AH43*Assms!K13 -> #N/A | AI44: =AI43*Assms!K13 -> #N/A | AJ44: =AJ43*Assms!K13 -> #N/A | AK44: =AK43*Assms!K13 -> #N/A | AL44: =AL43*Assms!K13 -> #N/A | AM44: =AM43*Assms!K13 -> #N/A | AN44: =AN43*Assms!K13 -> #N/A | AO44: =AO43*Assms!K13 -> #N/A
A45: DAC tax payments | B45: =Pricing!B105*'Alt1'!$B$1/Pricing!$K$10 -> #N/A | C45: =Pricing!C105*'Alt1'!$B$1/Pricing!$K$10 -> #N/A | D45: =Pricing!D105*'Alt1'!$B$1/Pricing!$K$10 -> #N/A | E45: =Pricing!E105*'Alt1'!$B$1/Pricing!$K$10 -> #N/A | F45: =Pricing!F105*'Alt1'!$B$1/Pricing!$K$10 -> #N/A | G45: =Pricing!G105*'Alt1'!$B$1/Pricing!$K$10 -> #N/A | H45: =Pricing!H105*'Alt1'!$B$1/Pricing!$K$10 -> #N/A | I45: =Pricing!I105*'Alt1'!$B$1/Pricing!$K$10 -> #N/A | ... AO45: =Pricing!AO105*'Alt1'!$B$1/Pricing!$K$10 -> #N/A
A46: Net income | B46: =B43-B44+B45 -> #N/A | C46: =C43-C44+C45 -> #N/A | D46: =D43-D44+D45 -> #N/A | E46: =E43-E44+E45 -> #N/A | F46: =F43-F44+F45 -> #N/A | G46: =G43-G44+G45 -> #N/A | H46: =H43-H44+H45 -> #N/A | I46: =I43-I44+I45 -> #N/A | ... AO46: =AO43-AO44+AO45 -> #N/A
A47: Cumulative | B47: =B46 -> #N/A | C47: =B47+C46 -> #N/A | D47: =C47+D46 -> #N/A | E47: =D47+E46 -> #N/A | F47: =E47+F46 -> #N/A | G47: =F47+G46 -> #N/A | H47: =G47+H46 -> #N/A | I47: =H47+I46 -> #N/A | J47: =I47+J46 -> #N/A | ... AO47: =AN47+AO46 -> #N/A
A49: Risk based cap | B49: =Assms!$K$26*B30+(Assms!$K$27*B29)+(Assms!$K$28*B35) -> #N/A | C49: =Assms!$K$26*C30+(Assms!$K$27*C29)+(Assms!$K$28*C35) -> #N/A | D49: =Assms!$K$26*D30+(Assms!$K$27*D29)+(Assms!$K$28*D35) -> #N/A | E49: =Assms!$K$26*E30+(Assms!$K$27*E29)+(Assms!$K$28*E35) -> #N/A | F49: =Assms!$K$26*F30+(Assms!$K$27*F29)+(Assms!$K$28*F35) -> #N/A | G49: =Assms!$K$26*G30+(Assms!$K$27*G29)+(Assms!$K$28*G35) -> #N/A | H49: =Assms!$K$26*H30+(Assms!$K$27*H29)+(Assms!$K$28*H35) -> #N/A | I49: =Assms!$K$26*I30+(Assms!$K$27*I29)+(Assms!$K$28*I35) -> #N/A | ... AN49: =Assms!$K$26*AN30+(Assms!$K$27*AN29)+(Assms!$K$28*AN35) -> #N/A | AO49: 0
A51: Distributable profit with RBC
A52: change RBC | B52: =B49 -> #N/A | C52: =C49-B49 -> #N/A | D52: =D49-C49 -> #N/A | E52: =E49-D49 -> #N/A | F52: =F49-E49 -> #N/A | G52: =G49-F49 -> #N/A | H52: =H49-G49 -> #N/A | I52: =I49-H49 -> #N/A | J52: =J49-I49 -> #N/A | ... AO52: =AO49-AN49 -> #N/A
A53: Inv inc RBC | B53: =B49*Assms!K12 -> #N/A | C53: =C49*Assms!K12 -> #N/A | D53: =D49*Assms!K12 -> #N/A | E53: =E49*Assms!K12 -> #N/A | F53: =F49*Assms!K12 -> #N/A | G53: =G49*Assms!K12 -> #N/A | H53: =H49*Assms!K12 -> #N/A | I53: =I49*Assms!K12 -> #N/A | J53: =J49*Assms!K12 -> #N/A | K53: =K49*Assms!K12 -> #N/A | L53: =L49*Assms!K12 -> #N/A | M53: =M49*Assms!K12 -> #N/A | N53: =N49*Assms!K12 -> #N/A | O53: =O49*Assms!K12 -> #N/A | P53: =P49*Assms!K12 -> #N/A | Q53: =Q49*Assms!K12 -> #N/A | R53: =R49*Assms!K12 -> #N/A | S53: =S49*Assms!K12 -> #N/A | T53: =T49*Assms!K12 -> #N/A | U53: =U49*Assms!K12 -> #N/A | V53: =V49*Assms!K12 -> #N/A | W53: =W49*Assms!K12 -> #N/A | X53: =X49*Assms!K12 -> #N/A | Y53: =Y49*Assms!K12 -> #N/A | Z53: =Z49*Assms!K12 -> #N/A | AA53: =AA49*Assms!K12 -> #N/A | AB53: =AB49*Assms!K12 -> #N/A | AC53: =AC49*Assms!K12 -> #N/A | AD53: =AD49*Assms!K12 -> #N/A | AE53: =AE49*Assms!K12 -> #N/A | AF53: =AF49*Assms!K12 -> #N/A | AG53: =AG49*Assms!K12 -> #N/A | AH53: =AH49*Assms!K12 -> #N/A | AI53: =AI49*Assms!K12 -> #N/A | AJ53: =AJ49*Assms!K12 -> #N/A | AK53: =AK49*Assms!K12 -> #N/A | AL53: =AL49*Assms!K12 -> #N/A | AM53: =AM49*Assms!K12 -> #N/A | AN53: =AN49*Assms!K12 -> #N/A | AO53: =AO49*Assms!K12 -> 0
A54: Tax on inv inc | B54: =B53*Assms!K13 -> #N/A | C54: =C53*Assms!K13 -> #N/A | D54: =D53*Assms!K13 -> #N/A | E54: =E53*Assms!K13 -> #N/A | F54: =F53*Assms!K13 -> #N/A | G54: =G53*Assms!K13 -> #N/A | H54: =H53*Assms!K13 -> #N/A | I54: =I53*Assms!K13 -> #N/A | J54: =J53*Assms!K13 -> #N/A | K54: =K53*Assms!K13 -> #N/A | L54: =L53*Assms!K13 -> #N/A | M54: =M53*Assms!K13 -> #N/A | N54: =N53*Assms!K13 -> #N/A | O54: =O53*Assms!K13 -> #N/A | P54: =P53*Assms!K13 -> #N/A | Q54: =Q53*Assms!K13 -> #N/A | R54: =R53*Assms!K13 -> #N/A | S54: =S53*Assms!K13 -> #N/A | T54: =T53*Assms!K13 -> #N/A | U54: =U53*Assms!K13 -> #N/A | V54: =V53*Assms!K13 -> #N/A | W54: =W53*Assms!K13 -> #N/A | X54: =X53*Assms!K13 -> #N/A | Y54: =Y53*Assms!K13 -> #N/A | Z54: =Z53*Assms!K13 -> #N/A | AA54: =AA53*Assms!K13 -> #N/A | AB54: =AB53*Assms!K13 -> #N/A | AC54: =AC53*Assms!K13 -> #N/A | AD54: =AD53*Assms!K13 -> #N/A | AE54: =AE53*Assms!K13 -> #N/A | AF54: =AF53*Assms!K13 -> #N/A | AG54: =AG53*Assms!K13 -> #N/A | AH54: =AH53*Assms!K13 -> #N/A | AI54: =AI53*Assms!K13 -> #N/A | AJ54: =AJ53*Assms!K13 -> #N/A | AK54: =AK53*Assms!K13 -> #N/A | AL54: =AL53*Assms!K13 -> #N/A | AM54: =AM53*Assms!K13 -> #N/A | AN54: =AN53*Assms!K13 -> #N/A | AO54: =AO53*Assms!K13 -> 0
A55: Distrib Profit | B55: =B46-B52+B53-B54 -> #N/A | C55: =C46-C52+C53-C54 -> #N/A | D55: =D46-D52+D53-D54 -> #N/A | E55: =E46-E52+E53-E54 -> #N/A | F55: =F46-F52+F53-F54 -> #N/A | G55: =G46-G52+G53-G54 -> #N/A | H55: =H46-H52+H53-H54 -> #N/A | I55: =I46-I52+I53-I54 -> #N/A | ... AO55: =AO46-AO52+AO53-AO54 -> #N/A

Sheet StatV
A1: Reserve calculation #1: base lapse rates | I1: Note about lapse rates:
D2: Premium | F2: =Pricing!$H$30 -> #N/A | I2: VM-20 requires using best estimate lapse rates (ergo pricing) with a margin for conservatism
A3: Valuation discount rate (NPR): | B3: 0.03 | D3: PV expected Adj Gross prem | F3: =SUM(B28:AO28) -> #N/A | I3: For the margin, this model uses 50% of the estimated lapse rate (but is a variable that can be changed on the assumption tab)
A4: First Year allow for Net Prem Resv: | B4: =B21*2.5/1000 -> 2105 | D4: PV expected DB paid | F4: =NPV(B3,B30:AO30) -> #N/A | I4: Calculated reserves should be no less then that created using 6% level lapse rates
A5: Deterministic reserve discount rate | B5: =Assms!$K$12 -> 0.06 | D5: VNP factor | F5: =((F4+B4))/F3 -> #N/A | I5: Thus this model calculates reserves under 4 scenarios: pricing, more than pricing, less than pricing, and 6%
I6: Model selects the lapse rates that produced the greatest reserves over the first [5] years (the sum)
I7: There is the question whether "pricing lapse rates" is the base rates or whether they include excess lapses. This model uses excess lapses.
A8: Pricing lapse rates
A9: Year: | B9: 1 | C9: 2 | D9: 3 | E9: 4 | F9: 5 | G9: 6 | H9: 7 | I9: 8 | J9: 9 | K9: 10 | L9: 11 | M9: 12 | N9: 13 | O9: 14 | P9: 15 | Q9: 16 | R9: 17 | S9: 18 | T9: 19 | U9: 20 | V9: 21 | W9: 22 | X9: 23 | Y9: 24 | Z9: 25 | AA9: 26 | AB9: 27 | AC9: 28 | AD9: 29 | AE9: 30 | AF9: 31 | AG9: 32 | AH9: 33 | AI9: 34 | AJ9: 35 | AK9: 36 | AL9: 37 | AM9: 38 | AN9: 39 | AO9: 40
A10: Age | B10: =VQx!D1 -> 0 | C10: =B10+1 -> 1 | D10: =C10+1 -> 2 | E10: =D10+1 -> 3 | F10: =E10+1 -> 4 | G10: =F10+1 -> 5 | H10: =G10+1 -> 6 | I10: =H10+1 -> 7 | J10: =I10+1 -> 8 | ... AO10: =AN10+1 -> 39
A11: Adj GP factors | B11: 0 | C11: 0.9 | D11: 0.9 | E11: 0.9 | F11: 0.9 | G11: 1 | H11: 1 | I11: 1 | J11: 1 | K11: 1 | L11: 1 | M11: 1 | N11: 1 | O11: 1 | P11: 1 | Q11: 1 | R11: 1 | S11: 1 | T11: 1 | U11: 1 | V11: 1 | W11: 1 | X11: 1 | Y11: 1 | Z11: 1 | AA11: 1 | AB11: 1 | AC11: 1 | AD11: 1 | AE11: 1 | AF11: 1 | AG11: 1 | AH11: 1 | AI11: 1 | AJ11: 1 | AK11: 1 | AL11: 1 | AM11: 1 | AN11: 1 | AO11: 1
A12: Inforce? | B12: =Pricing!B$37 -> 1 | C12: =Pricing!C$37 -> 1 | D12: =Pricing!D$37 -> 1 | E12: =Pricing!E$37 -> 1 | F12: =Pricing!F$37 -> 1 | G12: =Pricing!G$37 -> 1 | H12: =Pricing!H$37 -> 1 | I12: =Pricing!I$37 -> 1 | ... AO12: =Pricing!AO$37 -> 0
A13: CSO qx | B13: =VQx!C$19 -> #N/A | C13: =VQx!D$19 -> #N/A | D13: =VQx!E$19 -> #N/A | E13: =VQx!F$19 -> #N/A | F13: =VQx!G$19 -> #N/A | G13: =VQx!H$19 -> #N/A | H13: =VQx!I$19 -> #N/A | I13: =VQx!J$19 -> #N/A | ... AO13: =VQx!AP$19 -> #N/A
A14: VM-20 lapses | B14: =Pricing!B57 -> 0.04 | C14: =Pricing!C57 -> 0.05 | D14: =Pricing!D57 -> 0.05 | E14: =Pricing!E57 -> 0.04 | F14: =Pricing!F57 -> 0.04 | G14: =Pricing!G57 -> 0.04 | H14: =Pricing!H57 -> 0.03 | I14: =Pricing!I57 -> 0.03 | ... AO14: =Pricing!AO57 -> 0.02
A15: tPx CSO Qx | B15: 1 | C15: =B15*(1-B13-B14)*C12 -> #N/A | D15: =C15*(1-C13-C14)*D12 -> #N/A | E15: =D15*(1-D13-D14)*E12 -> #N/A | F15: =E15*(1-E13-E14)*F12 -> #N/A | G15: =F15*(1-F13-F14)*G12 -> #N/A | H15: =G15*(1-G13-G14)*H12 -> #N/A | I15: =H15*(1-H13-H14)*I12 -> #N/A | J15: =I15*(1-I13-I14)*J12 -> #N/A | ... AO15: =AN15*(1-AN13-AN14)*AO12 -> #N/A
A16: pricing Qx | B16: =Pricing!B42 -> #N/A | C16: =Pricing!C42 -> #N/A | D16: =Pricing!D42 -> #N/A | E16: =Pricing!E42 -> #N/A | F16: =Pricing!F42 -> #N/A | G16: =Pricing!G42 -> #N/A | H16: =Pricing!H42 -> #N/A | I16: =Pricing!I42 -> #N/A | ... AO16: =Pricing!AO42 -> #N/A
A17: tPx pricing Qx | B17: 1 | C17: =B17*(1-B14-B16)*C12 -> #N/A | D17: =C17*(1-C14-C16)*D12 -> #N/A | E17: =D17*(1-D14-D16)*E12 -> #N/A | F17: =E17*(1-E14-E16)*F12 -> #N/A | G17: =F17*(1-F14-F16)*G12 -> #N/A | H17: =G17*(1-G14-G16)*H12 -> #N/A | I17: =H17*(1-H14-H16)*I12 -> #N/A | J17: =I17*(1-I14-I16)*J12 -> #N/A | ... AO17: =AN17*(1-AN14-AN16)*AO12 -> #N/A
A18: Inflation factor (cumulative since issue) | B18: 1 | C18: =B18*(1+Assms!$C$23) -> 1.02 | D18: =C18*(1+Assms!$C$23) -> 1.0404 | E18: =D18*(1+Assms!$C$23) -> 1.061208 | F18: =E18*(1+Assms!$C$23) -> 1.0824322 | G18: =F18*(1+Assms!$C$23) -> 1.1040808 | H18: =G18*(1+Assms!$C$23) -> 1.1261624 | I18: =H18*(1+Assms!$C$23) -> 1.1486857 | J18: =I18*(1+Assms!$C$23) -> 1.1716594 | ... AO18: =AN18*(1+Assms!$C$23) -> 2.1647448
A20: Custom death benefit-reserves
A21: Custom DB | B21: =Pricing!B$39 -> 842000 | C21: =Pricing!C$39 -> 837000 | D21: =Pricing!D$39 -> 830000 | E21: =Pricing!E$39 -> 821000 | F21: =Pricing!F$39 -> 811000 | G21: =Pricing!G$39 -> 798000 | H21: =Pricing!H$39 -> 784000 | I21: =Pricing!I$39 -> 767000 | ... AO21: =Pricing!AO$39 -> 0
A22: Premiums | B22: =StatV!$F$2*StatV!B$17 -> #N/A | C22: =StatV!$F$2*StatV!C17 -> #N/A | D22: =StatV!$F$2*StatV!D17 -> #N/A | E22: =StatV!$F$2*StatV!E17 -> #N/A | F22: =StatV!$F$2*StatV!F17 -> #N/A | G22: =StatV!$F$2*StatV!G17 -> #N/A | H22: =StatV!$F$2*StatV!H17 -> #N/A | I22: =StatV!$F$2*StatV!I17 -> #N/A | J22: =StatV!$F$2*StatV!J17 -> #N/A | ... AO22: =StatV!$F$2*StatV!AO17 -> #N/A
A23: Prem-based exp | B23: =(B22-B15*Assms!$C$31)*Assms!$C$12+(Assms!$C$13*B22) -> #N/A | C23: =(C22-C15*Assms!$C$31)*Assms!$C$17+(C22*(Assms!$C$16+Assms!$C$18)) -> #N/A | D23: =(D22-D15*Assms!$C$31)*Assms!$C$17+(D22*(Assms!$C$16+Assms!$C$18)) -> #N/A | E23: =(E22-E15*Assms!$C$31)*Assms!$C$17+(E22*(Assms!$C$16+Assms!$C$18)) -> #N/A | F23: =(F22-F15*Assms!$C$31)*Assms!$C$17+(F22*(Assms!$C$16+Assms!$C$18)) -> #N/A | G23: =(G22-G15*Assms!$C$31)*Assms!$C$17+(G22*(Assms!$C$16+Assms!$C$18)) -> #N/A | H23: =(H22-H15*Assms!$C$31)*Assms!$C$17+(H22*(Assms!$C$16+Assms!$C$18)) -> #N/A | I23: =(I22-I15*Assms!$C$31)*Assms!$C$17+(I22*(Assms!$C$16+Assms!$C$18)) -> #N/A | J23: =(J22-J15*Assms!$C$31)*Assms!$C$17+(J22*(Assms!$C$16+Assms!$C$18)) -> #N/A | ... AO23: =(AO22-AO15*Assms!$C$31)*Assms!$C$17+(AO22*(Assms!$C$16+Assms!$C$18)) -> #N/A
A24: Per policy Exp | B24: =Assms!$C$21+Assms!$C$22 -> 150 | C24: =IF(C21>0,Assms!$C$22*C18*C15,0) -> #N/A | D24: =IF(D21>0,Assms!$C$22*D18*D15,0) -> #N/A | E24: =IF(E21>0,Assms!$C$22*E18*E15,0) -> #N/A | F24: =IF(F21>0,Assms!$C$22*F18*F15,0) -> #N/A | G24: =IF(G21>0,Assms!$C$22*G18*G15,0) -> #N/A | H24: =IF(H21>0,Assms!$C$22*H18*H15,0) -> #N/A | I24: =IF(I21>0,Assms!$C$22*I18*I15,0) -> #N/A | J24: =IF(J21>0,Assms!$C$22*J18*J15,0) -> #N/A | ... AO24: =IF(AO21>0,Assms!$C$22*AO18*AO15,0) -> 0
A25: pricingDeath claims | B25: =B21*B16*B17 -> #N/A | C25: =C21*C16*C17 -> #N/A | D25: =D21*D16*D17 -> #N/A | E25: =E21*E16*E17 -> #N/A | F25: =F21*F16*F17 -> #N/A | G25: =G21*G16*G17 -> #N/A | H25: =H21*H16*H17 -> #N/A | I25: =I21*I16*I17 -> #N/A | ... AO25: =AO21*AO16*AO17 -> #N/A
A27: Adj Gross Prm | B27: =$F$2*B11*B12 -> #N/A | C27: =$F$2*C11*C12 -> #N/A | D27: =$F$2*D11*D12 -> #N/A | E27: =$F$2*E11*E12 -> #N/A | F27: =$F$2*F11*F12 -> #N/A | G27: =$F$2*G11*G12 -> #N/A | H27: =$F$2*H11*H12 -> #N/A | I27: =$F$2*I11*I12 -> #N/A | ... AO27: =$F$2*AO11*AO12 -> #N/A
A28: Exp Adj GPrm | B28: =B27*B15 -> #N/A | C28: =C27*C15 -> #N/A | D28: =D27*D15 -> #N/A | E28: =E27*E15 -> #N/A | F28: =F27*F15 -> #N/A | G28: =G27*G15 -> #N/A | H28: =H27*H15 -> #N/A | I28: =I27*I15 -> #N/A | ... AO28: =AO27*AO15 -> #N/A
A29: Death claims | B29: =B21*B13 -> #N/A | C29: =C21*C13 -> #N/A | D29: =D21*D13 -> #N/A | E29: =E21*E13 -> #N/A | F29: =F21*F13 -> #N/A | G29: =G21*G13 -> #N/A | H29: =H21*H13 -> #N/A | I29: =I21*I13 -> #N/A | ... AO29: =AO21*AO13 -> #N/A
A30: Exp DB paid | B30: =B29*B15 -> #N/A | C30: =C29*C15 -> #N/A | D30: =D29*D15 -> #N/A | E30: =E29*E15 -> #N/A | F30: =F29*F15 -> #N/A | G30: =G29*G15 -> #N/A | H30: =H29*H15 -> #N/A | I30: =I29*I15 -> #N/A | ... AO30: =AO29*AO15 -> #N/A
A31: Val net prem | B31: =$F$5*B27 -> #N/A | C31: =$F$5*C27 -> #N/A | D31: =$F$5*D27 -> #N/A | E31: =$F$5*E27 -> #N/A | F31: =$F$5*F27 -> #N/A | G31: =$F$5*G27 -> #N/A | H31: =$F$5*H27 -> #N/A | I31: =$F$5*I27 -> #N/A | ... AO31: =$F$5*AO27 -> #N/A
A32: Exp VNP "paid" | B32: =B31*B15 -> #N/A | C32: =C31*C15 -> #N/A | D32: =D31*D15 -> #N/A | E32: =E31*E15 -> #N/A | F32: =F31*F15 -> #N/A | G32: =G31*G15 -> #N/A | H32: =H31*H15 -> #N/A | I32: =I31*I15 -> #N/A | ... AO32: =AO31*AO15 -> #N/A
A34: Reserves Per Policy Inforce
A35: PV DB | B35: =NPV($B$3,B30:$AO30) -> #N/A | C35: =((B35*(1+$B$3)-B29)/(1-B13-B14))*C12 -> #N/A | D35: =((C35*(1+$B$3)-C29)/(1-C13-C14))*D12 -> #N/A | E35: =((D35*(1+$B$3)-D29)/(1-D13-D14))*E12 -> #N/A | F35: =((E35*(1+$B$3)-E29)/(1-E13-E14))*F12 -> #N/A | G35: =((F35*(1+$B$3)-F29)/(1-F13-F14))*G12 -> #N/A | H35: =((G35*(1+$B$3)-G29)/(1-G13-G14))*H12 -> #N/A | I35: =((H35*(1+$B$3)-H29)/(1-H13-H14))*I12 -> #N/A | J35: =((I35*(1+$B$3)-I29)/(1-I13-I14))*J12 -> #N/A | ... AO35: =((AN35*(1+$B$3)-AN29)/(1-AN13-AN14))*AO12 -> #N/A
A36: PV VNP | B36: =NPV($B$3,C32:$AO32)+B32 -> #N/A | C36: =((B36*(1+$B$3)-B31)/(1-B13-B14))*C12 -> #N/A | D36: =((C36*(1+$B$3)-C31)/(1-C13-C14))*D12 -> #N/A | E36: =((D36*(1+$B$3)-D31)/(1-D13-D14))*E12 -> #N/A | F36: =((E36*(1+$B$3)-E31)/(1-E13-E14))*F12 -> #N/A | G36: =((F36*(1+$B$3)-F31)/(1-F13-F14))*G12 -> #N/A | H36: =((G36*(1+$B$3)-G31)/(1-G13-G14))*H12 -> #N/A | I36: =((H36*(1+$B$3)-H31)/(1-H13-H14))*I12 -> #N/A | J36: =((I36*(1+$B$3)-I31)/(1-I13-I14))*J12 -> #N/A | ... AO36: =((AN36*(1+$B$3)-AN31)/(1-AN13-AN14))*AO12 -> #N/A
A37: PV(db)-PV(VNP) | B37: =B35-B36 -> #N/A | C37: =C35-C36 -> #N/A | D37: =D35-D36 -> #N/A | E37: =E35-E36 -> #N/A | F37: =F35-F36 -> #N/A | G37: =G35-G36 -> #N/A | H37: =H35-H36 -> #N/A | I37: =I35-I36 -> #N/A | ... AO37: =AO35-AO36 -> #N/A
A38: Exp inforce NPR | B38: =MAX(0,B37*B15) -> #N/A | C38: =MAX(0,C37*C15) -> #N/A | D38: =MAX(0,D37*D15) -> #N/A | E38: =MAX(0,E37*E15) -> #N/A | F38: =MAX(0,F37*F15) -> #N/A | G38: =MAX(0,G37*G15) -> #N/A | H38: =MAX(0,H37*H15) -> #N/A | I38: =MAX(0,I37*I15) -> #N/A | ... AO38: =MAX(0,AO37*AO15) -> #N/A
A40: PV Premiums | B40: =NPV($B$5,C22:$AO22)+B22 -> #N/A | C40: =NPV($B$5,D22:$AO22)+C22 -> #N/A | D40: =NPV($B$5,E22:$AO22)+D22 -> #N/A | E40: =NPV($B$5,F22:$AO22)+E22 -> #N/A | F40: =NPV($B$5,G22:$AO22)+F22 -> #N/A | G40: =NPV($B$5,H22:$AO22)+G22 -> #N/A | H40: =NPV($B$5,I22:$AO22)+H22 -> #N/A | I40: =NPV($B$5,J22:$AO22)+I22 -> #N/A | ... AN40: =NPV($B$5,AO22:$AO22)+AN22 -> #N/A | AO40: =NPV($B$5,$AO22:AP22)+AO22 -> #N/A
A41: PV Claims&exp | B41: =NPV($B$5,B25:$AO25)+B23+NPV($B$5,C23:$AO23)+B24+NPV($B$5,C24:$AO24) -> #N/A | C41: =NPV($B$5,C25:$AO25)+C23+NPV($B$5,D23:$AO23)+C24+NPV($B$5,D24:$AO24) -> #N/A | D41: =NPV($B$5,D25:$AO25)+D23+NPV($B$5,E23:$AO23)+D24+NPV($B$5,E24:$AO24) -> #N/A | E41: =NPV($B$5,E25:$AO25)+E23+NPV($B$5,F23:$AO23)+E24+NPV($B$5,F24:$AO24) -> #N/A | F41: =NPV($B$5,F25:$AO25)+F23+NPV($B$5,G23:$AO23)+F24+NPV($B$5,G24:$AO24) -> #N/A | G41: =NPV($B$5,G25:$AO25)+G23+NPV($B$5,H23:$AO23)+G24+NPV($B$5,H24:$AO24) -> #N/A | H41: =NPV($B$5,H25:$AO25)+H23+NPV($B$5,I23:$AO23)+H24+NPV($B$5,I24:$AO24) -> #N/A | I41: =NPV($B$5,I25:$AO25)+I23+NPV($B$5,J23:$AO23)+I24+NPV($B$5,J24:$AO24) -> #N/A | ... AN41: =NPV($B$5,AN25:$AO25)+AN23+NPV($B$5,AO23:$AO23)+AN24+NPV($B$5,AO24:$AO24) -> #N/A | AO41: =NPV($B$5,AO25:$AO25)+AO23+NPV($B$5,$AO23:AP23)+AO24+NPV($B$5,$AO24:AP24) -> #N/A
A42: Determ Resv | B42: =MAX(B41-B40,0) -> #N/A | C42: =MAX(C41-C40,0) -> #N/A | D42: =MAX(D41-D40,0) -> #N/A | E42: =MAX(E41-E40,0) -> #N/A | F42: =MAX(F41-F40,0) -> #N/A | G42: =MAX(G41-G40,0) -> #N/A | H42: =MAX(H41-H40,0) -> #N/A | I42: =MAX(I41-I40,0) -> #N/A | ... AO42: =MAX(AO41-AO40,0) -> #N/A
A44: CV/val Inforce | B44: =B21*B15*CashValue!C39*B12 -> #N/A | C44: =C21*C15*CashValue!D39*C12 -> #N/A | D44: =D21*D15*CashValue!E39*D12 -> #N/A | E44: =E21*E15*CashValue!F39*E12 -> #N/A | F44: =F21*F15*CashValue!G39*F12 -> #N/A | G44: =G21*G15*CashValue!H39*G12 -> #N/A | H44: =H21*H15*CashValue!I39*H12 -> #N/A | I44: =I21*I15*CashValue!J39*I12 -> #N/A | ... AO44: =AO21*AO15*CashValue!AP39*AO12 -> #N/A
A46: VM-20 Resv | B46: =MAX(B38+MAX(0,B42-B38),B44) -> #N/A | C46: =MAX(C38+MAX(0,C42-C38),C44) -> #N/A | D46: =MAX(D38+MAX(0,D42-D38),D44) -> #N/A | E46: =MAX(E38+MAX(0,E42-E38),E44) -> #N/A | F46: =MAX(F38+MAX(0,F42-F38),F44) -> #N/A | G46: =MAX(G38+MAX(0,G42-G38),G44) -> #N/A | H46: =MAX(H38+MAX(0,H42-H38),H44) -> #N/A | I46: =MAX(I38+MAX(0,I42-I38),I44) -> #N/A | ... AO46: =MAX(AO38+MAX(0,AO42-AO38),AO44) -> #N/A
A47: Reserve per inforce | B47: =IF(B21>0,B46/B15,0) -> #N/A | C47: =IF(C21>0,C46/C15,0) -> #N/A | D47: =IF(D21>0,D46/D15,0) -> #N/A | E47: =IF(E21>0,E46/E15,0) -> #N/A | F47: =IF(F21>0,F46/F15,0) -> #N/A | G47: =IF(G21>0,G46/G15,0) -> #N/A | H47: =IF(H21>0,H46/H15,0) -> #N/A | I47: =IF(I21>0,I46/I15,0) -> #N/A | ... AO47: =IF(AO21>0,AO46/AO15,0) -> 0
A48: Reserve per DB inforce | B48: =IF(B21>0,B47/B21,0) -> #N/A | C48: =IF(C21>0,C47/C21,0) -> #N/A | D48: =IF(D21>0,D47/D21,0) -> #N/A | E48: =IF(E21>0,E47/E21,0) -> #N/A | F48: =IF(F21>0,F47/F21,0) -> #N/A | G48: =IF(G21>0,G47/G21,0) -> #N/A | H48: =IF(H21>0,H47/H21,0) -> #N/A | I48: =IF(I21>0,I47/I21,0) -> #N/A | ... AO48: =IF(AO21>0,AO47/AO21,0) -> 0
A50: Reserve calculation #2: higher lapse rates
D51: Premium | F51: =Pricing!$H$30 -> #N/A
A52: Valuation discount rate (NPR): | B52: 0.03 | D52: PV expected Adj Gross prem | F52: =SUM(B77:AO77) -> #N/A
A53: First Year allow for Net Prem Resv: | B53: =B70*2.5/1000 -> 2105 | D53: PV expected DB paid | F53: =NPV(B52,B79:AO79) -> #N/A
A54: Deterministic reserve discount rate | B54: =Assms!$K$12 -> 0.06 | D54: VNP factor | F54: =((F53+B53))/F52 -> #N/A
A57: Pricing lapse rates
A58: Year: | B58: 1 | C58: 2 | D58: 3 | E58: 4 | F58: 5 | G58: 6 | H58: 7 | I58: 8 | J58: 9 | K58: 10 | L58: 11 | M58: 12 | N58: 13 | O58: 14 | P58: 15 | Q58: 16 | R58: 17 | S58: 18 | T58: 19 | U58: 20 | V58: 21 | W58: 22 | X58: 23 | Y58: 24 | Z58: 25 | AA58: 26 | AB58: 27 | AC58: 28 | AD58: 29 | AE58: 30 | AF58: 31 | AG58: 32 | AH58: 33 | AI58: 34 | AJ58: 35 | AK58: 36 | AL58: 37 | AM58: 38 | AN58: 39 | AO58: 40
A59: Age | B59: =VQx!D50 -> 0 | C59: =B59+1 -> 1 | D59: =C59+1 -> 2 | E59: =D59+1 -> 3 | F59: =E59+1 -> 4 | G59: =F59+1 -> 5 | H59: =G59+1 -> 6 | I59: =H59+1 -> 7 | J59: =I59+1 -> 8 | ... AO59: =AN59+1 -> 39
A60: Adj GP factors | B60: 0 | C60: 0.9 | D60: 0.9 | E60: 0.9 | F60: 0.9 | G60: 1 | H60: 1 | I60: 1 | J60: 1 | K60: 1 | L60: 1 | M60: 1 | N60: 1 | O60: 1 | P60: 1 | Q60: 1 | R60: 1 | S60: 1 | T60: 1 | U60: 1 | V60: 1 | W60: 1 | X60: 1 | Y60: 1 | Z60: 1 | AA60: 1 | AB60: 1 | AC60: 1 | AD60: 1 | AE60: 1 | AF60: 1 | AG60: 1 | AH60: 1 | AI60: 1 | AJ60: 1 | AK60: 1 | AL60: 1 | AM60: 1 | AN60: 1 | AO60: 1
A61: Inforce? | B61: =Pricing!B$37 -> 1 | C61: =Pricing!C$37 -> 1 | D61: =Pricing!D$37 -> 1 | E61: =Pricing!E$37 -> 1 | F61: =Pricing!F$37 -> 1 | G61: =Pricing!G$37 -> 1 | H61: =Pricing!H$37 -> 1 | I61: =Pricing!I$37 -> 1 | ... AO61: =Pricing!AO$37 -> 0
A62: CSO qx | B62: =VQx!C$19 -> #N/A | C62: =VQx!D$19 -> #N/A | D62: =VQx!E$19 -> #N/A | E62: =VQx!F$19 -> #N/A | F62: =VQx!G$19 -> #N/A | G62: =VQx!H$19 -> #N/A | H62: =VQx!I$19 -> #N/A | I62: =VQx!J$19 -> #N/A | ... AO62: =VQx!AP$19 -> #N/A
A63: VM-20 lapses | B63: =B14*(1+Assms!$K$23) -> 0.06 | C63: =C14*(1+Assms!$K$23) -> 0.075 | D63: =D14*(1+Assms!$K$23) -> 0.075 | E63: =E14*(1+Assms!$K$23) -> 0.06 | F63: =F14*(1+Assms!$K$23) -> 0.06 | G63: =G14*(1+Assms!$K$23) -> 0.06 | H63: =H14*(1+Assms!$K$23) -> 0.045 | I63: =I14*(1+Assms!$K$23) -> 0.045 | ... AO63: =AO14*(1+Assms!$K$23) -> 0.03
A64: tPx CSO Qx | B64: 1 | C64: =B64*(1-B62-B63)*C61 -> #N/A | D64: =C64*(1-C62-C63)*D61 -> #N/A | E64: =D64*(1-D62-D63)*E61 -> #N/A | F64: =E64*(1-E62-E63)*F61 -> #N/A | G64: =F64*(1-F62-F63)*G61 -> #N/A | H64: =G64*(1-G62-G63)*H61 -> #N/A | I64: =H64*(1-H62-H63)*I61 -> #N/A | J64: =I64*(1-I62-I63)*J61 -> #N/A | ... AO64: =AN64*(1-AN62-AN63)*AO61 -> #N/A
A65: pricing Qx | B65: =B16 -> #N/A | C65: =C16 -> #N/A | D65: =D16 -> #N/A | E65: =E16 -> #N/A | F65: =F16 -> #N/A | G65: =G16 -> #N/A | H65: =H16 -> #N/A | I65: =I16 -> #N/A | ... AO65: =AO16 -> #N/A
A66: tPx pricing Qx | B66: 1 | C66: =B66*(1-B63-B65)*C61 -> #N/A | D66: =C66*(1-C63-C65)*D61 -> #N/A | E66: =D66*(1-D63-D65)*E61 -> #N/A | F66: =E66*(1-E63-E65)*F61 -> #N/A | G66: =F66*(1-F63-F65)*G61 -> #N/A | H66: =G66*(1-G63-G65)*H61 -> #N/A | I66: =H66*(1-H63-H65)*I61 -> #N/A | J66: =I66*(1-I63-I65)*J61 -> #N/A | ... AO66: =AN66*(1-AN63-AN65)*AO61 -> #N/A
A67: Inflation factor (cumulative since issue) | B67: 1 | C67: =B67*(1+Assms!$C$23) -> 1.02 | D67: =C67*(1+Assms!$C$23) -> 1.0404 | E67: =D67*(1+Assms!$C$23) -> 1.061208 | F67: =E67*(1+Assms!$C$23) -> 1.0824322 | G67: =F67*(1+Assms!$C$23) -> 1.1040808 | H67: =G67*(1+Assms!$C$23) -> 1.1261624 | I67: =H67*(1+Assms!$C$23) -> 1.1486857 | J67: =I67*(1+Assms!$C$23) -> 1.1716594 | ... AO67: =AN67*(1+Assms!$C$23) -> 2.1647448
A69: Custom death benefit-reserves
A70: Custom DB | B70: =Pricing!B$39 -> 842000 | C70: =Pricing!C$39 -> 837000 | D70: =Pricing!D$39 -> 830000 | E70: =Pricing!E$39 -> 821000 | F70: =Pricing!F$39 -> 811000 | G70: =Pricing!G$39 -> 798000 | H70: =Pricing!H$39 -> 784000 | I70: =Pricing!I$39 -> 767000 | ... AO70: =Pricing!AO$39 -> 0
A71: Premiums | B71: =StatV!$F$2*StatV!B$17 -> #N/A | C71: =StatV!$F$2*StatV!C66 -> #N/A | D71: =StatV!$F$2*StatV!D66 -> #N/A | E71: =StatV!$F$2*StatV!E66 -> #N/A | F71: =StatV!$F$2*StatV!F66 -> #N/A | G71: =StatV!$F$2*StatV!G66 -> #N/A | H71: =StatV!$F$2*StatV!H66 -> #N/A | I71: =StatV!$F$2*StatV!I66 -> #N/A | J71: =StatV!$F$2*StatV!J66 -> #N/A | ... AO71: =StatV!$F$2*StatV!AO66 -> #N/A
A72: Prem-based exp | B72: =(B71-B64*Assms!$C$31)*Assms!$C$12+(Assms!$C$13*B71) -> #N/A | C72: =(C71-C64*Assms!$C$31)*Assms!$C$17+(C71*(Assms!$C$16+Assms!$C$18)) -> #N/A | D72: =(D71-D64*Assms!$C$31)*Assms!$C$17+(D71*(Assms!$C$16+Assms!$C$18)) -> #N/A | E72: =(E71-E64*Assms!$C$31)*Assms!$C$17+(E71*(Assms!$C$16+Assms!$C$18)) -> #N/A | F72: =(F71-F64*Assms!$C$31)*Assms!$C$17+(F71*(Assms!$C$16+Assms!$C$18)) -> #N/A | G72: =(G71-G64*Assms!$C$31)*Assms!$C$17+(G71*(Assms!$C$16+Assms!$C$18)) -> #N/A | H72: =(H71-H64*Assms!$C$31)*Assms!$C$17+(H71*(Assms!$C$16+Assms!$C$18)) -> #N/A | I72: =(I71-I64*Assms!$C$31)*Assms!$C$17+(I71*(Assms!$C$16+Assms!$C$18)) -> #N/A | J72: =(J71-J64*Assms!$C$31)*Assms!$C$17+(J71*(Assms!$C$16+Assms!$C$18)) -> #N/A | ... AO72: =(AO71-AO64*Assms!$C$31)*Assms!$C$17+(AO71*(Assms!$C$16+Assms!$C$18)) -> #N/A
A73: Per policy Exp | B73: =Assms!$C$21+Assms!$C$22 -> 150 | C73: =IF(C70>0,Assms!$C$22*C67*C64,0) -> #N/A | D73: =IF(D70>0,Assms!$C$22*D67*D64,0) -> #N/A | E73: =IF(E70>0,Assms!$C$22*E67*E64,0) -> #N/A | F73: =IF(F70>0,Assms!$C$22*F67*F64,0) -> #N/A | G73: =IF(G70>0,Assms!$C$22*G67*G64,0) -> #N/A | H73: =IF(H70>0,Assms!$C$22*H67*H64,0) -> #N/A | I73: =IF(I70>0,Assms!$C$22*I67*I64,0) -> #N/A | J73: =IF(J70>0,Assms!$C$22*J67*J64,0) -> #N/A | ... AO73: =IF(AO70>0,Assms!$C$22*AO67*AO64,0) -> 0
A74: pricingDeath claims | B74: =B70*B65*B66 -> #N/A | C74: =C70*C65*C66 -> #N/A | D74: =D70*D65*D66 -> #N/A | E74: =E70*E65*E66 -> #N/A | F74: =F70*F65*F66 -> #N/A | G74: =G70*G65*G66 -> #N/A | H74: =H70*H65*H66 -> #N/A | I74: =I70*I65*I66 -> #N/A | ... AO74: =AO70*AO65*AO66 -> #N/A
A76: Adj Gross Prm | B76: =$F$2*B60*B61 -> #N/A | C76: =$F$2*C60*C61 -> #N/A | D76: =$F$2*D60*D61 -> #N/A | E76: =$F$2*E60*E61 -> #N/A | F76: =$F$2*F60*F61 -> #N/A | G76: =$F$2*G60*G61 -> #N/A | H76: =$F$2*H60*H61 -> #N/A | I76: =$F$2*I60*I61 -> #N/A | ... AO76: =$F$2*AO60*AO61 -> #N/A
A77: Exp Adj GPrm | B77: =B76*B64 -> #N/A | C77: =C76*C64 -> #N/A | D77: =D76*D64 -> #N/A | E77: =E76*E64 -> #N/A | F77: =F76*F64 -> #N/A | G77: =G76*G64 -> #N/A | H77: =H76*H64 -> #N/A | I77: =I76*I64 -> #N/A | ... AO77: =AO76*AO64 -> #N/A
A78: Death claims | B78: =B70*B62 -> #N/A | C78: =C70*C62 -> #N/A | D78: =D70*D62 -> #N/A | E78: =E70*E62 -> #N/A | F78: =F70*F62 -> #N/A | G78: =G70*G62 -> #N/A | H78: =H70*H62 -> #N/A | I78: =I70*I62 -> #N/A | ... AO78: =AO70*AO62 -> #N/A
A79: Exp DB paid | B79: =B78*B64 -> #N/A | C79: =C78*C64 -> #N/A | D79: =D78*D64 -> #N/A | E79: =E78*E64 -> #N/A | F79: =F78*F64 -> #N/A | G79: =G78*G64 -> #N/A | H79: =H78*H64 -> #N/A | I79: =I78*I64 -> #N/A | ... AO79: =AO78*AO64 -> #N/A
A80: Val net prem | B80: =$F$5*B76 -> #N/A | C80: =$F$5*C76 -> #N/A | D80: =$F$5*D76 -> #N/A | E80: =$F$5*E76 -> #N/A | F80: =$F$5*F76 -> #N/A | G80: =$F$5*G76 -> #N/A | H80: =$F$5*H76 -> #N/A | I80: =$F$5*I76 -> #N/A | ... AO80: =$F$5*AO76 -> #N/A
A81: Exp VNP "paid" | B81: =B80*B64 -> #N/A | C81: =C80*C64 -> #N/A | D81: =D80*D64 -> #N/A | E81: =E80*E64 -> #N/A | F81: =F80*F64 -> #N/A | G81: =G80*G64 -> #N/A | H81: =H80*H64 -> #N/A | I81: =I80*I64 -> #N/A | ... AO81: =AO80*AO64 -> #N/A
A83: Reserves Per Policy Inforce
A84: PV DB | B84: =NPV($B$3,B79:$AO79) -> #N/A | C84: =((B84*(1+$B$3)-B78)/(1-B62-B63))*C61 -> #N/A | D84: =((C84*(1+$B$3)-C78)/(1-C62-C63))*D61 -> #N/A | E84: =((D84*(1+$B$3)-D78)/(1-D62-D63))*E61 -> #N/A | F84: =((E84*(1+$B$3)-E78)/(1-E62-E63))*F61 -> #N/A | G84: =((F84*(1+$B$3)-F78)/(1-F62-F63))*G61 -> #N/A | H84: =((G84*(1+$B$3)-G78)/(1-G62-G63))*H61 -> #N/A | I84: =((H84*(1+$B$3)-H78)/(1-H62-H63))*I61 -> #N/A | J84: =((I84*(1+$B$3)-I78)/(1-I62-I63))*J61 -> #N/A | ... AO84: =((AN84*(1+$B$3)-AN78)/(1-AN62-AN63))*AO61 -> #N/A
A85: PV VNP | B85: =NPV($B$3,C81:$AO81)+B81 -> #N/A | C85: =((B85*(1+$B$3)-B80)/(1-B62-B63))*C61 -> #N/A | D85: =((C85*(1+$B$3)-C80)/(1-C62-C63))*D61 -> #N/A | E85: =((D85*(1+$B$3)-D80)/(1-D62-D63))*E61 -> #N/A | F85: =((E85*(1+$B$3)-E80)/(1-E62-E63))*F61 -> #N/A | G85: =((F85*(1+$B$3)-F80)/(1-F62-F63))*G61 -> #N/A | H85: =((G85*(1+$B$3)-G80)/(1-G62-G63))*H61 -> #N/A | I85: =((H85*(1+$B$3)-H80)/(1-H62-H63))*I61 -> #N/A | J85: =((I85*(1+$B$3)-I80)/(1-I62-I63))*J61 -> #N/A | ... AO85: =((AN85*(1+$B$3)-AN80)/(1-AN62-AN63))*AO61 -> #N/A
A86: PV(db)-PV(VNP) | B86: =B84-B85 -> #N/A | C86: =C84-C85 -> #N/A | D86: =D84-D85 -> #N/A | E86: =E84-E85 -> #N/A | F86: =F84-F85 -> #N/A | G86: =G84-G85 -> #N/A | H86: =H84-H85 -> #N/A | I86: =I84-I85 -> #N/A | ... AO86: =AO84-AO85 -> #N/A
A87: Exp inforce NPR | B87: =MAX(0,B86*B64) -> #N/A | C87: =MAX(0,C86*C64) -> #N/A | D87: =MAX(0,D86*D64) -> #N/A | E87: =MAX(0,E86*E64) -> #N/A | F87: =MAX(0,F86*F64) -> #N/A | G87: =MAX(0,G86*G64) -> #N/A | H87: =MAX(0,H86*H64) -> #N/A | I87: =MAX(0,I86*I64) -> #N/A | ... AO87: =MAX(0,AO86*AO64) -> #N/A
A89: PV Premiums | B89: =NPV($B$5,C71:$AO71)+B71 -> #N/A | C89: =NPV($B$5,D71:$AO71)+C71 -> #N/A | D89: =NPV($B$5,E71:$AO71)+D71 -> #N/A | E89: =NPV($B$5,F71:$AO71)+E71 -> #N/A | F89: =NPV($B$5,G71:$AO71)+F71 -> #N/A | G89: =NPV($B$5,H71:$AO71)+G71 -> #N/A | H89: =NPV($B$5,I71:$AO71)+H71 -> #N/A | I89: =NPV($B$5,J71:$AO71)+I71 -> #N/A | ... AN89: =NPV($B$5,AO71:$AO71)+AN71 -> #N/A | AO89: =NPV($B$5,$AO71:AP71)+AO71 -> #N/A
A90: PV Claims&exp | B90: =NPV($B$5,B74:$AO74)+B72+NPV($B$5,C72:$AO72)+B73+NPV($B$5,C73:$AO73) -> #N/A | C90: =NPV($B$5,C74:$AO74)+C72+NPV($B$5,D72:$AO72)+C73+NPV($B$5,D73:$AO73) -> #N/A | D90: =NPV($B$5,D74:$AO74)+D72+NPV($B$5,E72:$AO72)+D73+NPV($B$5,E73:$AO73) -> #N/A | E90: =NPV($B$5,E74:$AO74)+E72+NPV($B$5,F72:$AO72)+E73+NPV($B$5,F73:$AO73) -> #N/A | F90: =NPV($B$5,F74:$AO74)+F72+NPV($B$5,G72:$AO72)+F73+NPV($B$5,G73:$AO73) -> #N/A | G90: =NPV($B$5,G74:$AO74)+G72+NPV($B$5,H72:$AO72)+G73+NPV($B$5,H73:$AO73) -> #N/A | H90: =NPV($B$5,H74:$AO74)+H72+NPV($B$5,I72:$AO72)+H73+NPV($B$5,I73:$AO73) -> #N/A | I90: =NPV($B$5,I74:$AO74)+I72+NPV($B$5,J72:$AO72)+I73+NPV($B$5,J73:$AO73) -> #N/A | ... AN90: =NPV($B$5,AN74:$AO74)+AN72+NPV($B$5,AO72:$AO72)+AN73+NPV($B$5,AO73:$AO73) -> #N/A | AO90: =NPV($B$5,AO74:$AO74)+AO72+NPV($B$5,$AO72:AP72)+AO73+NPV($B$5,$AO73:AP73) -> #N/A
A91: Determ Resv | B91: =MAX(B90-B89,0) -> #N/A | C91: =MAX(C90-C89,0) -> #N/A | D91: =MAX(D90-D89,0) -> #N/A | E91: =MAX(E90-E89,0) -> #N/A | F91: =MAX(F90-F89,0) -> #N/A | G91: =MAX(G90-G89,0) -> #N/A | H91: =MAX(H90-H89,0) -> #N/A | I91: =MAX(I90-I89,0) -> #N/A | ... AO91: =MAX(AO90-AO89,0) -> #N/A
A93: CV/val Inforce | B93: =B70*B64*CashValue!C88*B61 -> 0 | C93: =C70*C64*CashValue!D88*C61 -> #N/A | D93: =D70*D64*CashValue!E88*D61 -> #N/A | E93: =E70*E64*CashValue!F88*E61 -> #N/A | F93: =F70*F64*CashValue!G88*F61 -> #N/A | G93: =G70*G64*CashValue!H88*G61 -> #N/A | H93: =H70*H64*CashValue!I88*H61 -> #N/A | I93: =I70*I64*CashValue!J88*I61 -> #N/A | ... AO93: =AO70*AO64*CashValue!AP88*AO61 -> #N/A
A95: VM-20 Resv | B95: =MAX(B87+MAX(0,B91-B87),B93) -> #N/A | C95: =MAX(C87+MAX(0,C91-C87),C93) -> #N/A | D95: =MAX(D87+MAX(0,D91-D87),D93) -> #N/A | E95: =MAX(E87+MAX(0,E91-E87),E93) -> #N/A | F95: =MAX(F87+MAX(0,F91-F87),F93) -> #N/A | G95: =MAX(G87+MAX(0,G91-G87),G93) -> #N/A | H95: =MAX(H87+MAX(0,H91-H87),H93) -> #N/A | I95: =MAX(I87+MAX(0,I91-I87),I93) -> #N/A | ... AO95: =MAX(AO87+MAX(0,AO91-AO87),AO93) -> #N/A
A96: Reserve per inforce | B96: =IF(B70>0,B95/B64,0) -> #N/A | C96: =IF(C70>0,C95/C64,0) -> #N/A | D96: =IF(D70>0,D95/D64,0) -> #N/A | E96: =IF(E70>0,E95/E64,0) -> #N/A | F96: =IF(F70>0,F95/F64,0) -> #N/A | G96: =IF(G70>0,G95/G64,0) -> #N/A | H96: =IF(H70>0,H95/H64,0) -> #N/A | I96: =IF(I70>0,I95/I64,0) -> #N/A | ... AO96: =IF(AO70>0,AO95/AO64,0) -> 0
A97: Reserve per DB inforce | B97: =IF(B70>0,B96/B70,0) -> #N/A | C97: =IF(C70>0,C96/C70,0) -> #N/A | D97: =IF(D70>0,D96/D70,0) -> #N/A | E97: =IF(E70>0,E96/E70,0) -> #N/A | F97: =IF(F70>0,F96/F70,0) -> #N/A | G97: =IF(G70>0,G96/G70,0) -> #N/A | H97: =IF(H70>0,H96/H70,0) -> #N/A | I97: =IF(I70>0,I96/I70,0) -> #N/A | ... AO97: =IF(AO70>0,AO96/AO70,0) -> 0
A99: Reserve calculation #3: lower lapse rates
D100: Premium | F100: =Pricing!$H$30 -> #N/A
A101: Valuation discount rate (NPR): | B101: 0.03 | D101: PV expected Adj Gross prem | F101: =SUM(B126:AO126) -> #N/A
A102: First Year allow for Net Prem Resv: | B102: =B119*2.5/1000 -> 2105 | D102: PV expected DB paid | F102: =NPV(B101,B128:AO128) -> #N/A
A103: Deterministic reserve discount rate | B103: =Assms!$K$12 -> 0.06 | D103: VNP factor | F103: =((F102+B102))/F101 -> #N/A
A106: Pricing lapse rates
A107: Year: | B107: 1 | C107: 2 | D107: 3 | E107: 4 | F107: 5 | G107: 6 | H107: 7 | I107: 8 | J107: 9 | K107: 10 | L107: 11 | M107: 12 | N107: 13 | O107: 14 | P107: 15 | Q107: 16 | R107: 17 | S107: 18 | T107: 19 | U107: 20 | V107: 21 | W107: 22 | X107: 23 | Y107: 24 | Z107: 25 | AA107: 26 | AB107: 27 | AC107: 28 | AD107: 29 | AE107: 30 | AF107: 31 | AG107: 32 | AH107: 33 | AI107: 34 | AJ107: 35 | AK107: 36 | AL107: 37 | AM107: 38 | AN107: 39 | AO107: 40
A108: Age | B108: =VQx!D99 -> 0 | C108: =B108+1 -> 1 | D108: =C108+1 -> 2 | E108: =D108+1 -> 3 | F108: =E108+1 -> 4 | G108: =F108+1 -> 5 | H108: =G108+1 -> 6 | I108: =H108+1 -> 7 | J108: =I108+1 -> 8 | ... AO108: =AN108+1 -> 39
A109: Adj GP factors | B109: 0 | C109: 0.9 | D109: 0.9 | E109: 0.9 | F109: 0.9 | G109: 1 | H109: 1 | I109: 1 | J109: 1 | K109: 1 | L109: 1 | M109: 1 | N109: 1 | O109: 1 | P109: 1 | Q109: 1 | R109: 1 | S109: 1 | T109: 1 | U109: 1 | V109: 1 | W109: 1 | X109: 1 | Y109: 1 | Z109: 1 | AA109: 1 | AB109: 1 | AC109: 1 | AD109: 1 | AE109: 1 | AF109: 1 | AG109: 1 | AH109: 1 | AI109: 1 | AJ109: 1 | AK109: 1 | AL109: 1 | AM109: 1 | AN109: 1 | AO109: 1
A110: Inforce? | B110: =Pricing!B$37 -> 1 | C110: =Pricing!C$37 -> 1 | D110: =Pricing!D$37 -> 1 | E110: =Pricing!E$37 -> 1 | F110: =Pricing!F$37 -> 1 | G110: =Pricing!G$37 -> 1 | H110: =Pricing!H$37 -> 1 | I110: =Pricing!I$37 -> 1 | ... AO110: =Pricing!AO$37 -> 0
A111: CSO qx | B111: =VQx!C$19 -> #N/A | C111: =VQx!D$19 -> #N/A | D111: =VQx!E$19 -> #N/A | E111: =VQx!F$19 -> #N/A | F111: =VQx!G$19 -> #N/A | G111: =VQx!H$19 -> #N/A | H111: =VQx!I$19 -> #N/A | I111: =VQx!J$19 -> #N/A | ... AO111: =VQx!AP$19 -> #N/A
A112: VM-20 lapses | B112: =B63*(1-Assms!$K$23) -> 0.03 | C112: =C63*(1-Assms!$K$23) -> 0.0375 | D112: =D63*(1-Assms!$K$23) -> 0.0375 | E112: =E63*(1-Assms!$K$23) -> 0.03 | F112: =F63*(1-Assms!$K$23) -> 0.03 | G112: =G63*(1-Assms!$K$23) -> 0.03 | H112: =H63*(1-Assms!$K$23) -> 0.0225 | I112: =I63*(1-Assms!$K$23) -> 0.0225 | ... AO112: =AO63*(1-Assms!$K$23) -> 0.015
A113: tPx CSO Qx | B113: 1 | C113: =B113*(1-B111-B112)*C110 -> #N/A | D113: =C113*(1-C111-C112)*D110 -> #N/A | E113: =D113*(1-D111-D112)*E110 -> #N/A | F113: =E113*(1-E111-E112)*F110 -> #N/A | G113: =F113*(1-F111-F112)*G110 -> #N/A | H113: =G113*(1-G111-G112)*H110 -> #N/A | I113: =H113*(1-H111-H112)*I110 -> #N/A | J113: =I113*(1-I111-I112)*J110 -> #N/A | ... AO113: =AN113*(1-AN111-AN112)*AO110 -> #N/A
A114: pricing Qx | B114: =B16 -> #N/A | C114: =C16 -> #N/A | D114: =D16 -> #N/A | E114: =E16 -> #N/A | F114: =F16 -> #N/A | G114: =G16 -> #N/A | H114: =H16 -> #N/A | I114: =I16 -> #N/A | ... AO114: =AO16 -> #N/A
A115: tPx pricing Qx | B115: 1 | C115: =B115*(1-B112-B114)*C110 -> #N/A | D115: =C115*(1-C112-C114)*D110 -> #N/A | E115: =D115*(1-D112-D114)*E110 -> #N/A | F115: =E115*(1-E112-E114)*F110 -> #N/A | G115: =F115*(1-F112-F114)*G110 -> #N/A | H115: =G115*(1-G112-G114)*H110 -> #N/A | I115: =H115*(1-H112-H114)*I110 -> #N/A | J115: =I115*(1-I112-I114)*J110 -> #N/A | ... AO115: =AN115*(1-AN112-AN114)*AO110 -> #N/A
A116: Inflation factor (cumulative since issue) | B116: 1 | C116: =B116*(1+Assms!$C$23) -> 1.02 | D116: =C116*(1+Assms!$C$23) -> 1.0404 | E116: =D116*(1+Assms!$C$23) -> 1.061208 | F116: =E116*(1+Assms!$C$23) -> 1.0824322 | G116: =F116*(1+Assms!$C$23) -> 1.1040808 | H116: =G116*(1+Assms!$C$23) -> 1.1261624 | I116: =H116*(1+Assms!$C$23) -> 1.1486857 | J116: =I116*(1+Assms!$C$23) -> 1.1716594 | ... AO116: =AN116*(1+Assms!$C$23) -> 2.1647448
A118: Custom death benefit-reserves
A119: Custom DB | B119: =Pricing!B$39 -> 842000 | C119: =Pricing!C$39 -> 837000 | D119: =Pricing!D$39 -> 830000 | E119: =Pricing!E$39 -> 821000 | F119: =Pricing!F$39 -> 811000 | G119: =Pricing!G$39 -> 798000 | H119: =Pricing!H$39 -> 784000 | I119: =Pricing!I$39 -> 767000 | ... AO119: =Pricing!AO$39 -> 0
...

Sheet SelectLX
Z1: This section pulls in the right set of term length / IA tables based on face amount
B2: Up to 12 | C2: 13-17 | D2: 18-22 | E2: 23-27 | F2: 28-40 | V2: Super preferred NT | AI2: Preferred NT | AV2: Standard & Standard Plus Non-Tobacco | BI2: Preferred & Standard Tobacco
B3: 0 | C3: 13 | D3: 18 | E3: 23 | F3: 28 | G3: Select | I3: 20 | J3: 25 | K3: 30 | L3: 35 | M3: 40 | N3: 45 | O3: 50 | P3: 55 | Q3: 60 | R3: 65 | S3: 70 | T3: 75 | V3: 20 | W3: 25 | X3: 30 | Y3: 35 | Z3: 40 | AA3: 45 | AB3: 50 | AC3: 55 | AD3: 60 | AE3: 65 | AF3: 70 | AG3: 75 | AI3: 20 | AJ3: 25 | AK3: 30 | AL3: 35 | AM3: 40 | AN3: 45 | AO3: 50 | AP3: 55 | AQ3: 60 | AR3: 65 | AS3: 70 | AT3: 75 | AV3: 20 | AW3: 25 | AX3: 30 | AY3: 35 | AZ3: 40 | BA3: 45 | BB3: 50 | BC3: 55 | BD3: 60 | BE3: 65 | BF3: 70 | BG3: 75 | BI3: 20 | BJ3: 25 | BK3: 30 | BL3: 35 | BM3: 40 | BN3: 45 | BO3: 50 | BP3: 55 | BQ3: 60 | BR3: 65 | BS3: 70 | BT3: 75
A4: 1 | B4: =IF(Assms!$C$33<20,$I4,IF(Assms!$C$33>75,$T4,HLOOKUP(Assms!$C$33,$I$3:$T$15,$H4+1))) -> 0.08 | C4: =IF(Assms!$C$33<20,$I18,IF(Assms!$C$33>75,$T18,HLOOKUP(Assms!$C$33,$I$17:$T$34,$H18+1))) -> 0.06 | D4: =IF(Assms!$C$33<20,$I37,IF(Assms!$C$33>75,$T37,HLOOKUP(Assms!$C$33,$I$36:$T$58,$H37+1))) -> 0.06 | E4: =IF(Assms!$C$33<20,$I61,IF(Assms!$C$33>75,$T61,HLOOKUP(Assms!$C$33,$I$60:$T$87,$H61+1))) -> 0.04 | F4: =IF(Assms!$C$33<20,$I90,IF(Assms!$C$33>75,$T90,HLOOKUP(Assms!$C$33,$I$89:$T$119,$H90+1))) -> 0.06 | G4: =HLOOKUP(Assms!$C$34,$A$3:$F$41,A4+1) -> 0.04 | H4: 1 | I4: =IF(Assms!$C$36=1,V4,IF(Assms!$C$36=2,AI4,IF(Assms!$C$36=3,AV4,BI4))) -> 0.08 | J4: =IF(Assms!$C$36=1,W4,IF(Assms!$C$36=2,AJ4,IF(Assms!$C$36=3,AW4,BJ4))) -> 0.07 | K4: =IF(Assms!$C$36=1,X4,IF(Assms!$C$36=2,AK4,IF(Assms!$C$36=3,AX4,BK4))) -> 0.06 | L4: =IF(Assms!$C$36=1,Y4,IF(Assms!$C$36=2,AL4,IF(Assms!$C$36=3,AY4,BL4))) -> 0.05 | M4: =IF(Assms!$C$36=1,Z4,IF(Assms!$C$36=2,AM4,IF(Assms!$C$36=3,AZ4,BM4))) -> 0.05 | N4: =IF(Assms!$C$36=1,AA4,IF(Assms!$C$36=2,AN4,IF(Assms!$C$36=3,BA4,BN4))) -> 0.05 | O4: =IF(Assms!$C$36=1,AB4,IF(Assms!$C$36=2,AO4,IF(Assms!$C$36=3,BB4,BO4))) -> 0.05 | P4: =IF(Assms!$C$36=1,AC4,IF(Assms!$C$36=2,AP4,IF(Assms!$C$36=3,BC4,BP4))) -> 0.05 | ... T4: =IF(Assms!$C$36=1,AG4,IF(Assms!$C$36=2,AT4,IF(Assms!$C$36=3,BG4,BT4))) -> 0.07 | U4: 1 | V4: =IF(Assms!$F$37=1,LXtables!B4,IF(Assms!$F$37=2,LXtables!O4,IF(Assms!$F$37=3,LXtables!AB4,IF(Assms!$F$37=4,LXtables!AO4,IF(Assms!$F$37=5,LXtables!BB4,LXtables!BO4))))) -> 0.08 | W4: =IF(Assms!$F$37=1,LXtables!C4,IF(Assms!$F$37=2,LXtables!P4,IF(Assms!$F$37=3,LXtables!AC4,IF(Assms!$F$37=4,LXtables!AP4,IF(Assms!$F$37=5,LXtables!BC4,LXtables!BP4))))) -> 0.07 | X4: =IF(Assms!$F$37=1,LXtables!D4,IF(Assms!$F$37=2,LXtables!Q4,IF(Assms!$F$37=3,LXtables!AD4,IF(Assms!$F$37=4,LXtables!AQ4,IF(Assms!$F$37=5,LXtables!BD4,LXtables!BQ4))))) -> 0.06 | Y4: =IF(Assms!$F$37=1,LXtables!E4,IF(Assms!$F$37=2,LXtables!R4,IF(Assms!$F$37=3,LXtables!AE4,IF(Assms!$F$37=4,LXtables!AR4,IF(Assms!$F$37=5,LXtables!BE4,LXtables!BR4))))) -> 0.05 | Z4: =IF(Assms!$F$37=1,LXtables!F4,IF(Assms!$F$37=2,LXtables!S4,IF(Assms!$F$37=3,LXtables!AF4,IF(Assms!$F$37=4,LXtables!AS4,IF(Assms!$F$37=5,LXtables!BF4,LXtables!BS4))))) -> 0.05 | AA4: =IF(Assms!$F$37=1,LXtables!G4,IF(Assms!$F$37=2,LXtables!T4,IF(Assms!$F$37=3,LXtables!AG4,IF(Assms!$F$37=4,LXtables!AT4,IF(Assms!$F$37=5,LXtables!BG4,LXtables!BT4))))) -> 0.05 | AB4: =IF(Assms!$F$37=1,LXtables!H4,IF(Assms!$F$37=2,LXtables!U4,IF(Assms!$F$37=3,LXtables!AH4,IF(Assms!$F$37=4,LXtables!AU4,IF(Assms!$F$37=5,LXtables!BH4,LXtables!BU4))))) -> 0.05 | AC4: =IF(Assms!$F$37=1,LXtables!I4,IF(Assms!$F$37=2,LXtables!V4,IF(Assms!$F$37=3,LXtables!AI4,IF(Assms!$F$37=4,LXtables!AV4,IF(Assms!$F$37=5,LXtables!BI4,LXtables!BV4))))) -> 0.05 | ... AG4: =IF(Assms!$F$37=1,LXtables!M4,IF(Assms!$F$37=2,LXtables!Z4,IF(Assms!$F$37=3,LXtables!AM4,IF(Assms!$F$37=4,LXtables!AZ4,IF(Assms!$F$37=5,LXtables!BM4,LXtables!BZ4))))) -> 0.07 | AH4: 1 | AI4: =IF(Assms!$F$37=1,LXtables!CC4,IF(Assms!$F$37=2,LXtables!CP4,IF(Assms!$F$37=3,LXtables!DC4,IF(Assms!$F$37=4,LXtables!DP4,IF(Assms!$F$37=5,LXtables!EC4,LXtables!EP4))))) -> 0.1 | AJ4: =IF(Assms!$F$37=1,LXtables!CD4,IF(Assms!$F$37=2,LXtables!CQ4,IF(Assms!$F$37=3,LXtables!DD4,IF(Assms!$F$37=4,LXtables!DQ4,IF(Assms!$F$37=5,LXtables!ED4,LXtables!EQ4))))) -> 0.09 | AK4: =IF(Assms!$F$37=1,LXtables!CE4,IF(Assms!$F$37=2,LXtables!CR4,IF(Assms!$F$37=3,LXtables!DE4,IF(Assms!$F$37=4,LXtables!DR4,IF(Assms!$F$37=5,LXtables!EE4,LXtables!ER4))))) -> 0.07 | AL4: =IF(Assms!$F$37=1,LXtables!CF4,IF(Assms!$F$37=2,LXtables!CS4,IF(Assms!$F$37=3,LXtables!DF4,IF(Assms!$F$37=4,LXtables!DS4,IF(Assms!$F$37=5,LXtables!EF4,LXtables!ES4))))) -> 0.07 | AM4: =IF(Assms!$F$37=1,LXtables!CG4,IF(Assms!$F$37=2,LXtables!CT4,IF(Assms!$F$37=3,LXtables!DG4,IF(Assms!$F$37=4,LXtables!DT4,IF(Assms!$F$37=5,LXtables!EG4,LXtables!ET4))))) -> 0.06 | AN4: =IF(Assms!$F$37=1,LXtables!CH4,IF(Assms!$F$37=2,LXtables!CU4,IF(Assms!$F$37=3,LXtables!DH4,IF(Assms!$F$37=4,LXtables!DU4,IF(Assms!$F$37=5,LXtables!EH4,LXtables!EU4))))) -> 0.06 | AO4: =IF(Assms!$F$37=1,LXtables!CI4,IF(Assms!$F$37=2,LXtables!CV4,IF(Assms!$F$37=3,LXtables!DI4,IF(Assms!$F$37=4,LXtables!DV4,IF(Assms!$F$37=5,LXtables!EI4,LXtables!EV4))))) -> 0.07 | AP4: =IF(Assms!$F$37=1,LXtables!CJ4,IF(Assms!$F$37=2,LXtables!CW4,IF(Assms!$F$37=3,LXtables!DJ4,IF(Assms!$F$37=4,LXtables!DW4,IF(Assms!$F$37=5,LXtables!EJ4,LXtables!EW4))))) -> 0.07 | ... AT4: =IF(Assms!$F$37=1,LXtables!CN4,IF(Assms!$F$37=2,LXtables!DA4,IF(Assms!$F$37=3,LXtables!DN4,IF(Assms!$F$37=4,LXtables!EA4,IF(Assms!$F$37=5,LXtables!EN4,LXtables!FA4))))) -> 0.09 | AU4: 1 | AV4: =IF(Assms!$F$37=1,LXtables!FD4,IF(Assms!$F$37=2,LXtables!FQ4,IF(Assms!$F$37=3,LXtables!GD4,IF(Assms!$F$37=4,LXtables!GQ4,IF(Assms!$F$37=5,LXtables!HD4,LXtables!HQ4))))) -> 0.13 | AW4: =IF(Assms!$F$37=1,LXtables!FE4,IF(Assms!$F$37=2,LXtables!FR4,IF(Assms!$F$37=3,LXtables!GE4,IF(Assms!$F$37=4,LXtables!GR4,IF(Assms!$F$37=5,LXtables!HE4,LXtables!HR4))))) -> 0.12 | AX4: =IF(Assms!$F$37=1,LXtables!FF4,IF(Assms!$F$37=2,LXtables!FS4,IF(Assms!$F$37=3,LXtables!GF4,IF(Assms!$F$37=4,LXtables!GS4,IF(Assms!$F$37=5,LXtables!HF4,LXtables!HS4))))) -> 0.1 | AY4: =IF(Assms!$F$37=1,LXtables!FG4,IF(Assms!$F$37=2,LXtables!FT4,IF(Assms!$F$37=3,LXtables!GG4,IF(Assms!$F$37=4,LXtables!GT4,IF(Assms!$F$37=5,LXtables!HG4,LXtables!HT4))))) -> 0.09 | AZ4: =IF(Assms!$F$37=1,LXtables!FH4,IF(Assms!$F$37=2,LXtables!FU4,IF(Assms!$F$37=3,LXtables!GH4,IF(Assms!$F$37=4,LXtables!GU4,IF(Assms!$F$37=5,LXtables!HH4,LXtables!HU4))))) -> 0.08 | BA4: =IF(Assms!$F$37=1,LXtables!FI4,IF(Assms!$F$37=2,LXtables!FV4,IF(Assms!$F$37=3,LXtables!GI4,IF(Assms!$F$37=4,LXtables!GV4,IF(Assms!$F$37=5,LXtables!HI4,LXtables!HV4))))) -> 0.09 | BB4: =IF(Assms!$F$37=1,LXtables!FJ4,IF(Assms!$F$37=2,LXtables!FW4,IF(Assms!$F$37=3,LXtables!GJ4,IF(Assms!$F$37=4,LXtables!GW4,IF(Assms!$F$37=5,LXtables!HJ4,LXtables!HW4))))) -> 0.09 | BC4: =IF(Assms!$F$37=1,LXtables!FK4,IF(Assms!$F$37=2,LXtables!FX4,IF(Assms!$F$37=3,LXtables!GK4,IF(Assms!$F$37=4,LXtables!GX4,IF(Assms!$F$37=5,LXtables!HK4,LXtables!HX4))))) -> 0.09 | ... BG4: =IF(Assms!$F$37=1,LXtables!FO4,IF(Assms!$F$37=2,LXtables!GB4,IF(Assms!$F$37=3,LXtables!GO4,IF(Assms!$F$37=4,LXtables!HB4,IF(Assms!$F$37=5,LXtables!HO4,LXtables!IB4))))) -> 0.12 | BH4: 1 | BI4: =IF(Assms!$F$37=1,LXtables!IE4,IF(Assms!$F$37=2,LXtables!IR4,IF(Assms!$F$37=3,LXtables!JE4,IF(Assms!$F$37=4,LXtables!JR4,IF(Assms!$F$37=5,LXtables!KE4,LXtables!KR4))))) -> 0.2 | BJ4: =IF(Assms!$F$37=1,LXtables!IF4,IF(Assms!$F$37=2,LXtables!IS4,IF(Assms!$F$37=3,LXtables!JF4,IF(Assms!$F$37=4,LXtables!JS4,IF(Assms!$F$37=5,LXtables!KF4,LXtables!KS4))))) -> 0.19 | BK4: =IF(Assms!$F$37=1,LXtables!IG4,IF(Assms!$F$37=2,LXtables!IT4,IF(Assms!$F$37=3,LXtables!JG4,IF(Assms!$F$37=4,LXtables!JT4,IF(Assms!$F$37=5,LXtables!KG4,LXtables!KT4))))) -> 0.15 | BL4: =IF(Assms!$F$37=1,LXtables!IH4,IF(Assms!$F$37=2,LXtables!IU4,IF(Assms!$F$37=3,LXtables!JH4,IF(Assms!$F$37=4,LXtables!JU4,IF(Assms!$F$37=5,LXtables!KH4,LXtables!KU4))))) -> 0.13 | BM4: =IF(Assms!$F$37=1,LXtables!II4,IF(Assms!$F$37=2,LXtables!IV4,IF(Assms!$F$37=3,LXtables!JI4,IF(Assms!$F$37=4,LXtables!JV4,IF(Assms!$F$37=5,LXtables!KI4,LXtables!KV4))))) -> 0.13 | BN4: =IF(Assms!$F$37=1,LXtables!IJ4,IF(Assms!$F$37=2,LXtables!IW4,IF(Assms!$F$37=3,LXtables!JJ4,IF(Assms!$F$37=4,LXtables!JW4,IF(Assms!$F$37=5,LXtables!KJ4,LXtables!KW4))))) -> 0.13 | BO4: =IF(Assms!$F$37=1,LXtables!IK4,IF(Assms!$F$37=2,LXtables!IX4,IF(Assms!$F$37=3,LXtables!JK4,IF(Assms!$F$37=4,LXtables!JX4,IF(Assms!$F$37=5,LXtables!KK4,LXtables!KX4))))) -> 0.14 | BP4: =IF(Assms!$F$37=1,LXtables!IL4,IF(Assms!$F$37=2,LXtables!IY4,IF(Assms!$F$37=3,LXtables!JL4,IF(Assms!$F$37=4,LXtables!JY4,IF(Assms!$F$37=5,LXtables!KL4,LXtables!KY4))))) -> 0.14 | ... BT4: =IF(Assms!$F$37=1,LXtables!IP4,IF(Assms!$F$37=2,LXtables!JC4,IF(Assms!$F$37=3,LXtables!JP4,IF(Assms!$F$37=4,LXtables!KC4,IF(Assms!$F$37=5,LXtables!KP4,LXtables!LC4))))) -> 0.18
A5: 2 | B5: =IF(Assms!$C$33<20,$I5,IF(Assms!$C$33>75,$T5,HLOOKUP(Assms!$C$33,$I$3:$T$15,$H5+1))) -> 0.08 | C5: =IF(Assms!$C$33<20,$I19,IF(Assms!$C$33>75,$T19,HLOOKUP(Assms!$C$33,$I$17:$T$34,$H19+1))) -> 0.05 | D5: =IF(Assms!$C$33<20,$I38,IF(Assms!$C$33>75,$T38,HLOOKUP(Assms!$C$33,$I$36:$T$58,$H38+1))) -> 0.06 | E5: =IF(Assms!$C$33<20,$I62,IF(Assms!$C$33>75,$T62,HLOOKUP(Assms!$C$33,$I$60:$T$87,$H62+1))) -> 0.05 | F5: =IF(Assms!$C$33<20,$I91,IF(Assms!$C$33>75,$T91,HLOOKUP(Assms!$C$33,$I$89:$T$119,$H91+1))) -> 0.06 | G5: =HLOOKUP(Assms!$C$34,$A$3:$F$41,A5+1) -> 0.05 | H5: 2 | I5: =IF(Assms!$C$36=1,V5,IF(Assms!$C$36=2,AI5,IF(Assms!$C$36=3,AV5,BI5))) -> 0.08 | J5: =IF(Assms!$C$36=1,W5,IF(Assms!$C$36=2,AJ5,IF(Assms!$C$36=3,AW5,BJ5))) -> 0.07 | K5: =IF(Assms!$C$36=1,X5,IF(Assms!$C$36=2,AK5,IF(Assms!$C$36=3,AX5,BK5))) -> 0.06 | L5: =IF(Assms!$C$36=1,Y5,IF(Assms!$C$36=2,AL5,IF(Assms!$C$36=3,AY5,BL5))) -> 0.05 | M5: =IF(Assms!$C$36=1,Z5,IF(Assms!$C$36=2,AM5,IF(Assms!$C$36=3,AZ5,BM5))) -> 0.05 | N5: =IF(Assms!$C$36=1,AA5,IF(Assms!$C$36=2,AN5,IF(Assms!$C$36=3,BA5,BN5))) -> 0.05 | O5: =IF(Assms!$C$36=1,AB5,IF(Assms!$C$36=2,AO5,IF(Assms!$C$36=3,BB5,BO5))) -> 0.05 | P5: =IF(Assms!$C$36=1,AC5,IF(Assms!$C$36=2,AP5,IF(Assms!$C$36=3,BC5,BP5))) -> 0.05 | ... T5: =IF(Assms!$C$36=1,AG5,IF(Assms!$C$36=2,AT5,IF(Assms!$C$36=3,BG5,BT5))) -> 0.07 | U5: 2 | V5: =IF(Assms!$F$37=1,LXtables!B5,IF(Assms!$F$37=2,LXtables!O5,IF(Assms!$F$37=3,LXtables!AB5,IF(Assms!$F$37=4,LXtables!AO5,IF(Assms!$F$37=5,LXtables!BB5,LXtables!BO5))))) -> 0.08 | W5: =IF(Assms!$F$37=1,LXtables!C5,IF(Assms!$F$37=2,LXtables!P5,IF(Assms!$F$37=3,LXtables!AC5,IF(Assms!$F$37=4,LXtables!AP5,IF(Assms!$F$37=5,LXtables!BC5,LXtables!BP5))))) -> 0.07 | X5: =IF(Assms!$F$37=1,LXtables!D5,IF(Assms!$F$37=2,LXtables!Q5,IF(Assms!$F$37=3,LXtables!AD5,IF(Assms!$F$37=4,LXtables!AQ5,IF(Assms!$F$37=5,LXtables!BD5,LXtables!BQ5))))) -> 0.06 | Y5: =IF(Assms!$F$37=1,LXtables!E5,IF(Assms!$F$37=2,LXtables!R5,IF(Assms!$F$37=3,LXtables!AE5,IF(Assms!$F$37=4,LXtables!AR5,IF(Assms!$F$37=5,LXtables!BE5,LXtables!BR5))))) -> 0.05 | Z5: =IF(Assms!$F$37=1,LXtables!F5,IF(Assms!$F$37=2,LXtables!S5,IF(Assms!$F$37=3,LXtables!AF5,IF(Assms!$F$37=4,LXtables!AS5,IF(Assms!$F$37=5,LXtables!BF5,LXtables!BS5))))) -> 0.05 | AA5: =IF(Assms!$F$37=1,LXtables!G5,IF(Assms!$F$37=2,LXtables!T5,IF(Assms!$F$37=3,LXtables!AG5,IF(Assms!$F$37=4,LXtables!AT5,IF(Assms!$F$37=5,LXtables!BG5,LXtables!BT5))))) -> 0.05 | AB5: =IF(Assms!$F$37=1,LXtables!H5,IF(Assms!$F$37=2,LXtables!U5,IF(Assms!$F$37=3,LXtables!AH5,IF(Assms!$F$37=4,LXtables!AU5,IF(Assms!$F$37=5,LXtables!BH5,LXtables!BU5))))) -> 0.05 | AC5: =IF(Assms!$F$37=1,LXtables!I5,IF(Assms!$F$37=2,LXtables!V5,IF(Assms!$F$37=3,LXtables!AI5,IF(Assms!$F$37=4,LXtables!AV5,IF(Assms!$F$37=5,LXtables!BI5,LXtables!BV5))))) -> 0.05 | ... AG5: =IF(Assms!$F$37=1,LXtables!M5,IF(Assms!$F$37=2,LXtables!Z5,IF(Assms!$F$37=3,LXtables!AM5,IF(Assms!$F$37=4,LXtables!AZ5,IF(Assms!$F$37=5,LXtables!BM5,LXtables!BZ5))))) -> 0.07 | AH5: 2 | AI5: =IF(Assms!$F$37=1,LXtables!CC5,IF(Assms!$F$37=2,LXtables!CP5,IF(Assms!$F$37=3,LXtables!DC5,IF(Assms!$F$37=4,LXtables!DP5,IF(Assms!$F$37=5,LXtables!EC5,LXtables!EP5))))) -> 0.09 | AJ5: =IF(Assms!$F$37=1,LXtables!CD5,IF(Assms!$F$37=2,LXtables!CQ5,IF(Assms!$F$37=3,LXtables!DD5,IF(Assms!$F$37=4,LXtables!DQ5,IF(Assms!$F$37=5,LXtables!ED5,LXtables!EQ5))))) -> 0.09 | AK5: =IF(Assms!$F$37=1,LXtables!CE5,IF(Assms!$F$37=2,LXtables!CR5,IF(Assms!$F$37=3,LXtables!DE5,IF(Assms!$F$37=4,LXtables!DR5,IF(Assms!$F$37=5,LXtables!EE5,LXtables!ER5))))) -> 0.07 | AL5: =IF(Assms!$F$37=1,LXtables!CF5,IF(Assms!$F$37=2,LXtables!CS5,IF(Assms!$F$37=3,LXtables!DF5,IF(Assms!$F$37=4,LXtables!DS5,IF(Assms!$F$37=5,LXtables!EF5,LXtables!ES5))))) -> 0.06 | AM5: =IF(Assms!$F$37=1,LXtables!CG5,IF(Assms!$F$37=2,LXtables!CT5,IF(Assms!$F$37=3,LXtables!DG5,IF(Assms!$F$37=4,LXtables!DT5,IF(Assms!$F$37=5,LXtables!EG5,LXtables!ET5))))) -> 0.06 | AN5: =IF(Assms!$F$37=1,LXtables!CH5,IF(Assms!$F$37=2,LXtables!CU5,IF(Assms!$F$37=3,LXtables!DH5,IF(Assms!$F$37=4,LXtables!DU5,IF(Assms!$F$37=5,LXtables!EH5,LXtables!EU5))))) -> 0.06 | AO5: =IF(Assms!$F$37=1,LXtables!CI5,IF(Assms!$F$37=2,LXtables!CV5,IF(Assms!$F$37=3,LXtables!DI5,IF(Assms!$F$37=4,LXtables!DV5,IF(Assms!$F$37=5,LXtables!EI5,LXtables!EV5))))) -> 0.06 | AP5: =IF(Assms!$F$37=1,LXtables!CJ5,IF(Assms!$F$37=2,LXtables!CW5,IF(Assms!$F$37=3,LXtables!DJ5,IF(Assms!$F$37=4,LXtables!DW5,IF(Assms!$F$37=5,LXtables!EJ5,LXtables!EW5))))) -> 0.06 | ... AT5: =IF(Assms!$F$37=1,LXtables!CN5,IF(Assms!$F$37=2,LXtables!DA5,IF(Assms!$F$37=3,LXtables!DN5,IF(Assms!$F$37=4,LXtables!EA5,IF(Assms!$F$37=5,LXtables!EN5,LXtables!FA5))))) -> 0.09 | AU5: 2 | AV5: =IF(Assms!$F$37=1,LXtables!FD5,IF(Assms!$F$37=2,LXtables!FQ5,IF(Assms!$F$37=3,LXtables!GD5,IF(Assms!$F$37=4,LXtables!GQ5,IF(Assms!$F$37=5,LXtables!HD5,LXtables!HQ5))))) -> 0.12 | AW5: =IF(Assms!$F$37=1,LXtables!FE5,IF(Assms!$F$37=2,LXtables!FR5,IF(Assms!$F$37=3,LXtables!GE5,IF(Assms!$F$37=4,LXtables!GR5,IF(Assms!$F$37=5,LXtables!HE5,LXtables!HR5))))) -> 0.11 | AX5: =IF(Assms!$F$37=1,LXtables!FF5,IF(Assms!$F$37=2,LXtables!FS5,IF(Assms!$F$37=3,LXtables!GF5,IF(Assms!$F$37=4,LXtables!GS5,IF(Assms!$F$37=5,LXtables!HF5,LXtables!HS5))))) -> 0.09 | AY5: =IF(Assms!$F$37=1,LXtables!FG5,IF(Assms!$F$37=2,LXtables!FT5,IF(Assms!$F$37=3,LXtables!GG5,IF(Assms!$F$37=4,LXtables!GT5,IF(Assms!$F$37=5,LXtables!HG5,LXtables!HT5))))) -> 0.08 | AZ5: =IF(Assms!$F$37=1,LXtables!FH5,IF(Assms!$F$37=2,LXtables!FU5,IF(Assms!$F$37=3,LXtables!GH5,IF(Assms!$F$37=4,LXtables!GU5,IF(Assms!$F$37=5,LXtables!HH5,LXtables!HU5))))) -> 0.07 | BA5: =IF(Assms!$F$37=1,LXtables!FI5,IF(Assms!$F$37=2,LXtables!FV5,IF(Assms!$F$37=3,LXtables!GI5,IF(Assms!$F$37=4,LXtables!GV5,IF(Assms!$F$37=5,LXtables!HI5,LXtables!HV5))))) -> 0.08 | BB5: =IF(Assms!$F$37=1,LXtables!FJ5,IF(Assms!$F$37=2,LXtables!FW5,IF(Assms!$F$37=3,LXtables!GJ5,IF(Assms!$F$37=4,LXtables!GW5,IF(Assms!$F$37=5,LXtables!HJ5,LXtables!HW5))))) -> 0.08 | BC5: =IF(Assms!$F$37=1,LXtables!FK5,IF(Assms!$F$37=2,LXtables!FX5,IF(Assms!$F$37=3,LXtables!GK5,IF(Assms!$F$37=4,LXtables!GX5,IF(Assms!$F$37=5,LXtables!HK5,LXtables!HX5))))) -> 0.08 | ... BG5: =IF(Assms!$F$37=1,LXtables!FO5,IF(Assms!$F$37=2,LXtables!GB5,IF(Assms!$F$37=3,LXtables!GO5,IF(Assms!$F$37=4,LXtables!HB5,IF(Assms!$F$37=5,LXtables!HO5,LXtables!IB5))))) -> 0.11 | BH5: 2 | BI5: =IF(Assms!$F$37=1,LXtables!IE5,IF(Assms!$F$37=2,LXtables!IR5,IF(Assms!$F$37=3,LXtables!JE5,IF(Assms!$F$37=4,LXtables!JR5,IF(Assms!$F$37=5,LXtables!KE5,LXtables!KR5))))) -> 0.17 | BJ5: =IF(Assms!$F$37=1,LXtables!IF5,IF(Assms!$F$37=2,LXtables!IS5,IF(Assms!$F$37=3,LXtables!JF5,IF(Assms!$F$37=4,LXtables!JS5,IF(Assms!$F$37=5,LXtables!KF5,LXtables!KS5))))) -> 0.16 | BK5: =IF(Assms!$F$37=1,LXtables!IG5,IF(Assms!$F$37=2,LXtables!IT5,IF(Assms!$F$37=3,LXtables!JG5,IF(Assms!$F$37=4,LXtables!JT5,IF(Assms!$F$37=5,LXtables!KG5,LXtables!KT5))))) -> 0.13 | BL5: =IF(Assms!$F$37=1,LXtables!IH5,IF(Assms!$F$37=2,LXtables!IU5,IF(Assms!$F$37=3,LXtables!JH5,IF(Assms!$F$37=4,LXtables!JU5,IF(Assms!$F$37=5,LXtables!KH5,LXtables!KU5))))) -> 0.11 | BM5: =IF(Assms!$F$37=1,LXtables!II5,IF(Assms!$F$37=2,LXtables!IV5,IF(Assms!$F$37=3,LXtables!JI5,IF(Assms!$F$37=4,LXtables!JV5,IF(Assms!$F$37=5,LXtables!KI5,LXtables!KV5))))) -> 0.11 | BN5: =IF(Assms!$F$37=1,LXtables!IJ5,IF(Assms!$F$37=2,LXtables!IW5,IF(Assms!$F$37=3,LXtables!JJ5,IF(Assms!$F$37=4,LXtables!JW5,IF(Assms!$F$37=5,LXtables!KJ5,LXtables!KW5))))) -> 0.11 | BO5: =IF(Assms!$F$37=1,LXtables!IK5,IF(Assms!$F$37=2,LXtables!IX5,IF(Assms!$F$37=3,LXtables!JK5,IF(Assms!$F$37=4,LXtables!JX5,IF(Assms!$F$37=5,LXtables!KK5,LXtables!KX5))))) -> 0.11 | BP5: =IF(Assms!$F$37=1,LXtables!IL5,IF(Assms!$F$37=2,LXtables!IY5,IF(Assms!$F$37=3,LXtables!JL5,IF(Assms!$F$37=4,LXtables!JY5,IF(Assms!$F$37=5,LXtables!KL5,LXtables!KY5))))) -> 0.12 | ... BT5: =IF(Assms!$F$37=1,LXtables!IP5,IF(Assms!$F$37=2,LXtables!JC5,IF(Assms!$F$37=3,LXtables!JP5,IF(Assms!$F$37=4,LXtables!KC5,IF(Assms!$F$37=5,LXtables!KP5,LXtables!LC5))))) -> 0.16
A6: 3 | B6: =IF(Assms!$C$33<20,$I6,IF(Assms!$C$33>75,$T6,HLOOKUP(Assms!$C$33,$I$3:$T$15,$H6+1))) -> 0.07 | C6: =IF(Assms!$C$33<20,$I20,IF(Assms!$C$33>75,$T20,HLOOKUP(Assms!$C$33,$I$17:$T$34,$H20+1))) -> 0.05 | D6: =IF(Assms!$C$33<20,$I39,IF(Assms!$C$33>75,$T39,HLOOKUP(Assms!$C$33,$I$36:$T$58,$H39+1))) -> 0.05 | E6: =IF(Assms!$C$33<20,$I63,IF(Assms!$C$33>75,$T63,HLOOKUP(Assms!$C$33,$I$60:$T$87,$H63+1))) -> 0.05 | F6: =IF(Assms!$C$33<20,$I92,IF(Assms!$C$33>75,$T92,HLOOKUP(Assms!$C$33,$I$89:$T$119,$H92+1))) -> 0.05 | G6: =HLOOKUP(Assms!$C$34,$A$3:$F$41,A6+1) -> 0.05 | H6: 3 | I6: =IF(Assms!$C$36=1,V6,IF(Assms!$C$36=2,AI6,IF(Assms!$C$36=3,AV6,BI6))) -> 0.07 | J6: =IF(Assms!$C$36=1,W6,IF(Assms!$C$36=2,AJ6,IF(Assms!$C$36=3,AW6,BJ6))) -> 0.07 | K6: =IF(Assms!$C$36=1,X6,IF(Assms!$C$36=2,AK6,IF(Assms!$C$36=3,AX6,BK6))) -> 0.05 | L6: =IF(Assms!$C$36=1,Y6,IF(Assms!$C$36=2,AL6,IF(Assms!$C$36=3,AY6,BL6))) -> 0.05 | M6: =IF(Assms!$C$36=1,Z6,IF(Assms!$C$36=2,AM6,IF(Assms!$C$36=3,AZ6,BM6))) -> 0.05 | N6: =IF(Assms!$C$36=1,AA6,IF(Assms!$C$36=2,AN6,IF(Assms!$C$36=3,BA6,BN6))) -> 0.05 | O6: =IF(Assms!$C$36=1,AB6,IF(Assms!$C$36=2,AO6,IF(Assms!$C$36=3,BB6,BO6))) -> 0.05 | P6: =IF(Assms!$C$36=1,AC6,IF(Assms!$C$36=2,AP6,IF(Assms!$C$36=3,BC6,BP6))) -> 0.05 | ... T6: =IF(Assms!$C$36=1,AG6,IF(Assms!$C$36=2,AT6,IF(Assms!$C$36=3,BG6,BT6))) -> 0.07 | U6: 3 | V6: =IF(Assms!$F$37=1,LXtables!B6,IF(Assms!$F$37=2,LXtables!O6,IF(Assms!$F$37=3,LXtables!AB6,IF(Assms!$F$37=4,LXtables!AO6,IF(Assms!$F$37=5,LXtables!BB6,LXtables!BO6))))) -> 0.07 | W6: =IF(Assms!$F$37=1,LXtables!C6,IF(Assms!$F$37=2,LXtables!P6,IF(Assms!$F$37=3,LXtables!AC6,IF(Assms!$F$37=4,LXtables!AP6,IF(Assms!$F$37=5,LXtables!BC6,LXtables!BP6))))) -> 0.07 | X6: =IF(Assms!$F$37=1,LXtables!D6,IF(Assms!$F$37=2,LXtables!Q6,IF(Assms!$F$37=3,LXtables!AD6,IF(Assms!$F$37=4,LXtables!AQ6,IF(Assms!$F$37=5,LXtables!BD6,LXtables!BQ6))))) -> 0.05 | Y6: =IF(Assms!$F$37=1,LXtables!E6,IF(Assms!$F$37=2,LXtables!R6,IF(Assms!$F$37=3,LXtables!AE6,IF(Assms!$F$37=4,LXtables!AR6,IF(Assms!$F$37=5,LXtables!BE6,LXtables!BR6))))) -> 0.05 | Z6: =IF(Assms!$F$37=1,LXtables!F6,IF(Assms!$F$37=2,LXtables!S6,IF(Assms!$F$37=3,LXtables!AF6,IF(Assms!$F$37=4,LXtables!AS6,IF(Assms!$F$37=5,LXtables!BF6,LXtables!BS6))))) -> 0.05 | AA6: =IF(Assms!$F$37=1,LXtables!G6,IF(Assms!$F$37=2,LXtables!T6,IF(Assms!$F$37=3,LXtables!AG6,IF(Assms!$F$37=4,LXtables!AT6,IF(Assms!$F$37=5,LXtables!BG6,LXtables!BT6))))) -> 0.05 | AB6: =IF(Assms!$F$37=1,LXtables!H6,IF(Assms!$F$37=2,LXtables!U6,IF(Assms!$F$37=3,LXtables!AH6,IF(Assms!$F$37=4,LXtables!AU6,IF(Assms!$F$37=5,LXtables!BH6,LXtables!BU6))))) -> 0.05 | AC6: =IF(Assms!$F$37=1,LXtables!I6,IF(Assms!$F$37=2,LXtables!V6,IF(Assms!$F$37=3,LXtables!AI6,IF(Assms!$F$37=4,LXtables!AV6,IF(Assms!$F$37=5,LXtables!BI6,LXtables!BV6))))) -> 0.05 | ... AG6: =IF(Assms!$F$37=1,LXtables!M6,IF(Assms!$F$37=2,LXtables!Z6,IF(Assms!$F$37=3,LXtables!AM6,IF(Assms!$F$37=4,LXtables!AZ6,IF(Assms!$F$37=5,LXtables!BM6,LXtables!BZ6))))) -> 0.07 | AH6: 3 | AI6: =IF(Assms!$F$37=1,LXtables!CC6,IF(Assms!$F$37=2,LXtables!CP6,IF(Assms!$F$37=3,LXtables!DC6,IF(Assms!$F$37=4,LXtables!DP6,IF(Assms!$F$37=5,LXtables!EC6,LXtables!EP6))))) -> 0.09 | AJ6: =IF(Assms!$F$37=1,LXtables!CD6,IF(Assms!$F$37=2,LXtables!CQ6,IF(Assms!$F$37=3,LXtables!DD6,IF(Assms!$F$37=4,LXtables!DQ6,IF(Assms!$F$37=5,LXtables!ED6,LXtables!EQ6))))) -> 0.08 | AK6: =IF(Assms!$F$37=1,LXtables!CE6,IF(Assms!$F$37=2,LXtables!CR6,IF(Assms!$F$37=3,LXtables!DE6,IF(Assms!$F$37=4,LXtables!DR6,IF(Assms!$F$37=5,LXtables!EE6,LXtables!ER6))))) -> 0.07 | AL6: =IF(Assms!$F$37=1,LXtables!CF6,IF(Assms!$F$37=2,LXtables!CS6,IF(Assms!$F$37=3,LXtables!DF6,IF(Assms!$F$37=4,LXtables!DS6,IF(Assms!$F$37=5,LXtables!EF6,LXtables!ES6))))) -> 0.06 | AM6: =IF(Assms!$F$37=1,LXtables!CG6,IF(Assms!$F$37=2,LXtables!CT6,IF(Assms!$F$37=3,LXtables!DG6,IF(Assms!$F$37=4,LXtables!DT6,IF(Assms!$F$37=5,LXtables!EG6,LXtables!ET6))))) -> 0.06 | AN6: =IF(Assms!$F$37=1,LXtables!CH6,IF(Assms!$F$37=2,LXtables!CU6,IF(Assms!$F$37=3,LXtables!DH6,IF(Assms!$F$37=4,LXtables!DU6,IF(Assms!$F$37=5,LXtables!EH6,LXtables!EU6))))) -> 0.06 | AO6: =IF(Assms!$F$37=1,LXtables!CI6,IF(Assms!$F$37=2,LXtables!CV6,IF(Assms!$F$37=3,LXtables!DI6,IF(Assms!$F$37=4,LXtables!DV6,IF(Assms!$F$37=5,LXtables!EI6,LXtables!EV6))))) -> 0.06 | AP6: =IF(Assms!$F$37=1,LXtables!CJ6,IF(Assms!$F$37=2,LXtables!CW6,IF(Assms!$F$37=3,LXtables!DJ6,IF(Assms!$F$37=4,LXtables!DW6,IF(Assms!$F$37=5,LXtables!EJ6,LXtables!EW6))))) -> 0.06 | ... AT6: =IF(Assms!$F$37=1,LXtables!CN6,IF(Assms!$F$37=2,LXtables!DA6,IF(Assms!$F$37=3,LXtables!DN6,IF(Assms!$F$37=4,LXtables!EA6,IF(Assms!$F$37=5,LXtables!EN6,LXtables!FA6))))) -> 0.08 | AU6: 3 | AV6: =IF(Assms!$F$37=1,LXtables!FD6,IF(Assms!$F$37=2,LXtables!FQ6,IF(Assms!$F$37=3,LXtables!GD6,IF(Assms!$F$37=4,LXtables!GQ6,IF(Assms!$F$37=5,LXtables!HD6,LXtables!HQ6))))) -> 0.11 | AW6: =IF(Assms!$F$37=1,LXtables!FE6,IF(Assms!$F$37=2,LXtables!FR6,IF(Assms!$F$37=3,LXtables!GE6,IF(Assms!$F$37=4,LXtables!GR6,IF(Assms!$F$37=5,LXtables!HE6,LXtables!HR6))))) -> 0.1 | AX6: =IF(Assms!$F$37=1,LXtables!FF6,IF(Assms!$F$37=2,LXtables!FS6,IF(Assms!$F$37=3,LXtables!GF6,IF(Assms!$F$37=4,LXtables!GS6,IF(Assms!$F$37=5,LXtables!HF6,LXtables!HS6))))) -> 0.08 | AY6: =IF(Assms!$F$37=1,LXtables!FG6,IF(Assms!$F$37=2,LXtables!FT6,IF(Assms!$F$37=3,LXtables!GG6,IF(Assms!$F$37=4,LXtables!GT6,IF(Assms!$F$37=5,LXtables!HG6,LXtables!HT6))))) -> 0.07 | AZ6: =IF(Assms!$F$37=1,LXtables!FH6,IF(Assms!$F$37=2,LXtables!FU6,IF(Assms!$F$37=3,LXtables!GH6,IF(Assms!$F$37=4,LXtables!GU6,IF(Assms!$F$37=5,LXtables!HH6,LXtables!HU6))))) -> 0.07 | BA6: =IF(Assms!$F$37=1,LXtables!FI6,IF(Assms!$F$37=2,LXtables!FV6,IF(Assms!$F$37=3,LXtables!GI6,IF(Assms!$F$37=4,LXtables!GV6,IF(Assms!$F$37=5,LXtables!HI6,LXtables!HV6))))) -> 0.07 | BB6: =IF(Assms!$F$37=1,LXtables!FJ6,IF(Assms!$F$37=2,LXtables!FW6,IF(Assms!$F$37=3,LXtables!GJ6,IF(Assms!$F$37=4,LXtables!GW6,IF(Assms!$F$37=5,LXtables!HJ6,LXtables!HW6))))) -> 0.07 | BC6: =IF(Assms!$F$37=1,LXtables!FK6,IF(Assms!$F$37=2,LXtables!FX6,IF(Assms!$F$37=3,LXtables!GK6,IF(Assms!$F$37=4,LXtables!GX6,IF(Assms!$F$37=5,LXtables!HK6,LXtables!HX6))))) -> 0.08 | ... BG6: =IF(Assms!$F$37=1,LXtables!FO6,IF(Assms!$F$37=2,LXtables!GB6,IF(Assms!$F$37=3,LXtables!GO6,IF(Assms!$F$37=4,LXtables!HB6,IF(Assms!$F$37=5,LXtables!HO6,LXtables!IB6))))) -> 0.1 | BH6: 3 | BI6: =IF(Assms!$F$37=1,LXtables!IE6,IF(Assms!$F$37=2,LXtables!IR6,IF(Assms!$F$37=3,LXtables!JE6,IF(Assms!$F$37=4,LXtables!JR6,IF(Assms!$F$37=5,LXtables!KE6,LXtables!KR6))))) -> 0.15 | BJ6: =IF(Assms!$F$37=1,LXtables!IF6,IF(Assms!$F$37=2,LXtables!IS6,IF(Assms!$F$37=3,LXtables!JF6,IF(Assms!$F$37=4,LXtables!JS6,IF(Assms!$F$37=5,LXtables!KF6,LXtables!KS6))))) -> 0.14 | BK6: =IF(Assms!$F$37=1,LXtables!IG6,IF(Assms!$F$37=2,LXtables!IT6,IF(Assms!$F$37=3,LXtables!JG6,IF(Assms!$F$37=4,LXtables!JT6,IF(Assms!$F$37=5,LXtables!KG6,LXtables!KT6))))) -> 0.11 | BL6: =IF(Assms!$F$37=1,LXtables!IH6,IF(Assms!$F$37=2,LXtables!IU6,IF(Assms!$F$37=3,LXtables!JH6,IF(Assms!$F$37=4,LXtables!JU6,IF(Assms!$F$37=5,LXtables!KH6,LXtables!KU6))))) -> 0.1 | BM6: =IF(Assms!$F$37=1,LXtables!II6,IF(Assms!$F$37=2,LXtables!IV6,IF(Assms!$F$37=3,LXtables!JI6,IF(Assms!$F$37=4,LXtables!JV6,IF(Assms!$F$37=5,LXtables!KI6,LXtables!KV6))))) -> 0.1 | BN6: =IF(Assms!$F$37=1,LXtables!IJ6,IF(Assms!$F$37=2,LXtables!IW6,IF(Assms!$F$37=3,LXtables!JJ6,IF(Assms!$F$37=4,LXtables!JW6,IF(Assms!$F$37=5,LXtables!KJ6,LXtables!KW6))))) -> 0.1 | BO6: =IF(Assms!$F$37=1,LXtables!IK6,IF(Assms!$F$37=2,LXtables!IX6,IF(Assms!$F$37=3,LXtables!JK6,IF(Assms!$F$37=4,LXtables!JX6,IF(Assms!$F$37=5,LXtables!KK6,LXtables!KX6))))) -> 0.1 | BP6: =IF(Assms!$F$37=1,LXtables!IL6,IF(Assms!$F$37=2,LXtables!IY6,IF(Assms!$F$37=3,LXtables!JL6,IF(Assms!$F$37=4,LXtables!JY6,IF(Assms!$F$37=5,LXtables!KL6,LXtables!KY6))))) -> 0.11 | ... BT6: =IF(Assms!$F$37=1,LXtables!IP6,IF(Assms!$F$37=2,LXtables!JC6,IF(Assms!$F$37=3,LXtables!JP6,IF(Assms!$F$37=4,LXtables!KC6,IF(Assms!$F$37=5,LXtables!KP6,LXtables!LC6))))) -> 0.14
A7: 4 | B7: =IF(Assms!$C$33<20,$I7,IF(Assms!$C$33>75,$T7,HLOOKUP(Assms!$C$33,$I$3:$T$15,$H7+1))) -> 0.07 | C7: =IF(Assms!$C$33<20,$I21,IF(Assms!$C$33>75,$T21,HLOOKUP(Assms!$C$33,$I$17:$T$34,$H21+1))) -> 0.05 | D7: =IF(Assms!$C$33<20,$I40,IF(Assms!$C$33>75,$T40,HLOOKUP(Assms!$C$33,$I$36:$T$58,$H40+1))) -> 0.05 | E7: =IF(Assms!$C$33<20,$I64,IF(Assms!$C$33>75,$T64,HLOOKUP(Assms!$C$33,$I$60:$T$87,$H64+1))) -> 0.04 | F7: =IF(Assms!$C$33<20,$I93,IF(Assms!$C$33>75,$T93,HLOOKUP(Assms!$C$33,$I$89:$T$119,$H93+1))) -> 0.05 | G7: =HLOOKUP(Assms!$C$34,$A$3:$F$41,A7+1) -> 0.04 | H7: 4 | I7: =IF(Assms!$C$36=1,V7,IF(Assms!$C$36=2,AI7,IF(Assms!$C$36=3,AV7,BI7))) -> 0.07 | J7: =IF(Assms!$C$36=1,W7,IF(Assms!$C$36=2,AJ7,IF(Assms!$C$36=3,AW7,BJ7))) -> 0.07 | K7: =IF(Assms!$C$36=1,X7,IF(Assms!$C$36=2,AK7,IF(Assms!$C$36=3,AX7,BK7))) -> 0.05 | L7: =IF(Assms!$C$36=1,Y7,IF(Assms!$C$36=2,AL7,IF(Assms!$C$36=3,AY7,BL7))) -> 0.05 | M7: =IF(Assms!$C$36=1,Z7,IF(Assms!$C$36=2,AM7,IF(Assms!$C$36=3,AZ7,BM7))) -> 0.05 | N7: =IF(Assms!$C$36=1,AA7,IF(Assms!$C$36=2,AN7,IF(Assms!$C$36=3,BA7,BN7))) -> 0.05 | O7: =IF(Assms!$C$36=1,AB7,IF(Assms!$C$36=2,AO7,IF(Assms!$C$36=3,BB7,BO7))) -> 0.05 | P7: =IF(Assms!$C$36=1,AC7,IF(Assms!$C$36=2,AP7,IF(Assms!$C$36=3,BC7,BP7))) -> 0.05 | ... T7: =IF(Assms!$C$36=1,AG7,IF(Assms!$C$36=2,AT7,IF(Assms!$C$36=3,BG7,BT7))) -> 0.07 | U7: 4 | V7: =IF(Assms!$F$37=1,LXtables!B7,IF(Assms!$F$37=2,LXtables!O7,IF(Assms!$F$37=3,LXtables!AB7,IF(Assms!$F$37=4,LXtables!AO7,IF(Assms!$F$37=5,LXtables!BB7,LXtables!BO7))))) -> 0.07 | W7: =IF(Assms!$F$37=1,LXtables!C7,IF(Assms!$F$37=2,LXtables!P7,IF(Assms!$F$37=3,LXtables!AC7,IF(Assms!$F$37=4,LXtables!AP7,IF(Assms!$F$37=5,LXtables!BC7,LXtables!BP7))))) -> 0.07 | X7: =IF(Assms!$F$37=1,LXtables!D7,IF(Assms!$F$37=2,LXtables!Q7,IF(Assms!$F$37=3,LXtables!AD7,IF(Assms!$F$37=4,LXtables!AQ7,IF(Assms!$F$37=5,LXtables!BD7,LXtables!BQ7))))) -> 0.05 | Y7: =IF(Assms!$F$37=1,LXtables!E7,IF(Assms!$F$37=2,LXtables!R7,IF(Assms!$F$37=3,LXtables!AE7,IF(Assms!$F$37=4,LXtables!AR7,IF(Assms!$F$37=5,LXtables!BE7,LXtables!BR7))))) -> 0.05 | Z7: =IF(Assms!$F$37=1,LXtables!F7,IF(Assms!$F$37=2,LXtables!S7,IF(Assms!$F$37=3,LXtables!AF7,IF(Assms!$F$37=4,LXtables!AS7,IF(Assms!$F$37=5,LXtables!BF7,LXtables!BS7))))) -> 0.05 | AA7: =IF(Assms!$F$37=1,LXtables!G7,IF(Assms!$F$37=2,LXtables!T7,IF(Assms!$F$37=3,LXtables!AG7,IF(Assms!$F$37=4,LXtables!AT7,IF(Assms!$F$37=5,LXtables!BG7,LXtables!BT7))))) -> 0.05 | AB7: =IF(Assms!$F$37=1,LXtables!H7,IF(Assms!$F$37=2,LXtables!U7,IF(Assms!$F$37=3,LXtables!AH7,IF(Assms!$F$37=4,LXtables!AU7,IF(Assms!$F$37=5,LXtables!BH7,LXtables!BU7))))) -> 0.05 | AC7: =IF(Assms!$F$37=1,LXtables!I7,IF(Assms!$F$37=2,LXtables!V7,IF(Assms!$F$37=3,LXtables!AI7,IF(Assms!$F$37=4,LXtables!AV7,IF(Assms!$F$37=5,LXtables!BI7,LXtables!BV7))))) -> 0.05 | ... AG7: =IF(Assms!$F$37=1,LXtables!M7,IF(Assms!$F$37=2,LXtables!Z7,IF(Assms!$F$37=3,LXtables!AM7,IF(Assms!$F$37=4,LXtables!AZ7,IF(Assms!$F$37=5,LXtables!BM7,LXtables!BZ7))))) -> 0.07 | AH7: 4 | AI7: =IF(Assms!$F$37=1,LXtables!CC7,IF(Assms!$F$37=2,LXtables!CP7,IF(Assms!$F$37=3,LXtables!DC7,IF(Assms!$F$37=4,LXtables!DP7,IF(Assms!$F$37=5,LXtables!EC7,LXtables!EP7))))) -> 0.09 | AJ7: =IF(Assms!$F$37=1,LXtables!CD7,IF(Assms!$F$37=2,LXtables!CQ7,IF(Assms!$F$37=3,LXtables!DD7,IF(Assms!$F$37=4,LXtables!DQ7,IF(Assms!$F$37=5,LXtables!ED7,LXtables!EQ7))))) -> 0.08 | AK7: =IF(Assms!$F$37=1,LXtables!CE7,IF(Assms!$F$37=2,LXtables!CR7,IF(Assms!$F$37=3,LXtables!DE7,IF(Assms!$F$37=4,LXtables!DR7,IF(Assms!$F$37=5,LXtables!EE7,LXtables!ER7))))) -> 0.06 | AL7: =IF(Assms!$F$37=1,LXtables!CF7,IF(Assms!$F$37=2,LXtables!CS7,IF(Assms!$F$37=3,LXtables!DF7,IF(Assms!$F$37=4,LXtables!DS7,IF(Assms!$F$37=5,LXtables!EF7,LXtables!ES7))))) -> 0.06 | AM7: =IF(Assms!$F$37=1,LXtables!CG7,IF(Assms!$F$37=2,LXtables!CT7,IF(Assms!$F$37=3,LXtables!DG7,IF(Assms!$F$37=4,LXtables!DT7,IF(Assms!$F$37=5,LXtables!EG7,LXtables!ET7))))) -> 0.05 | AN7: =IF(Assms!$F$37=1,LXtables!CH7,IF(Assms!$F$37=2,LXtables!CU7,IF(Assms!$F$37=3,LXtables!DH7,IF(Assms!$F$37=4,LXtables!DU7,IF(Assms!$F$37=5,LXtables!EH7,LXtables!EU7))))) -> 0.06 | AO7: =IF(Assms!$F$37=1,LXtables!CI7,IF(Assms!$F$37=2,LXtables!CV7,IF(Assms!$F$37=3,LXtables!DI7,IF(Assms!$F$37=4,LXtables!DV7,IF(Assms!$F$37=5,LXtables!EI7,LXtables!EV7))))) -> 0.06 | AP7: =IF(Assms!$F$37=1,LXtables!CJ7,IF(Assms!$F$37=2,LXtables!CW7,IF(Assms!$F$37=3,LXtables!DJ7,IF(Assms!$F$37=4,LXtables!DW7,IF(Assms!$F$37=5,LXtables!EJ7,LXtables!EW7))))) -> 0.06 | ... AT7: =IF(Assms!$F$37=1,LXtables!CN7,IF(Assms!$F$37=2,LXtables!DA7,IF(Assms!$F$37=3,LXtables!DN7,IF(Assms!$F$37=4,LXtables!EA7,IF(Assms!$F$37=5,LXtables!EN7,LXtables!FA7))))) -> 0.08 | AU7: 4 | AV7: =IF(Assms!$F$37=1,LXtables!FD7,IF(Assms!$F$37=2,LXtables!FQ7,IF(Assms!$F$37=3,LXtables!GD7,IF(Assms!$F$37=4,LXtables!GQ7,IF(Assms!$F$37=5,LXtables!HD7,LXtables!HQ7))))) -> 0.1 | AW7: =IF(Assms!$F$37=1,LXtables!FE7,IF(Assms!$F$37=2,LXtables!FR7,IF(Assms!$F$37=3,LXtables!GE7,IF(Assms!$F$37=4,LXtables!GR7,IF(Assms!$F$37=5,LXtables!HE7,LXtables!HR7))))) -> 0.1 | AX7: =IF(Assms!$F$37=1,LXtables!FF7,IF(Assms!$F$37=2,LXtables!FS7,IF(Assms!$F$37=3,LXtables!GF7,IF(Assms!$F$37=4,LXtables!GS7,IF(Assms!$F$37=5,LXtables!HF7,LXtables!HS7))))) -> 0.08 | AY7: =IF(Assms!$F$37=1,LXtables!FG7,IF(Assms!$F$37=2,LXtables!FT7,IF(Assms!$F$37=3,LXtables!GG7,IF(Assms!$F$37=4,LXtables!GT7,IF(Assms!$F$37=5,LXtables!HG7,LXtables!HT7))))) -> 0.07 | AZ7: =IF(Assms!$F$37=1,LXtables!FH7,IF(Assms!$F$37=2,LXtables!FU7,IF(Assms!$F$37=3,LXtables!GH7,IF(Assms!$F$37=4,LXtables!GU7,IF(Assms!$F$37=5,LXtables!HH7,LXtables!HU7))))) -> 0.07 | BA7: =IF(Assms!$F$37=1,LXtables!FI7,IF(Assms!$F$37=2,LXtables!FV7,IF(Assms!$F$37=3,LXtables!GI7,IF(Assms!$F$37=4,LXtables!GV7,IF(Assms!$F$37=5,LXtables!HI7,LXtables!HV7))))) -> 0.07 | BB7: =IF(Assms!$F$37=1,LXtables!FJ7,IF(Assms!$F$37=2,LXtables!FW7,IF(Assms!$F$37=3,LXtables!GJ7,IF(Assms!$F$37=4,LXtables!GW7,IF(Assms!$F$37=5,LXtables!HJ7,LXtables!HW7))))) -> 0.07 | BC7: =IF(Assms!$F$37=1,LXtables!FK7,IF(Assms!$F$37=2,LXtables!FX7,IF(Assms!$F$37=3,LXtables!GK7,IF(Assms!$F$37=4,LXtables!GX7,IF(Assms!$F$37=5,LXtables!HK7,LXtables!HX7))))) -> 0.07 | ... BG7: =IF(Assms!$F$37=1,LXtables!FO7,IF(Assms!$F$37=2,LXtables!GB7,IF(Assms!$F$37=3,LXtables!GO7,IF(Assms!$F$37=4,LXtables!HB7,IF(Assms!$F$37=5,LXtables!HO7,LXtables!IB7))))) -> 0.1 | BH7: 4 | BI7: =IF(Assms!$F$37=1,LXtables!IE7,IF(Assms!$F$37=2,LXtables!IR7,IF(Assms!$F$37=3,LXtables!JE7,IF(Assms!$F$37=4,LXtables!JR7,IF(Assms!$F$37=5,LXtables!KE7,LXtables!KR7))))) -> 0.14 | BJ7: =IF(Assms!$F$37=1,LXtables!IF7,IF(Assms!$F$37=2,LXtables!IS7,IF(Assms!$F$37=3,LXtables!JF7,IF(Assms!$F$37=4,LXtables!JS7,IF(Assms!$F$37=5,LXtables!KF7,LXtables!KS7))))) -> 0.13 | BK7: =IF(Assms!$F$37=1,LXtables!IG7,IF(Assms!$F$37=2,LXtables!IT7,IF(Assms!$F$37=3,LXtables!JG7,IF(Assms!$F$37=4,LXtables!JT7,IF(Assms!$F$37=5,LXtables!KG7,LXtables!KT7))))) -> 0.1 | BL7: =IF(Assms!$F$37=1,LXtables!IH7,IF(Assms!$F$37=2,LXtables!IU7,IF(Assms!$F$37=3,LXtables!JH7,IF(Assms!$F$37=4,LXtables!JU7,IF(Assms!$F$37=5,LXtables!KH7,LXtables!KU7))))) -> 0.09 | BM7: =IF(Assms!$F$37=1,LXtables!II7,IF(Assms!$F$37=2,LXtables!IV7,IF(Assms!$F$37=3,LXtables!JI7,IF(Assms!$F$37=4,LXtables!JV7,IF(Assms!$F$37=5,LXtables!KI7,LXtables!KV7))))) -> 0.09 | BN7: =IF(Assms!$F$37=1,LXtables!IJ7,IF(Assms!$F$37=2,LXtables!IW7,IF(Assms!$F$37=3,LXtables!JJ7,IF(Assms!$F$37=4,LXtables!JW7,IF(Assms!$F$37=5,LXtables!KJ7,LXtables!KW7))))) -> 0.09 | BO7: =IF(Assms!$F$37=1,LXtables!IK7,IF(Assms!$F$37=2,LXtables!IX7,IF(Assms!$F$37=3,LXtables!JK7,IF(Assms!$F$37=4,LXtables!JX7,IF(Assms!$F$37=5,LXtables!KK7,LXtables!KX7))))) -> 0.1 | BP7: =IF(Assms!$F$37=1,LXtables!IL7,IF(Assms!$F$37=2,LXtables!IY7,IF(Assms!$F$37=3,LXtables!JL7,IF(Assms!$F$37=4,LXtables!JY7,IF(Assms!$F$37=5,LXtables!KL7,LXtables!KY7))))) -> 0.1 | ... BT7: =IF(Assms!$F$37=1,LXtables!IP7,IF(Assms!$F$37=2,LXtables!JC7,IF(Assms!$F$37=3,LXtables!JP7,IF(Assms!$F$37=4,LXtables!KC7,IF(Assms!$F$37=5,LXtables!KP7,LXtables!LC7))))) -> 0.13
A8: 5 | B8: =IF(Assms!$C$33<20,$I8,IF(Assms!$C$33>75,$T8,HLOOKUP(Assms!$C$33,$I$3:$T$15,$H8+1))) -> 0.07 | C8: =IF(Assms!$C$33<20,$I22,IF(Assms!$C$33>75,$T22,HLOOKUP(Assms!$C$33,$I$17:$T$34,$H22+1))) -> 0.05 | D8: =IF(Assms!$C$33<20,$I41,IF(Assms!$C$33>75,$T41,HLOOKUP(Assms!$C$33,$I$36:$T$58,$H41+1))) -> 0.05 | E8: =IF(Assms!$C$33<20,$I65,IF(Assms!$C$33>75,$T65,HLOOKUP(Assms!$C$33,$I$60:$T$87,$H65+1))) -> 0.04 | F8: =IF(Assms!$C$33<20,$I94,IF(Assms!$C$33>75,$T94,HLOOKUP(Assms!$C$33,$I$89:$T$119,$H94+1))) -> 0.04 | G8: =HLOOKUP(Assms!$C$34,$A$3:$F$41,A8+1) -> 0.04 | H8: 5 | I8: =IF(Assms!$C$36=1,V8,IF(Assms!$C$36=2,AI8,IF(Assms!$C$36=3,AV8,BI8))) -> 0.07 | J8: =IF(Assms!$C$36=1,W8,IF(Assms!$C$36=2,AJ8,IF(Assms!$C$36=3,AW8,BJ8))) -> 0.07 | K8: =IF(Assms!$C$36=1,X8,IF(Assms!$C$36=2,AK8,IF(Assms!$C$36=3,AX8,BK8))) -> 0.05 | L8: =IF(Assms!$C$36=1,Y8,IF(Assms!$C$36=2,AL8,IF(Assms!$C$36=3,AY8,BL8))) -> 0.05 | M8: =IF(Assms!$C$36=1,Z8,IF(Assms!$C$36=2,AM8,IF(Assms!$C$36=3,AZ8,BM8))) -> 0.05 | N8: =IF(Assms!$C$36=1,AA8,IF(Assms!$C$36=2,AN8,IF(Assms!$C$36=3,BA8,BN8))) -> 0.05 | O8: =IF(Assms!$C$36=1,AB8,IF(Assms!$C$36=2,AO8,IF(Assms!$C$36=3,BB8,BO8))) -> 0.05 | P8: =IF(Assms!$C$36=1,AC8,IF(Assms!$C$36=2,AP8,IF(Assms!$C$36=3,BC8,BP8))) -> 0.05 | ... T8: =IF(Assms!$C$36=1,AG8,IF(Assms!$C$36=2,AT8,IF(Assms!$C$36=3,BG8,BT8))) -> 0.11 | U8: 5 | V8: =IF(Assms!$F$37=1,LXtables!B8,IF(Assms!$F$37=2,LXtables!O8,IF(Assms!$F$37=3,LXtables!AB8,IF(Assms!$F$37=4,LXtables!AO8,IF(Assms!$F$37=5,LXtables!BB8,LXtables!BO8))))) -> 0.07 | W8: =IF(Assms!$F$37=1,LXtables!C8,IF(Assms!$F$37=2,LXtables!P8,IF(Assms!$F$37=3,LXtables!AC8,IF(Assms!$F$37=4,LXtables!AP8,IF(Assms!$F$37=5,LXtables!BC8,LXtables!BP8))))) -> 0.07 | X8: =IF(Assms!$F$37=1,LXtables!D8,IF(Assms!$F$37=2,LXtables!Q8,IF(Assms!$F$37=3,LXtables!AD8,IF(Assms!$F$37=4,LXtables!AQ8,IF(Assms!$F$37=5,LXtables!BD8,LXtables!BQ8))))) -> 0.05 | Y8: =IF(Assms!$F$37=1,LXtables!E8,IF(Assms!$F$37=2,LXtables!R8,IF(Assms!$F$37=3,LXtables!AE8,IF(Assms!$F$37=4,LXtables!AR8,IF(Assms!$F$37=5,LXtables!BE8,LXtables!BR8))))) -> 0.05 | Z8: =IF(Assms!$F$37=1,LXtables!F8,IF(Assms!$F$37=2,LXtables!S8,IF(Assms!$F$37=3,LXtables!AF8,IF(Assms!$F$37=4,LXtables!AS8,IF(Assms!$F$37=5,LXtables!BF8,LXtables!BS8))))) -> 0.05 | AA8: =IF(Assms!$F$37=1,LXtables!G8,IF(Assms!$F$37=2,LXtables!T8,IF(Assms!$F$37=3,LXtables!AG8,IF(Assms!$F$37=4,LXtables!AT8,IF(Assms!$F$37=5,LXtables!BG8,LXtables!BT8))))) -> 0.05 | AB8: =IF(Assms!$F$37=1,LXtables!H8,IF(Assms!$F$37=2,LXtables!U8,IF(Assms!$F$37=3,LXtables!AH8,IF(Assms!$F$37=4,LXtables!AU8,IF(Assms!$F$37=5,LXtables!BH8,LXtables!BU8))))) -> 0.05 | AC8: =IF(Assms!$F$37=1,LXtables!I8,IF(Assms!$F$37=2,LXtables!V8,IF(Assms!$F$37=3,LXtables!AI8,IF(Assms!$F$37=4,LXtables!AV8,IF(Assms!$F$37=5,LXtables!BI8,LXtables!BV8))))) -> 0.05 | ... AG8: =IF(Assms!$F$37=1,LXtables!M8,IF(Assms!$F$37=2,LXtables!Z8,IF(Assms!$F$37=3,LXtables!AM8,IF(Assms!$F$37=4,LXtables!AZ8,IF(Assms!$F$37=5,LXtables!BM8,LXtables!BZ8))))) -> 0.11 | AH8: 5 | AI8: =IF(Assms!$F$37=1,LXtables!CC8,IF(Assms!$F$37=2,LXtables!CP8,IF(Assms!$F$37=3,LXtables!DC8,IF(Assms!$F$37=4,LXtables!DP8,IF(Assms!$F$37=5,LXtables!EC8,LXtables!EP8))))) -> 0.08 | AJ8: =IF(Assms!$F$37=1,LXtables!CD8,IF(Assms!$F$37=2,LXtables!CQ8,IF(Assms!$F$37=3,LXtables!DD8,IF(Assms!$F$37=4,LXtables!DQ8,IF(Assms!$F$37=5,LXtables!ED8,LXtables!EQ8))))) -> 0.08 | AK8: =IF(Assms!$F$37=1,LXtables!CE8,IF(Assms!$F$37=2,LXtables!CR8,IF(Assms!$F$37=3,LXtables!DE8,IF(Assms!$F$37=4,LXtables!DR8,IF(Assms!$F$37=5,LXtables!EE8,LXtables!ER8))))) -> 0.06 | AL8: =IF(Assms!$F$37=1,LXtables!CF8,IF(Assms!$F$37=2,LXtables!CS8,IF(Assms!$F$37=3,LXtables!DF8,IF(Assms!$F$37=4,LXtables!DS8,IF(Assms!$F$37=5,LXtables!EF8,LXtables!ES8))))) -> 0.05 | AM8: =IF(Assms!$F$37=1,LXtables!CG8,IF(Assms!$F$37=2,LXtables!CT8,IF(Assms!$F$37=3,LXtables!DG8,IF(Assms!$F$37=4,LXtables!DT8,IF(Assms!$F$37=5,LXtables!EG8,LXtables!ET8))))) -> 0.05 | AN8: =IF(Assms!$F$37=1,LXtables!CH8,IF(Assms!$F$37=2,LXtables!CU8,IF(Assms!$F$37=3,LXtables!DH8,IF(Assms!$F$37=4,LXtables!DU8,IF(Assms!$F$37=5,LXtables!EH8,LXtables!EU8))))) -> 0.05 | AO8: =IF(Assms!$F$37=1,LXtables!CI8,IF(Assms!$F$37=2,LXtables!CV8,IF(Assms!$F$37=3,LXtables!DI8,IF(Assms!$F$37=4,LXtables!DV8,IF(Assms!$F$37=5,LXtables!EI8,LXtables!EV8))))) -> 0.06 | AP8: =IF(Assms!$F$37=1,LXtables!CJ8,IF(Assms!$F$37=2,LXtables!CW8,IF(Assms!$F$37=3,LXtables!DJ8,IF(Assms!$F$37=4,LXtables!DW8,IF(Assms!$F$37=5,LXtables!EJ8,LXtables!EW8))))) -> 0.06 | ... AT8: =IF(Assms!$F$37=1,LXtables!CN8,IF(Assms!$F$37=2,LXtables!DA8,IF(Assms!$F$37=3,LXtables!DN8,IF(Assms!$F$37=4,LXtables!EA8,IF(Assms!$F$37=5,LXtables!EN8,LXtables!FA8))))) -> 0.12 | AU8: 5 | AV8: =IF(Assms!$F$37=1,LXtables!FD8,IF(Assms!$F$37=2,LXtables!FQ8,IF(Assms!$F$37=3,LXtables!GD8,IF(Assms!$F$37=4,LXtables!GQ8,IF(Assms!$F$37=5,LXtables!HD8,LXtables!HQ8))))) -> 0.1 | AW8: =IF(Assms!$F$37=1,LXtables!FE8,IF(Assms!$F$37=2,LXtables!FR8,IF(Assms!$F$37=3,LXtables!GE8,IF(Assms!$F$37=4,LXtables!GR8,IF(Assms!$F$37=5,LXtables!HE8,LXtables!HR8))))) -> 0.09 | AX8: =IF(Assms!$F$37=1,LXtables!FF8,IF(Assms!$F$37=2,LXtables!FS8,IF(Assms!$F$37=3,LXtables!GF8,IF(Assms!$F$37=4,LXtables!GS8,IF(Assms!$F$37=5,LXtables!HF8,LXtables!HS8))))) -> 0.07 | AY8: =IF(Assms!$F$37=1,LXtables!FG8,IF(Assms!$F$37=2,LXtables!FT8,IF(Assms!$F$37=3,LXtables!GG8,IF(Assms!$F$37=4,LXtables!GT8,IF(Assms!$F$37=5,LXtables!HG8,LXtables!HT8))))) -> 0.07 | AZ8: =IF(Assms!$F$37=1,LXtables!FH8,IF(Assms!$F$37=2,LXtables!FU8,IF(Assms!$F$37=3,LXtables!GH8,IF(Assms!$F$37=4,LXtables!GU8,IF(Assms!$F$37=5,LXtables!HH8,LXtables!HU8))))) -> 0.06 | BA8: =IF(Assms!$F$37=1,LXtables!FI8,IF(Assms!$F$37=2,LXtables!FV8,IF(Assms!$F$37=3,LXtables!GI8,IF(Assms!$F$37=4,LXtables!GV8,IF(Assms!$F$37=5,LXtables!HI8,LXtables!HV8))))) -> 0.06 | BB8: =IF(Assms!$F$37=1,LXtables!FJ8,IF(Assms!$F$37=2,LXtables!FW8,IF(Assms!$F$37=3,LXtables!GJ8,IF(Assms!$F$37=4,LXtables!GW8,IF(Assms!$F$37=5,LXtables!HJ8,LXtables!HW8))))) -> 0.07 | BC8: =IF(Assms!$F$37=1,LXtables!FK8,IF(Assms!$F$37=2,LXtables!FX8,IF(Assms!$F$37=3,LXtables!GK8,IF(Assms!$F$37=4,LXtables!GX8,IF(Assms!$F$37=5,LXtables!HK8,LXtables!HX8))))) -> 0.07 | ... BG8: =IF(Assms!$F$37=1,LXtables!FO8,IF(Assms!$F$37=2,LXtables!GB8,IF(Assms!$F$37=3,LXtables!GO8,IF(Assms!$F$37=4,LXtables!HB8,IF(Assms!$F$37=5,LXtables!HO8,LXtables!IB8))))) -> 0.15 | BH8: 5 | BI8: =IF(Assms!$F$37=1,LXtables!IE8,IF(Assms!$F$37=2,LXtables!IR8,IF(Assms!$F$37=3,LXtables!JE8,IF(Assms!$F$37=4,LXtables!JR8,IF(Assms!$F$37=5,LXtables!KE8,LXtables!KR8))))) -> 0.13 | BJ8: =IF(Assms!$F$37=1,LXtables!IF8,IF(Assms!$F$37=2,LXtables!IS8,IF(Assms!$F$37=3,LXtables!JF8,IF(Assms!$F$37=4,LXtables!JS8,IF(Assms!$F$37=5,LXtables!KF8,LXtables!KS8))))) -> 0.12 | BK8: =IF(Assms!$F$37=1,LXtables!IG8,IF(Assms!$F$37=2,LXtables!IT8,IF(Assms!$F$37=3,LXtables!JG8,IF(Assms!$F$37=4,LXtables!JT8,IF(Assms!$F$37=5,LXtables!KG8,LXtables!KT8))))) -> 0.1 | BL8: =IF(Assms!$F$37=1,LXtables!IH8,IF(Assms!$F$37=2,LXtables!IU8,IF(Assms!$F$37=3,LXtables!JH8,IF(Assms!$F$37=4,LXtables!JU8,IF(Assms!$F$37=5,LXtables!KH8,LXtables!KU8))))) -> 0.09 | BM8: =IF(Assms!$F$37=1,LXtables!II8,IF(Assms!$F$37=2,LXtables!IV8,IF(Assms!$F$37=3,LXtables!JI8,IF(Assms!$F$37=4,LXtables!JV8,IF(Assms!$F$37=5,LXtables!KI8,LXtables!KV8))))) -> 0.08 | BN8: =IF(Assms!$F$37=1,LXtables!IJ8,IF(Assms!$F$37=2,LXtables!IW8,IF(Assms!$F$37=3,LXtables!JJ8,IF(Assms!$F$37=4,LXtables!JW8,IF(Assms!$F$37=5,LXtables!KJ8,LXtables!KW8))))) -> 0.09 | BO8: =IF(Assms!$F$37=1,LXtables!IK8,IF(Assms!$F$37=2,LXtables!IX8,IF(Assms!$F$37=3,LXtables!JK8,IF(Assms!$F$37=4,LXtables!JX8,IF(Assms!$F$37=5,LXtables!KK8,LXtables!KX8))))) -> 0.09 | BP8: =IF(Assms!$F$37=1,LXtables!IL8,IF(Assms!$F$37=2,LXtables!IY8,IF(Assms!$F$37=3,LXtables!JL8,IF(Assms!$F$37=4,LXtables!JY8,IF(Assms!$F$37=5,LXtables!KL8,LXtables!KY8))))) -> 0.09 | ... BT8: =IF(Assms!$F$37=1,LXtables!IP8,IF(Assms!$F$37=2,LXtables!JC8,IF(Assms!$F$37=3,LXtables!JP8,IF(Assms!$F$37=4,LXtables!KC8,IF(Assms!$F$37=5,LXtables!KP8,LXtables!LC8))))) -> 0.19
A9: 6 | B9: =IF(Assms!$C$33<20,$I9,IF(Assms!$C$33>75,$T9,HLOOKUP(Assms!$C$33,$I$3:$T$15,$H9+1))) -> 0.07 | C9: =IF(Assms!$C$33<20,$I23,IF(Assms!$C$33>75,$T23,HLOOKUP(Assms!$C$33,$I$17:$T$34,$H23+1))) -> 0.05 | D9: =IF(Assms!$C$33<20,$I42,IF(Assms!$C$33>75,$T42,HLOOKUP(Assms!$C$33,$I$36:$T$58,$H42+1))) -> 0.04 | E9: =IF(Assms!$C$33<20,$I66,IF(Assms!$C$33>75,$T66,HLOOKUP(Assms!$C$33,$I$60:$T$87,$H66+1))) -> 0.04 | F9: =IF(Assms!$C$33<20,$I95,IF(Assms!$C$33>75,$T95,HLOOKUP(Assms!$C$33,$I$89:$T$119,$H95+1))) -> 0.04 | G9: =HLOOKUP(Assms!$C$34,$A$3:$F$41,A9+1) -> 0.04 | H9: 6 | I9: =IF(Assms!$C$36=1,V9,IF(Assms!$C$36=2,AI9,IF(Assms!$C$36=3,AV9,BI9))) -> 0.07 | J9: =IF(Assms!$C$36=1,W9,IF(Assms!$C$36=2,AJ9,IF(Assms!$C$36=3,AW9,BJ9))) -> 0.07 | K9: =IF(Assms!$C$36=1,X9,IF(Assms!$C$36=2,AK9,IF(Assms!$C$36=3,AX9,BK9))) -> 0.05 | L9: =IF(Assms!$C$36=1,Y9,IF(Assms!$C$36=2,AL9,IF(Assms!$C$36=3,AY9,BL9))) -> 0.05 | M9: =IF(Assms!$C$36=1,Z9,IF(Assms!$C$36=2,AM9,IF(Assms!$C$36=3,AZ9,BM9))) -> 0.05 | N9: =IF(Assms!$C$36=1,AA9,IF(Assms!$C$36=2,AN9,IF(Assms!$C$36=3,BA9,BN9))) -> 0.05 | O9: =IF(Assms!$C$36=1,AB9,IF(Assms!$C$36=2,AO9,IF(Assms!$C$36=3,BB9,BO9))) -> 0.05 | P9: =IF(Assms!$C$36=1,AC9,IF(Assms!$C$36=2,AP9,IF(Assms!$C$36=3,BC9,BP9))) -> 0.05 | ... T9: =IF(Assms!$C$36=1,AG9,IF(Assms!$C$36=2,AT9,IF(Assms!$C$36=3,BG9,BT9))) -> 0.07 | U9: 6 | V9: =IF(Assms!$F$37=1,LXtables!B9,IF(Assms!$F$37=2,LXtables!O9,IF(Assms!$F$37=3,LXtables!AB9,IF(Assms!$F$37=4,LXtables!AO9,IF(Assms!$F$37=5,LXtables!BB9,LXtables!BO9))))) -> 0.07 | W9: =IF(Assms!$F$37=1,LXtables!C9,IF(Assms!$F$37=2,LXtables!P9,IF(Assms!$F$37=3,LXtables!AC9,IF(Assms!$F$37=4,LXtables!AP9,IF(Assms!$F$37=5,LXtables!BC9,LXtables!BP9))))) -> 0.07 | X9: =IF(Assms!$F$37=1,LXtables!D9,IF(Assms!$F$37=2,LXtables!Q9,IF(Assms!$F$37=3,LXtables!AD9,IF(Assms!$F$37=4,LXtables!AQ9,IF(Assms!$F$37=5,LXtables!BD9,LXtables!BQ9))))) -> 0.05 | Y9: =IF(Assms!$F$37=1,LXtables!E9,IF(Assms!$F$37=2,LXtables!R9,IF(Assms!$F$37=3,LXtables!AE9,IF(Assms!$F$37=4,LXtables!AR9,IF(Assms!$F$37=5,LXtables!BE9,LXtables!BR9))))) -> 0.05 | Z9: =IF(Assms!$F$37=1,LXtables!F9,IF(Assms!$F$37=2,LXtables!S9,IF(Assms!$F$37=3,LXtables!AF9,IF(Assms!$F$37=4,LXtables!AS9,IF(Assms!$F$37=5,LXtables!BF9,LXtables!BS9))))) -> 0.05 | AA9: =IF(Assms!$F$37=1,LXtables!G9,IF(Assms!$F$37=2,LXtables!T9,IF(Assms!$F$37=3,LXtables!AG9,IF(Assms!$F$37=4,LXtables!AT9,IF(Assms!$F$37=5,LXtables!BG9,LXtables!BT9))))) -> 0.05 | AB9: =IF(Assms!$F$37=1,LXtables!H9,IF(Assms!$F$37=2,LXtables!U9,IF(Assms!$F$37=3,LXtables!AH9,IF(Assms!$F$37=4,LXtables!AU9,IF(Assms!$F$37=5,LXtables!BH9,LXtables!BU9))))) -> 0.05 | AC9: =IF(Assms!$F$37=1,LXtables!I9,IF(Assms!$F$37=2,LXtables!V9,IF(Assms!$F$37=3,LXtables!AI9,IF(Assms!$F$37=4,LXtables!AV9,IF(Assms!$F$37=5,LXtables!BI9,LXtables!BV9))))) -> 0.05 | ... AG9: =IF(Assms!$F$37=1,LXtables!M9,IF(Assms!$F$37=2,LXtables!Z9,IF(Assms!$F$37=3,LXtables!AM9,IF(Assms!$F$37=4,LXtables!AZ9,IF(Assms!$F$37=5,LXtables!BM9,LXtables!BZ9))))) -> 0.07 | AH9: 6 | AI9: =IF(Assms!$F$37=1,LXtables!CC9,IF(Assms!$F$37=2,LXtables!CP9,IF(Assms!$F$37=3,LXtables!DC9,IF(Assms!$F$37=4,LXtables!DP9,IF(Assms!$F$37=5,LXtables!EC9,LXtables!EP9))))) -> 0.08 | AJ9: =IF(Assms!$F$37=1,LXtables!CD9,IF(Assms!$F$37=2,LXtables!CQ9,IF(Assms!$F$37=3,LXtables!DD9,IF(Assms!$F$37=4,LXtables!DQ9,IF(Assms!$F$37=5,LXtables!ED9,LXtables!EQ9))))) -> 0.08 | AK9: =IF(Assms!$F$37=1,LXtables!CE9,IF(Assms!$F$37=2,LXtables!CR9,IF(Assms!$F$37=3,LXtables!DE9,IF(Assms!$F$37=4,LXtables!DR9,IF(Assms!$F$37=5,LXtables!EE9,LXtables!ER9))))) -> 0.06 | AL9: =IF(Assms!$F$37=1,LXtables!CF9,IF(Assms!$F$37=2,LXtables!CS9,IF(Assms!$F$37=3,LXtables!DF9,IF(Assms!$F$37=4,LXtables!DS9,IF(Assms!$F$37=5,LXtables!EF9,LXtables!ES9))))) -> 0.05 | AM9: =IF(Assms!$F$37=1,LXtables!CG9,IF(Assms!$F$37=2,LXtables!CT9,IF(Assms!$F$37=3,LXtables!DG9,IF(Assms!$F$37=4,LXtables!DT9,IF(Assms!$F$37=5,LXtables!EG9,LXtables!ET9))))) -> 0.05 | AN9: =IF(Assms!$F$37=1,LXtables!CH9,IF(Assms!$F$37=2,LXtables!CU9,IF(Assms!$F$37=3,LXtables!DH9,IF(Assms!$F$37=4,LXtables!DU9,IF(Assms!$F$37=5,LXtables!EH9,LXtables!EU9))))) -> 0.05 | AO9: =IF(Assms!$F$37=1,LXtables!CI9,IF(Assms!$F$37=2,LXtables!CV9,IF(Assms!$F$37=3,LXtables!DI9,IF(Assms!$F$37=4,LXtables!DV9,IF(Assms!$F$37=5,LXtables!EI9,LXtables!EV9))))) -> 0.06 | AP9: =IF(Assms!$F$37=1,LXtables!CJ9,IF(Assms!$F$37=2,LXtables!CW9,IF(Assms!$F$37=3,LXtables!DJ9,IF(Assms!$F$37=4,LXtables!DW9,IF(Assms!$F$37=5,LXtables!EJ9,LXtables!EW9))))) -> 0.06 | ... AT9: =IF(Assms!$F$37=1,LXtables!CN9,IF(Assms!$F$37=2,LXtables!DA9,IF(Assms!$F$37=3,LXtables!DN9,IF(Assms!$F$37=4,LXtables!EA9,IF(Assms!$F$37=5,LXtables!EN9,LXtables!FA9))))) -> 0.08 | AU9: 6 | AV9: =IF(Assms!$F$37=1,LXtables!FD9,IF(Assms!$F$37=2,LXtables!FQ9,IF(Assms!$F$37=3,LXtables!GD9,IF(Assms!$F$37=4,LXtables!GQ9,IF(Assms!$F$37=5,LXtables!HD9,LXtables!HQ9))))) -> 0.1 | AW9: =IF(Assms!$F$37=1,LXtables!FE9,IF(Assms!$F$37=2,LXtables!FR9,IF(Assms!$F$37=3,LXtables!GE9,IF(Assms!$F$37=4,LXtables!GR9,IF(Assms!$F$37=5,LXtables!HE9,LXtables!HR9))))) -> 0.09 | AX9: =IF(Assms!$F$37=1,LXtables!FF9,IF(Assms!$F$37=2,LXtables!FS9,IF(Assms!$F$37=3,LXtables!GF9,IF(Assms!$F$37=4,LXtables!GS9,IF(Assms!$F$37=5,LXtables!HF9,LXtables!HS9))))) -> 0.07 | AY9: =IF(Assms!$F$37=1,LXtables!FG9,IF(Assms!$F$37=2,LXtables!FT9,IF(Assms!$F$37=3,LXtables!GG9,IF(Assms!$F$37=4,LXtables!GT9,IF(Assms!$F$37=5,LXtables!HG9,LXtables!HT9))))) -> 0.06 | AZ9: =IF(Assms!$F$37=1,LXtables!FH9,IF(Assms!$F$37=2,LXtables!FU9,IF(Assms!$F$37=3,LXtables!GH9,IF(Assms!$F$37=4,LXtables!GU9,IF(Assms!$F$37=5,LXtables!HH9,LXtables!HU9))))) -> 0.06 | BA9: =IF(Assms!$F$37=1,LXtables!FI9,IF(Assms!$F$37=2,LXtables!FV9,IF(Assms!$F$37=3,LXtables!GI9,IF(Assms!$F$37=4,LXtables!GV9,IF(Assms!$F$37=5,LXtables!HI9,LXtables!HV9))))) -> 0.06 | BB9: =IF(Assms!$F$37=1,LXtables!FJ9,IF(Assms!$F$37=2,LXtables!FW9,IF(Assms!$F$37=3,LXtables!GJ9,IF(Assms!$F$37=4,LXtables!GW9,IF(Assms!$F$37=5,LXtables!HJ9,LXtables!HW9))))) -> 0.07 | BC9: =IF(Assms!$F$37=1,LXtables!FK9,IF(Assms!$F$37=2,LXtables!FX9,IF(Assms!$F$37=3,LXtables!GK9,IF(Assms!$F$37=4,LXtables!GX9,IF(Assms!$F$37=5,LXtables!HK9,LXtables!HX9))))) -> 0.07 | ... BG9: =IF(Assms!$F$37=1,LXtables!FO9,IF(Assms!$F$37=2,LXtables!GB9,IF(Assms!$F$37=3,LXtables!GO9,IF(Assms!$F$37=4,LXtables!HB9,IF(Assms!$F$37=5,LXtables!HO9,LXtables!IB9))))) -> 0.09 | BH9: 6 | BI9: =IF(Assms!$F$37=1,LXtables!IE9,IF(Assms!$F$37=2,LXtables!IR9,IF(Assms!$F$37=3,LXtables!JE9,IF(Assms!$F$37=4,LXtables!JR9,IF(Assms!$F$37=5,LXtables!KE9,LXtables!KR9))))) -> 0.12 | BJ9: =IF(Assms!$F$37=1,LXtables!IF9,IF(Assms!$F$37=2,LXtables!IS9,IF(Assms!$F$37=3,LXtables!JF9,IF(Assms!$F$37=4,LXtables!JS9,IF(Assms!$F$37=5,LXtables!KF9,LXtables!KS9))))) -> 0.12 | BK9: =IF(Assms!$F$37=1,LXtables!IG9,IF(Assms!$F$37=2,LXtables!IT9,IF(Assms!$F$37=3,LXtables!JG9,IF(Assms!$F$37=4,LXtables!JT9,IF(Assms!$F$37=5,LXtables!KG9,LXtables!KT9))))) -> 0.09 | BL9: =IF(Assms!$F$37=1,LXtables!IH9,IF(Assms!$F$37=2,LXtables!IU9,IF(Assms!$F$37=3,LXtables!JH9,IF(Assms!$F$37=4,LXtables!JU9,IF(Assms!$F$37=5,LXtables!KH9,LXtables!KU9))))) -> 0.08 | BM9: =IF(Assms!$F$37=1,LXtables!II9,IF(Assms!$F$37=2,LXtables!IV9,IF(Assms!$F$37=3,LXtables!JI9,IF(Assms!$F$37=4,LXtables!JV9,IF(Assms!$F$37=5,LXtables!KI9,LXtables!KV9))))) -> 0.08 | BN9: =IF(Assms!$F$37=1,LXtables!IJ9,IF(Assms!$F$37=2,LXtables!IW9,IF(Assms!$F$37=3,LXtables!JJ9,IF(Assms!$F$37=4,LXtables!JW9,IF(Assms!$F$37=5,LXtables!KJ9,LXtables!KW9))))) -> 0.08 | BO9: =IF(Assms!$F$37=1,LXtables!IK9,IF(Assms!$F$37=2,LXtables!IX9,IF(Assms!$F$37=3,LXtables!JK9,IF(Assms!$F$37=4,LXtables!JX9,IF(Assms!$F$37=5,LXtables!KK9,LXtables!KX9))))) -> 0.08 | BP9: =IF(Assms!$F$37=1,LXtables!IL9,IF(Assms!$F$37=2,LXtables!IY9,IF(Assms!$F$37=3,LXtables!JL9,IF(Assms!$F$37=4,LXtables!JY9,IF(Assms!$F$37=5,LXtables!KL9,LXtables!KY9))))) -> 0.09 | ... BT9: =IF(Assms!$F$37=1,LXtables!IP9,IF(Assms!$F$37=2,LXtables!JC9,IF(Assms!$F$37=3,LXtables!JP9,IF(Assms!$F$37=4,LXtables!KC9,IF(Assms!$F$37=5,LXtables!KP9,LXtables!LC9))))) -> 0.11
A10: 7 | B10: =IF(Assms!$C$33<20,$I10,IF(Assms!$C$33>75,$T10,HLOOKUP(Assms!$C$33,$I$3:$T$15,$H10+1))) -> 0.07 | C10: =IF(Assms!$C$33<20,$I24,IF(Assms!$C$33>75,$T24,HLOOKUP(Assms!$C$33,$I$17:$T$34,$H24+1))) -> 0.05 | D10: =IF(Assms!$C$33<20,$I43,IF(Assms!$C$33>75,$T43,HLOOKUP(Assms!$C$33,$I$36:$T$58,$H43+1))) -> 0.04 | E10: =IF(Assms!$C$33<20,$I67,IF(Assms!$C$33>75,$T67,HLOOKUP(Assms!$C$33,$I$60:$T$87,$H67+1))) -> 0.03 | F10: =IF(Assms!$C$33<20,$I96,IF(Assms!$C$33>75,$T96,HLOOKUP(Assms!$C$33,$I$89:$T$119,$H96+1))) -> 0.04 | G10: =HLOOKUP(Assms!$C$34,$A$3:$F$41,A10+1) -> 0.03 | H10: 7 | I10: =IF(Assms!$C$36=1,V10,IF(Assms!$C$36=2,AI10,IF(Assms!$C$36=3,AV10,BI10))) -> 0.07 | J10: =IF(Assms!$C$36=1,W10,IF(Assms!$C$36=2,AJ10,IF(Assms!$C$36=3,AW10,BJ10))) -> 0.07 | K10: =IF(Assms!$C$36=1,X10,IF(Assms!$C$36=2,AK10,IF(Assms!$C$36=3,AX10,BK10))) -> 0.05 | L10: =IF(Assms!$C$36=1,Y10,IF(Assms!$C$36=2,AL10,IF(Assms!$C$36=3,AY10,BL10))) -> 0.05 | M10: =IF(Assms!$C$36=1,Z10,IF(Assms!$C$36=2,AM10,IF(Assms!$C$36=3,AZ10,BM10))) -> 0.04 | N10: =IF(Assms!$C$36=1,AA10,IF(Assms!$C$36=2,AN10,IF(Assms!$C$36=3,BA10,BN10))) -> 0.05 | O10: =IF(Assms!$C$36=1,AB10,IF(Assms!$C$36=2,AO10,IF(Assms!$C$36=3,BB10,BO10))) -> 0.05 | P10: =IF(Assms!$C$36=1,AC10,IF(Assms!$C$36=2,AP10,IF(Assms!$C$36=3,BC10,BP10))) -> 0.05 | ... T10: =IF(Assms!$C$36=1,AG10,IF(Assms!$C$36=2,AT10,IF(Assms!$C$36=3,BG10,BT10))) -> 0.07 | U10: 7 | V10: =IF(Assms!$F$37=1,LXtables!B10,IF(Assms!$F$37=2,LXtables!O10,IF(Assms!$F$37=3,LXtables!AB10,IF(Assms!$F$37=4,LXtables!AO10,IF(Assms!$F$37=5,LXtables!BB10,LXtables!BO10))))) -> 0.07 | W10: =IF(Assms!$F$37=1,LXtables!C10,IF(Assms!$F$37=2,LXtables!P10,IF(Assms!$F$37=3,LXtables!AC10,IF(Assms!$F$37=4,LXtables!AP10,IF(Assms!$F$37=5,LXtables!BC10,LXtables!BP10))))) -> 0.07 | X10: =IF(Assms!$F$37=1,LXtables!D10,IF(Assms!$F$37=2,LXtables!Q10,IF(Assms!$F$37=3,LXtables!AD10,IF(Assms!$F$37=4,LXtables!AQ10,IF(Assms!$F$37=5,LXtables!BD10,LXtables!BQ10))))) -> 0.05 | Y10: =IF(Assms!$F$37=1,LXtables!E10,IF(Assms!$F$37=2,LXtables!R10,IF(Assms!$F$37=3,LXtables!AE10,IF(Assms!$F$37=4,LXtables!AR10,IF(Assms!$F$37=5,LXtables!BE10,LXtables!BR10))))) -> 0.05 | Z10: =IF(Assms!$F$37=1,LXtables!F10,IF(Assms!$F$37=2,LXtables!S10,IF(Assms!$F$37=3,LXtables!AF10,IF(Assms!$F$37=4,LXtables!AS10,IF(Assms!$F$37=5,LXtables!BF10,LXtables!BS10))))) -> 0.04 | AA10: =IF(Assms!$F$37=1,LXtables!G10,IF(Assms!$F$37=2,LXtables!T10,IF(Assms!$F$37=3,LXtables!AG10,IF(Assms!$F$37=4,LXtables!AT10,IF(Assms!$F$37=5,LXtables!BG10,LXtables!BT10))))) -> 0.05 | AB10: =IF(Assms!$F$37=1,LXtables!H10,IF(Assms!$F$37=2,LXtables!U10,IF(Assms!$F$37=3,LXtables!AH10,IF(Assms!$F$37=4,LXtables!AU10,IF(Assms!$F$37=5,LXtables!BH10,LXtables!BU10))))) -> 0.05 | AC10: =IF(Assms!$F$37=1,LXtables!I10,IF(Assms!$F$37=2,LXtables!V10,IF(Assms!$F$37=3,LXtables!AI10,IF(Assms!$F$37=4,LXtables!AV10,IF(Assms!$F$37=5,LXtables!BI10,LXtables!BV10))))) -> 0.05 | ... AG10: =IF(Assms!$F$37=1,LXtables!M10,IF(Assms!$F$37=2,LXtables!Z10,IF(Assms!$F$37=3,LXtables!AM10,IF(Assms!$F$37=4,LXtables!AZ10,IF(Assms!$F$37=5,LXtables!BM10,LXtables!BZ10))))) -> 0.07 | AH10: 7 | AI10: =IF(Assms!$F$37=1,LXtables!CC10,IF(Assms!$F$37=2,LXtables!CP10,IF(Assms!$F$37=3,LXtables!DC10,IF(Assms!$F$37=4,LXtables!DP10,IF(Assms!$F$37=5,LXtables!EC10,LXtables!EP10))))) -> 0.08 | AJ10: =IF(Assms!$F$37=1,LXtables!CD10,IF(Assms!$F$37=2,LXtables!CQ10,IF(Assms!$F$37=3,LXtables!DD10,IF(Assms!$F$37=4,LXtables!DQ10,IF(Assms!$F$37=5,LXtables!ED10,LXtables!EQ10))))) -> 0.08 | AK10: =IF(Assms!$F$37=1,LXtables!CE10,IF(Assms!$F$37=2,LXtables!CR10,IF(Assms!$F$37=3,LXtables!DE10,IF(Assms!$F$37=4,LXtables!DR10,IF(Assms!$F$37=5,LXtables!EE10,LXtables!ER10))))) -> 0.06 | AL10: =IF(Assms!$F$37=1,LXtables!CF10,IF(Assms!$F$37=2,LXtables!CS10,IF(Assms!$F$37=3,LXtables!DF10,IF(Assms!$F$37=4,LXtables!DS10,IF(Assms!$F$37=5,LXtables!EF10,LXtables!ES10))))) -> 0.05 | AM10: =IF(Assms!$F$37=1,LXtables!CG10,IF(Assms!$F$37=2,LXtables!CT10,IF(Assms!$F$37=3,LXtables!DG10,IF(Assms!$F$37=4,LXtables!DT10,IF(Assms!$F$37=5,LXtables!EG10,LXtables!ET10))))) -> 0.05 | AN10: =IF(Assms!$F$37=1,LXtables!CH10,IF(Assms!$F$37=2,LXtables!CU10,IF(Assms!$F$37=3,LXtables!DH10,IF(Assms!$F$37=4,LXtables!DU10,IF(Assms!$F$37=5,LXtables!EH10,LXtables!EU10))))) -> 0.05 | AO10: =IF(Assms!$F$37=1,LXtables!CI10,IF(Assms!$F$37=2,LXtables!CV10,IF(Assms!$F$37=3,LXtables!DI10,IF(Assms!$F$37=4,LXtables!DV10,IF(Assms!$F$37=5,LXtables!EI10,LXtables!EV10))))) -> 0.05 | AP10: =IF(Assms!$F$37=1,LXtables!CJ10,IF(Assms!$F$37=2,LXtables!CW10,IF(Assms!$F$37=3,LXtables!DJ10,IF(Assms!$F$37=4,LXtables!DW10,IF(Assms!$F$37=5,LXtables!EJ10,LXtables!EW10))))) -> 0.06 | ... AT10: =IF(Assms!$F$37=1,LXtables!CN10,IF(Assms!$F$37=2,LXtables!DA10,IF(Assms!$F$37=3,LXtables!DN10,IF(Assms!$F$37=4,LXtables!EA10,IF(Assms!$F$37=5,LXtables!EN10,LXtables!FA10))))) -> 0.07 | AU10: 7 | AV10: =IF(Assms!$F$37=1,LXtables!FD10,IF(Assms!$F$37=2,LXtables!FQ10,IF(Assms!$F$37=3,LXtables!GD10,IF(Assms!$F$37=4,LXtables!GQ10,IF(Assms!$F$37=5,LXtables!HD10,LXtables!HQ10))))) -> 0.09 | AW10: =IF(Assms!$F$37=1,LXtables!FE10,IF(Assms!$F$37=2,LXtables!FR10,IF(Assms!$F$37=3,LXtables!GE10,IF(Assms!$F$37=4,LXtables!GR10,IF(Assms!$F$37=5,LXtables!HE10,LXtables!HR10))))) -> 0.09 | AX10: =IF(Assms!$F$37=1,LXtables!FF10,IF(Assms!$F$37=2,LXtables!FS10,IF(Assms!$F$37=3,LXtables!GF10,IF(Assms!$F$37=4,LXtables!GS10,IF(Assms!$F$37=5,LXtables!HF10,LXtables!HS10))))) -> 0.07 | AY10: =IF(Assms!$F$37=1,LXtables!FG10,IF(Assms!$F$37=2,LXtables!FT10,IF(Assms!$F$37=3,LXtables!GG10,IF(Assms!$F$37=4,LXtables!GT10,IF(Assms!$F$37=5,LXtables!HG10,LXtables!HT10))))) -> 0.06 | AZ10: =IF(Assms!$F$37=1,LXtables!FH10,IF(Assms!$F$37=2,LXtables!FU10,IF(Assms!$F$37=3,LXtables!GH10,IF(Assms!$F$37=4,LXtables!GU10,IF(Assms!$F$37=5,LXtables!HH10,LXtables!HU10))))) -> 0.06 | BA10: =IF(Assms!$F$37=1,LXtables!FI10,IF(Assms!$F$37=2,LXtables!FV10,IF(Assms!$F$37=3,LXtables!GI10,IF(Assms!$F$37=4,LXtables!GV10,IF(Assms!$F$37=5,LXtables!HI10,LXtables!HV10))))) -> 0.06 | BB10: =IF(Assms!$F$37=1,LXtables!FJ10,IF(Assms!$F$37=2,LXtables!FW10,IF(Assms!$F$37=3,LXtables!GJ10,IF(Assms!$F$37=4,LXtables!GW10,IF(Assms!$F$37=5,LXtables!HJ10,LXtables!HW10))))) -> 0.06 | BC10: =IF(Assms!$F$37=1,LXtables!FK10,IF(Assms!$F$37=2,LXtables!FX10,IF(Assms!$F$37=3,LXtables!GK10,IF(Assms!$F$37=4,LXtables!GX10,IF(Assms!$F$37=5,LXtables!HK10,LXtables!HX10))))) -> 0.06 | ... BG10: =IF(Assms!$F$37=1,LXtables!FO10,IF(Assms!$F$37=2,LXtables!GB10,IF(Assms!$F$37=3,LXtables!GO10,IF(Assms!$F$37=4,LXtables!HB10,IF(Assms!$F$37=5,LXtables!HO10,LXtables!IB10))))) -> 0.09 | BH10: 7 | BI10: =IF(Assms!$F$37=1,LXtables!IE10,IF(Assms!$F$37=2,LXtables!IR10,IF(Assms!$F$37=3,LXtables!JE10,IF(Assms!$F$37=4,LXtables!JR10,IF(Assms!$F$37=5,LXtables!KE10,LXtables!KR10))))) -> 0.12 | BJ10: =IF(Assms!$F$37=1,LXtables!IF10,IF(Assms!$F$37=2,LXtables!IS10,IF(Assms!$F$37=3,LXtables!JF10,IF(Assms!$F$37=4,LXtables!JS10,IF(Assms!$F$37=5,LXtables!KF10,LXtables!KS10))))) -> 0.11 | BK10: =IF(Assms!$F$37=1,LXtables!IG10,IF(Assms!$F$37=2,LXtables!IT10,IF(Assms!$F$37=3,LXtables!JG10,IF(Assms!$F$37=4,LXtables!JT10,IF(Assms!$F$37=5,LXtables!KG10,LXtables!KT10))))) -> 0.09 | BL10: =IF(Assms!$F$37=1,LXtables!IH10,IF(Assms!$F$37=2,LXtables!IU10,IF(Assms!$F$37=3,LXtables!JH10,IF(Assms!$F$37=4,LXtables!JU10,IF(Assms!$F$37=5,LXtables!KH10,LXtables!KU10))))) -> 0.08 | BM10: =IF(Assms!$F$37=1,LXtables!II10,IF(Assms!$F$37=2,LXtables!IV10,IF(Assms!$F$37=3,LXtables!JI10,IF(Assms!$F$37=4,LXtables!JV10,IF(Assms!$F$37=5,LXtables!KI10,LXtables!KV10))))) -> 0.07 | BN10: =IF(Assms!$F$37=1,LXtables!IJ10,IF(Assms!$F$37=2,LXtables!IW10,IF(Assms!$F$37=3,LXtables!JJ10,IF(Assms!$F$37=4,LXtables!JW10,IF(Assms!$F$37=5,LXtables!KJ10,LXtables!KW10))))) -> 0.08 | BO10: =IF(Assms!$F$37=1,LXtables!IK10,IF(Assms!$F$37=2,LXtables!IX10,IF(Assms!$F$37=3,LXtables!JK10,IF(Assms!$F$37=4,LXtables!JX10,IF(Assms!$F$37=5,LXtables!KK10,LXtables!KX10))))) -> 0.08 | BP10: =IF(Assms!$F$37=1,LXtables!IL10,IF(Assms!$F$37=2,LXtables!IY10,IF(Assms!$F$37=3,LXtables!JL10,IF(Assms!$F$37=4,LXtables!JY10,IF(Assms!$F$37=5,LXtables!KL10,LXtables!KY10))))) -> 0.08 | ... BT10: =IF(Assms!$F$37=1,LXtables!IP10,IF(Assms!$F$37=2,LXtables!JC10,IF(Assms!$F$37=3,LXtables!JP10,IF(Assms!$F$37=4,LXtables!KC10,IF(Assms!$F$37=5,LXtables!KP10,LXtables!LC10))))) -> 0.11
A11: 8 | B11: =IF(Assms!$C$33<20,$I11,IF(Assms!$C$33>75,$T11,HLOOKUP(Assms!$C$33,$I$3:$T$15,$H11+1))) -> 0.07 | C11: =IF(Assms!$C$33<20,$I25,IF(Assms!$C$33>75,$T25,HLOOKUP(Assms!$C$33,$I$17:$T$34,$H25+1))) -> 0.05 | D11: =IF(Assms!$C$33<20,$I44,IF(Assms!$C$33>75,$T44,HLOOKUP(Assms!$C$33,$I$36:$T$58,$H44+1))) -> 0.04 | E11: =IF(Assms!$C$33<20,$I68,IF(Assms!$C$33>75,$T68,HLOOKUP(Assms!$C$33,$I$60:$T$87,$H68+1))) -> 0.03 | F11: =IF(Assms!$C$33<20,$I97,IF(Assms!$C$33>75,$T97,HLOOKUP(Assms!$C$33,$I$89:$T$119,$H97+1))) -> 0.03 | G11: =HLOOKUP(Assms!$C$34,$A$3:$F$41,A11+1) -> 0.03 | H11: 8 | I11: =IF(Assms!$C$36=1,V11,IF(Assms!$C$36=2,AI11,IF(Assms!$C$36=3,AV11,BI11))) -> 0.07 | J11: =IF(Assms!$C$36=1,W11,IF(Assms!$C$36=2,AJ11,IF(Assms!$C$36=3,AW11,BJ11))) -> 0.07 | K11: =IF(Assms!$C$36=1,X11,IF(Assms!$C$36=2,AK11,IF(Assms!$C$36=3,AX11,BK11))) -> 0.05 | L11: =IF(Assms!$C$36=1,Y11,IF(Assms!$C$36=2,AL11,IF(Assms!$C$36=3,AY11,BL11))) -> 0.05 | M11: =IF(Assms!$C$36=1,Z11,IF(Assms!$C$36=2,AM11,IF(Assms!$C$36=3,AZ11,BM11))) -> 0.04 | N11: =IF(Assms!$C$36=1,AA11,IF(Assms!$C$36=2,AN11,IF(Assms!$C$36=3,BA11,BN11))) -> 0.05 | O11: =IF(Assms!$C$36=1,AB11,IF(Assms!$C$36=2,AO11,IF(Assms!$C$36=3,BB11,BO11))) -> 0.05 | P11: =IF(Assms!$C$36=1,AC11,IF(Assms!$C$36=2,AP11,IF(Assms!$C$36=3,BC11,BP11))) -> 0.05 | ... T11: =IF(Assms!$C$36=1,AG11,IF(Assms!$C$36=2,AT11,IF(Assms!$C$36=3,BG11,BT11))) -> 0.07 | U11: 8 | V11: =IF(Assms!$F$37=1,LXtables!B11,IF(Assms!$F$37=2,LXtables!O11,IF(Assms!$F$37=3,LXtables!AB11,IF(Assms!$F$37=4,LXtables!AO11,IF(Assms!$F$37=5,LXtables!BB11,LXtables!BO11))))) -> 0.07 | W11: =IF(Assms!$F$37=1,LXtables!C11,IF(Assms!$F$37=2,LXtables!P11,IF(Assms!$F$37=3,LXtables!AC11,IF(Assms!$F$37=4,LXtables!AP11,IF(Assms!$F$37=5,LXtables!BC11,LXtables!BP11))))) -> 0.07 | X11: =IF(Assms!$F$37=1,LXtables!D11,IF(Assms!$F$37=2,LXtables!Q11,IF(Assms!$F$37=3,LXtables!AD11,IF(Assms!$F$37=4,LXtables!AQ11,IF(Assms!$F$37=5,LXtables!BD11,LXtables!BQ11))))) -> 0.05 | Y11: =IF(Assms!$F$37=1,LXtables!E11,IF(Assms!$F$37=2,LXtables!R11,IF(Assms!$F$37=3,LXtables!AE11,IF(Assms!$F$37=4,LXtables!AR11,IF(Assms!$F$37=5,LXtables!BE11,LXtables!BR11))))) -> 0.05 | Z11: =IF(Assms!$F$37=1,LXtables!F11,IF(Assms!$F$37=2,LXtables!S11,IF(Assms!$F$37=3,LXtables!AF11,IF(Assms!$F$37=4,LXtables!AS11,IF(Assms!$F$37=5,LXtables!BF11,LXtables!BS11))))) -> 0.04 | AA11: =IF(Assms!$F$37=1,LXtables!G11,IF(Assms!$F$37=2,LXtables!T11,IF(Assms!$F$37=3,LXtables!AG11,IF(Assms!$F$37=4,LXtables!AT11,IF(Assms!$F$37=5,LXtables!BG11,LXtables!BT11))))) -> 0.05 | AB11: =IF(Assms!$F$37=1,LXtables!H11,IF(Assms!$F$37=2,LXtables!U11,IF(Assms!$F$37=3,LXtables!AH11,IF(Assms!$F$37=4,LXtables!AU11,IF(Assms!$F$37=5,LXtables!BH11,LXtables!BU11))))) -> 0.05 | AC11: =IF(Assms!$F$37=1,LXtables!I11,IF(Assms!$F$37=2,LXtables!V11,IF(Assms!$F$37=3,LXtables!AI11,IF(Assms!$F$37=4,LXtables!AV11,IF(Assms!$F$37=5,LXtables!BI11,LXtables!BV11))))) -> 0.05 | ... AG11: =IF(Assms!$F$37=1,LXtables!M11,IF(Assms!$F$37=2,LXtables!Z11,IF(Assms!$F$37=3,LXtables!AM11,IF(Assms!$F$37=4,LXtables!AZ11,IF(Assms!$F$37=5,LXtables!BM11,LXtables!BZ11))))) -> 0.07 | AH11: 8 | AI11: =IF(Assms!$F$37=1,LXtables!CC11,IF(Assms!$F$37=2,LXtables!CP11,IF(Assms!$F$37=3,LXtables!DC11,IF(Assms!$F$37=4,LXtables!DP11,IF(Assms!$F$37=5,LXtables!EC11,LXtables!EP11))))) -> 0.08 | AJ11: =IF(Assms!$F$37=1,LXtables!CD11,IF(Assms!$F$37=2,LXtables!CQ11,IF(Assms!$F$37=3,LXtables!DD11,IF(Assms!$F$37=4,LXtables!DQ11,IF(Assms!$F$37=5,LXtables!ED11,LXtables!EQ11))))) -> 0.07 | AK11: =IF(Assms!$F$37=1,LXtables!CE11,IF(Assms!$F$37=2,LXtables!CR11,IF(Assms!$F$37=3,LXtables!DE11,IF(Assms!$F$37=4,LXtables!DR11,IF(Assms!$F$37=5,LXtables!EE11,LXtables!ER11))))) -> 0.06 | AL11: =IF(Assms!$F$37=1,LXtables!CF11,IF(Assms!$F$37=2,LXtables!CS11,IF(Assms!$F$37=3,LXtables!DF11,IF(Assms!$F$37=4,LXtables!DS11,IF(Assms!$F$37=5,LXtables!EF11,LXtables!ES11))))) -> 0.05 | AM11: =IF(Assms!$F$37=1,LXtables!CG11,IF(Assms!$F$37=2,LXtables!CT11,IF(Assms!$F$37=3,LXtables!DG11,IF(Assms!$F$37=4,LXtables!DT11,IF(Assms!$F$37=5,LXtables!EG11,LXtables!ET11))))) -> 0.05 | AN11: =IF(Assms!$F$37=1,LXtables!CH11,IF(Assms!$F$37=2,LXtables!CU11,IF(Assms!$F$37=3,LXtables!DH11,IF(Assms!$F$37=4,LXtables!DU11,IF(Assms!$F$37=5,LXtables!EH11,LXtables!EU11))))) -> 0.05 | AO11: =IF(Assms!$F$37=1,LXtables!CI11,IF(Assms!$F$37=2,LXtables!CV11,IF(Assms!$F$37=3,LXtables!DI11,IF(Assms!$F$37=4,LXtables!DV11,IF(Assms!$F$37=5,LXtables!EI11,LXtables!EV11))))) -> 0.05 | AP11: =IF(Assms!$F$37=1,LXtables!CJ11,IF(Assms!$F$37=2,LXtables!CW11,IF(Assms!$F$37=3,LXtables!DJ11,IF(Assms!$F$37=4,LXtables!DW11,IF(Assms!$F$37=5,LXtables!EJ11,LXtables!EW11))))) -> 0.06 | ... AT11: =IF(Assms!$F$37=1,LXtables!CN11,IF(Assms!$F$37=2,LXtables!DA11,IF(Assms!$F$37=3,LXtables!DN11,IF(Assms!$F$37=4,LXtables!EA11,IF(Assms!$F$37=5,LXtables!EN11,LXtables!FA11))))) -> 0.07 | AU11: 8 | AV11: =IF(Assms!$F$37=1,LXtables!FD11,IF(Assms!$F$37=2,LXtables!FQ11,IF(Assms!$F$37=3,LXtables!GD11,IF(Assms!$F$37=4,LXtables!GQ11,IF(Assms!$F$37=5,LXtables!HD11,LXtables!HQ11))))) -> 0.09 | AW11: =IF(Assms!$F$37=1,LXtables!FE11,IF(Assms!$F$37=2,LXtables!FR11,IF(Assms!$F$37=3,LXtables!GE11,IF(Assms!$F$37=4,LXtables!GR11,IF(Assms!$F$37=5,LXtables!HE11,LXtables!HR11))))) -> 0.08 | AX11: =IF(Assms!$F$37=1,LXtables!FF11,IF(Assms!$F$37=2,LXtables!FS11,IF(Assms!$F$37=3,LXtables!GF11,IF(Assms!$F$37=4,LXtables!GS11,IF(Assms!$F$37=5,LXtables!HF11,LXtables!HS11))))) -> 0.07 | AY11: =IF(Assms!$F$37=1,LXtables!FG11,IF(Assms!$F$37=2,LXtables!FT11,IF(Assms!$F$37=3,LXtables!GG11,IF(Assms!$F$37=4,LXtables!GT11,IF(Assms!$F$37=5,LXtables!HG11,LXtables!HT11))))) -> 0.06 | AZ11: =IF(Assms!$F$37=1,LXtables!FH11,IF(Assms!$F$37=2,LXtables!FU11,IF(Assms!$F$37=3,LXtables!GH11,IF(Assms!$F$37=4,LXtables!GU11,IF(Assms!$F$37=5,LXtables!HH11,LXtables!HU11))))) -> 0.06 | BA11: =IF(Assms!$F$37=1,LXtables!FI11,IF(Assms!$F$37=2,LXtables!FV11,IF(Assms!$F$37=3,LXtables!GI11,IF(Assms!$F$37=4,LXtables!GV11,IF(Assms!$F$37=5,LXtables!HI11,LXtables!HV11))))) -> 0.06 | BB11: =IF(Assms!$F$37=1,LXtables!FJ11,IF(Assms!$F$37=2,LXtables!FW11,IF(Assms!$F$37=3,LXtables!GJ11,IF(Assms!$F$37=4,LXtables!GW11,IF(Assms!$F$37=5,LXtables!HJ11,LXtables!HW11))))) -> 0.06 | BC11: =IF(Assms!$F$37=1,LXtables!FK11,IF(Assms!$F$37=2,LXtables!FX11,IF(Assms!$F$37=3,LXtables!GK11,IF(Assms!$F$37=4,LXtables!GX11,IF(Assms!$F$37=5,LXtables!HK11,LXtables!HX11))))) -> 0.06 | ... BG11: =IF(Assms!$F$37=1,LXtables!FO11,IF(Assms!$F$37=2,LXtables!GB11,IF(Assms!$F$37=3,LXtables!GO11,IF(Assms!$F$37=4,LXtables!HB11,IF(Assms!$F$37=5,LXtables!HO11,LXtables!IB11))))) -> 0.08 | BH11: 8 | BI11: =IF(Assms!$F$37=1,LXtables!IE11,IF(Assms!$F$37=2,LXtables!IR11,IF(Assms!$F$37=3,LXtables!JE11,IF(Assms!$F$37=4,LXtables!JR11,IF(Assms!$F$37=5,LXtables!KE11,LXtables!KR11))))) -> 0.11 | BJ11: =IF(Assms!$F$37=1,LXtables!IF11,IF(Assms!$F$37=2,LXtables!IS11,IF(Assms!$F$37=3,LXtables!JF11,IF(Assms!$F$37=4,LXtables!JS11,IF(Assms!$F$37=5,LXtables!KF11,LXtables!KS11))))) -> 0.1 | BK11: =IF(Assms!$F$37=1,LXtables!IG11,IF(Assms!$F$37=2,LXtables!IT11,IF(Assms!$F$37=3,LXtables!JG11,IF(Assms!$F$37=4,LXtables!JT11,IF(Assms!$F$37=5,LXtables!KG11,LXtables!KT11))))) -> 0.08 | BL11: =IF(Assms!$F$37=1,LXtables!IH11,IF(Assms!$F$37=2,LXtables!IU11,IF(Assms!$F$37=3,LXtables!JH11,IF(Assms!$F$37=4,LXtables!JU11,IF(Assms!$F$37=5,LXtables!KH11,LXtables!KU11))))) -> 0.07 | BM11: =IF(Assms!$F$37=1,LXtables!II11,IF(Assms!$F$37=2,LXtables!IV11,IF(Assms!$F$37=3,LXtables!JI11,IF(Assms!$F$37=4,LXtables!JV11,IF(Assms!$F$37=5,LXtables!KI11,LXtables!KV11))))) -> 0.07 | BN11: =IF(Assms!$F$37=1,LXtables!IJ11,IF(Assms!$F$37=2,LXtables!IW11,IF(Assms!$F$37=3,LXtables!JJ11,IF(Assms!$F$37=4,LXtables!JW11,IF(Assms!$F$37=5,LXtables!KJ11,LXtables!KW11))))) -> 0.07 | BO11: =IF(Assms!$F$37=1,LXtables!IK11,IF(Assms!$F$37=2,LXtables!IX11,IF(Assms!$F$37=3,LXtables!JK11,IF(Assms!$F$37=4,LXtables!JX11,IF(Assms!$F$37=5,LXtables!KK11,LXtables!KX11))))) -> 0.08 | BP11: =IF(Assms!$F$37=1,LXtables!IL11,IF(Assms!$F$37=2,LXtables!IY11,IF(Assms!$F$37=3,LXtables!JL11,IF(Assms!$F$37=4,LXtables!JY11,IF(Assms!$F$37=5,LXtables!KL11,LXtables!KY11))))) -> 0.08 | ... BT11: =IF(Assms!$F$37=1,LXtables!IP11,IF(Assms!$F$37=2,LXtables!JC11,IF(Assms!$F$37=3,LXtables!JP11,IF(Assms!$F$37=4,LXtables!KC11,IF(Assms!$F$37=5,LXtables!KP11,LXtables!LC11))))) -> 0.1
A12: 9 | B12: =IF(Assms!$C$33<20,$I12,IF(Assms!$C$33>75,$T12,HLOOKUP(Assms!$C$33,$I$3:$T$15,$H12+1))) -> 0.08 | C12: =IF(Assms!$C$33<20,$I26,IF(Assms!$C$33>75,$T26,HLOOKUP(Assms!$C$33,$I$17:$T$34,$H26+1))) -> 0.04 | D12: =IF(Assms!$C$33<20,$I45,IF(Assms!$C$33>75,$T45,HLOOKUP(Assms!$C$33,$I$36:$T$58,$H45+1))) -> 0.04 | E12: =IF(Assms!$C$33<20,$I69,IF(Assms!$C$33>75,$T69,HLOOKUP(Assms!$C$33,$I$60:$T$87,$H69+1))) -> 0.03 | F12: =IF(Assms!$C$33<20,$I98,IF(Assms!$C$33>75,$T98,HLOOKUP(Assms!$C$33,$I$89:$T$119,$H98+1))) -> 0.03 | G12: =HLOOKUP(Assms!$C$34,$A$3:$F$41,A12+1) -> 0.03 | H12: 9 | I12: =IF(Assms!$C$36=1,V12,IF(Assms!$C$36=2,AI12,IF(Assms!$C$36=3,AV12,BI12))) -> 0.08 | J12: =IF(Assms!$C$36=1,W12,IF(Assms!$C$36=2,AJ12,IF(Assms!$C$36=3,AW12,BJ12))) -> 0.08 | K12: =IF(Assms!$C$36=1,X12,IF(Assms!$C$36=2,AK12,IF(Assms!$C$36=3,AX12,BK12))) -> 0.06 | L12: =IF(Assms!$C$36=1,Y12,IF(Assms!$C$36=2,AL12,IF(Assms!$C$36=3,AY12,BL12))) -> 0.05 | M12: =IF(Assms!$C$36=1,Z12,IF(Assms!$C$36=2,AM12,IF(Assms!$C$36=3,AZ12,BM12))) -> 0.05 | N12: =IF(Assms!$C$36=1,AA12,IF(Assms!$C$36=2,AN12,IF(Assms!$C$36=3,BA12,BN12))) -> 0.05 | O12: =IF(Assms!$C$36=1,AB12,IF(Assms!$C$36=2,AO12,IF(Assms!$C$36=3,BB12,BO12))) -> 0.06 | P12: =IF(Assms!$C$36=1,AC12,IF(Assms!$C$36=2,AP12,IF(Assms!$C$36=3,BC12,BP12))) -> 0.06 | ... T12: =IF(Assms!$C$36=1,AG12,IF(Assms!$C$36=2,AT12,IF(Assms!$C$36=3,BG12,BT12))) -> 0.08 | U12: 9 | V12: =IF(Assms!$F$37=1,LXtables!B12,IF(Assms!$F$37=2,LXtables!O12,IF(Assms!$F$37=3,LXtables!AB12,IF(Assms!$F$37=4,LXtables!AO12,IF(Assms!$F$37=5,LXtables!BB12,LXtables!BO12))))) -> 0.08 | W12: =IF(Assms!$F$37=1,LXtables!C12,IF(Assms!$F$37=2,LXtables!P12,IF(Assms!$F$37=3,LXtables!AC12,IF(Assms!$F$37=4,LXtables!AP12,IF(Assms!$F$37=5,LXtables!BC12,LXtables!BP12))))) -> 0.08 | X12: =IF(Assms!$F$37=1,LXtables!D12,IF(Assms!$F$37=2,LXtables!Q12,IF(Assms!$F$37=3,LXtables!AD12,IF(Assms!$F$37=4,LXtables!AQ12,IF(Assms!$F$37=5,LXtables!BD12,LXtables!BQ12))))) -> 0.06 | Y12: =IF(Assms!$F$37=1,LXtables!E12,IF(Assms!$F$37=2,LXtables!R12,IF(Assms!$F$37=3,LXtables!AE12,IF(Assms!$F$37=4,LXtables!AR12,IF(Assms!$F$37=5,LXtables!BE12,LXtables!BR12))))) -> 0.05 | Z12: =IF(Assms!$F$37=1,LXtables!F12,IF(Assms!$F$37=2,LXtables!S12,IF(Assms!$F$37=3,LXtables!AF12,IF(Assms!$F$37=4,LXtables!AS12,IF(Assms!$F$37=5,LXtables!BF12,LXtables!BS12))))) -> 0.05 | AA12: =IF(Assms!$F$37=1,LXtables!G12,IF(Assms!$F$37=2,LXtables!T12,IF(Assms!$F$37=3,LXtables!AG12,IF(Assms!$F$37=4,LXtables!AT12,IF(Assms!$F$37=5,LXtables!BG12,LXtables!BT12))))) -> 0.05 | AB12: =IF(Assms!$F$37=1,LXtables!H12,IF(Assms!$F$37=2,LXtables!U12,IF(Assms!$F$37=3,LXtables!AH12,IF(Assms!$F$37=4,LXtables!AU12,IF(Assms!$F$37=5,LXtables!BH12,LXtables!BU12))))) -> 0.06 | AC12: =IF(Assms!$F$37=1,LXtables!I12,IF(Assms!$F$37=2,LXtables!V12,IF(Assms!$F$37=3,LXtables!AI12,IF(Assms!$F$37=4,LXtables!AV12,IF(Assms!$F$37=5,LXtables!BI12,LXtables!BV12))))) -> 0.06 | ... AG12: =IF(Assms!$F$37=1,LXtables!M12,IF(Assms!$F$37=2,LXtables!Z12,IF(Assms!$F$37=3,LXtables!AM12,IF(Assms!$F$37=4,LXtables!AZ12,IF(Assms!$F$37=5,LXtables!BM12,LXtables!BZ12))))) -> 0.08 | AH12: 9 | AI12: =IF(Assms!$F$37=1,LXtables!CC12,IF(Assms!$F$37=2,LXtables!CP12,IF(Assms!$F$37=3,LXtables!DC12,IF(Assms!$F$37=4,LXtables!DP12,IF(Assms!$F$37=5,LXtables!EC12,LXtables!EP12))))) -> 0.09 | AJ12: =IF(Assms!$F$37=1,LXtables!CD12,IF(Assms!$F$37=2,LXtables!CQ12,IF(Assms!$F$37=3,LXtables!DD12,IF(Assms!$F$37=4,LXtables!DQ12,IF(Assms!$F$37=5,LXtables!ED12,LXtables!EQ12))))) -> 0.09 | AK12: =IF(Assms!$F$37=1,LXtables!CE12,IF(Assms!$F$37=2,LXtables!CR12,IF(Assms!$F$37=3,LXtables!DE12,IF(Assms!$F$37=4,LXtables!DR12,IF(Assms!$F$37=5,LXtables!EE12,LXtables!ER12))))) -> 0.07 | AL12: =IF(Assms!$F$37=1,LXtables!CF12,IF(Assms!$F$37=2,LXtables!CS12,IF(Assms!$F$37=3,LXtables!DF12,IF(Assms!$F$37=4,LXtables!DS12,IF(Assms!$F$37=5,LXtables!EF12,LXtables!ES12))))) -> 0.06 | AM12: =IF(Assms!$F$37=1,LXtables!CG12,IF(Assms!$F$37=2,LXtables!CT12,IF(Assms!$F$37=3,LXtables!DG12,IF(Assms!$F$37=4,LXtables!DT12,IF(Assms!$F$37=5,LXtables!EG12,LXtables!ET12))))) -> 0.06 | AN12: =IF(Assms!$F$37=1,LXtables!CH12,IF(Assms!$F$37=2,LXtables!CU12,IF(Assms!$F$37=3,LXtables!DH12,IF(Assms!$F$37=4,LXtables!DU12,IF(Assms!$F$37=5,LXtables!EH12,LXtables!EU12))))) -> 0.06 | AO12: =IF(Assms!$F$37=1,LXtables!CI12,IF(Assms!$F$37=2,LXtables!CV12,IF(Assms!$F$37=3,LXtables!DI12,IF(Assms!$F$37=4,LXtables!DV12,IF(Assms!$F$37=5,LXtables!EI12,LXtables!EV12))))) -> 0.06 | AP12: =IF(Assms!$F$37=1,LXtables!CJ12,IF(Assms!$F$37=2,LXtables!CW12,IF(Assms!$F$37=3,LXtables!DJ12,IF(Assms!$F$37=4,LXtables!DW12,IF(Assms!$F$37=5,LXtables!EJ12,LXtables!EW12))))) -> 0.06 | ... AT12: =IF(Assms!$F$37=1,LXtables!CN12,IF(Assms!$F$37=2,LXtables!DA12,IF(Assms!$F$37=3,LXtables!DN12,IF(Assms!$F$37=4,LXtables!EA12,IF(Assms!$F$37=5,LXtables!EN12,LXtables!FA12))))) -> 0.09 | AU12: 9 | AV12: =IF(Assms!$F$37=1,LXtables!FD12,IF(Assms!$F$37=2,LXtables!FQ12,IF(Assms!$F$37=3,LXtables!GD12,IF(Assms!$F$37=4,LXtables!GQ12,IF(Assms!$F$37=5,LXtables!HD12,LXtables!HQ12))))) -> 0.1 | AW12: =IF(Assms!$F$37=1,LXtables!FE12,IF(Assms!$F$37=2,LXtables!FR12,IF(Assms!$F$37=3,LXtables!GE12,IF(Assms!$F$37=4,LXtables!GR12,IF(Assms!$F$37=5,LXtables!HE12,LXtables!HR12))))) -> 0.1 | AX12: =IF(Assms!$F$37=1,LXtables!FF12,IF(Assms!$F$37=2,LXtables!FS12,IF(Assms!$F$37=3,LXtables!GF12,IF(Assms!$F$37=4,LXtables!GS12,IF(Assms!$F$37=5,LXtables!HF12,LXtables!HS12))))) -> 0.08 | AY12: =IF(Assms!$F$37=1,LXtables!FG12,IF(Assms!$F$37=2,LXtables!FT12,IF(Assms!$F$37=3,LXtables!GG12,IF(Assms!$F$37=4,LXtables!GT12,IF(Assms!$F$37=5,LXtables!HG12,LXtables!HT12))))) -> 0.07 | AZ12: =IF(Assms!$F$37=1,LXtables!FH12,IF(Assms!$F$37=2,LXtables!FU12,IF(Assms!$F$37=3,LXtables!GH12,IF(Assms!$F$37=4,LXtables!GU12,IF(Assms!$F$37=5,LXtables!HH12,LXtables!HU12))))) -> 0.07 | BA12: =IF(Assms!$F$37=1,LXtables!FI12,IF(Assms!$F$37=2,LXtables!FV12,IF(Assms!$F$37=3,LXtables!GI12,IF(Assms!$F$37=4,LXtables!GV12,IF(Assms!$F$37=5,LXtables!HI12,LXtables!HV12))))) -> 0.07 | BB12: =IF(Assms!$F$37=1,LXtables!FJ12,IF(Assms!$F$37=2,LXtables!FW12,IF(Assms!$F$37=3,LXtables!GJ12,IF(Assms!$F$37=4,LXtables!GW12,IF(Assms!$F$37=5,LXtables!HJ12,LXtables!HW12))))) -> 0.07 | BC12: =IF(Assms!$F$37=1,LXtables!FK12,IF(Assms!$F$37=2,LXtables!FX12,IF(Assms!$F$37=3,LXtables!GK12,IF(Assms!$F$37=4,LXtables!GX12,IF(Assms!$F$37=5,LXtables!HK12,LXtables!HX12))))) -> 0.07 | ... BG12: =IF(Assms!$F$37=1,LXtables!FO12,IF(Assms!$F$37=2,LXtables!GB12,IF(Assms!$F$37=3,LXtables!GO12,IF(Assms!$F$37=4,LXtables!HB12,IF(Assms!$F$37=5,LXtables!HO12,LXtables!IB12))))) -> 0.1 | BH12: 9 | BI12: =IF(Assms!$F$37=1,LXtables!IE12,IF(Assms!$F$37=2,LXtables!IR12,IF(Assms!$F$37=3,LXtables!JE12,IF(Assms!$F$37=4,LXtables!JR12,IF(Assms!$F$37=5,LXtables!KE12,LXtables!KR12))))) -> 0.13 | BJ12: =IF(Assms!$F$37=1,LXtables!IF12,IF(Assms!$F$37=2,LXtables!IS12,IF(Assms!$F$37=3,LXtables!JF12,IF(Assms!$F$37=4,LXtables!JS12,IF(Assms!$F$37=5,LXtables!KF12,LXtables!KS12))))) -> 0.12 | BK12: =IF(Assms!$F$37=1,LXtables!IG12,IF(Assms!$F$37=2,LXtables!IT12,IF(Assms!$F$37=3,LXtables!JG12,IF(Assms!$F$37=4,LXtables!JT12,IF(Assms!$F$37=5,LXtables!KG12,LXtables!KT12))))) -> 0.1 | BL12: =IF(Assms!$F$37=1,LXtables!IH12,IF(Assms!$F$37=2,LXtables!IU12,IF(Assms!$F$37=3,LXtables!JH12,IF(Assms!$F$37=4,LXtables!JU12,IF(Assms!$F$37=5,LXtables!KH12,LXtables!KU12))))) -> 0.08 | BM12: =IF(Assms!$F$37=1,LXtables!II12,IF(Assms!$F$37=2,LXtables!IV12,IF(Assms!$F$37=3,LXtables!JI12,IF(Assms!$F$37=4,LXtables!JV12,IF(Assms!$F$37=5,LXtables!KI12,LXtables!KV12))))) -> 0.08 | BN12: =IF(Assms!$F$37=1,LXtables!IJ12,IF(Assms!$F$37=2,LXtables!IW12,IF(Assms!$F$37=3,LXtables!JJ12,IF(Assms!$F$37=4,LXtables!JW12,IF(Assms!$F$37=5,LXtables!KJ12,LXtables!KW12))))) -> 0.08 | BO12: =IF(Assms!$F$37=1,LXtables!IK12,IF(Assms!$F$37=2,LXtables!IX12,IF(Assms!$F$37=3,LXtables!JK12,IF(Assms!$F$37=4,LXtables!JX12,IF(Assms!$F$37=5,LXtables!KK12,LXtables!KX12))))) -> 0.09 | BP12: =IF(Assms!$F$37=1,LXtables!IL12,IF(Assms!$F$37=2,LXtables!IY12,IF(Assms!$F$37=3,LXtables!JL12,IF(Assms!$F$37=4,LXtables!JY12,IF(Assms!$F$37=5,LXtables!KL12,LXtables!KY12))))) -> 0.09 | ... BT12: =IF(Assms!$F$37=1,LXtables!IP12,IF(Assms!$F$37=2,LXtables!JC12,IF(Assms!$F$37=3,LXtables!JP12,IF(Assms!$F$37=4,LXtables!KC12,IF(Assms!$F$37=5,LXtables!KP12,LXtables!LC12))))) -> 0.12
